Workbook

Sheet Truth snapshot
A1: Truth snapshot
A3: As of | B3: 05 Oct 2026
A4: What this workbook is | B4: The single source of truth for plan status, task status and test evidence. Anything not recorded here is not claimed.
A5: Code state | B5: All implementation is in the uncommitted working tree. Nothing is committed, merged or deployed.
A6: Test run | B6: Backend full suite on SQLite: 3082 passed, 0 failed, 35 skipped. Postgres-only concurrency tests are skipped on SQLite and have not been run since the changes. Web: vitest, tsc -b and ESLint are clean at the last full run.
A7: Plan items | B7: 68 items: 16 Built, 46 Partial, 6 Not built (judged against each item's own scope, from code and tests).
A8: Sign-off | B8: No item is Done. Review is In progress on every Built item: agent review has run, a human has not signed. Decision and external items (host, CA, pharmacist, gateway, devices) are not recorded.
A9: Code review | B9: 69 findings across two rounds: 59 fixed, 8 open, 2 reverted. See the Code review 2026-10-05 sheet.
A10: Freeze | B10: Live NIC e-way, GSTR-2B API, Tally and WhatsApp Cloud stay off. Built items for those are stubs or stored fields only.
A11: Before any deploy | B11: Set PLANWAVE_DATA_KEY and MFA_ENCRYPTION_KEY; run manage.py seal_bank_accounts once; start workers with -Q celery,high_priority,media_heavy,reports; apply migrations (planwave 0004, masters 0030, inventory 0026-0027, core 0051, sales 0063).
A12: Known open items | B12: COD cash receipts on routes, 206AB rates for company vendors, AA consent verification, WhatsApp opt-in source, wall-clock SLA tests, lower-severity web items, Postgres re-run of concurrency tests.

Sheet Founder view
A1: Founder view
A2: Live counts from the task register. A task is verified only when Verification result is Pass. That column is Not run until a test is linked. OS ready stays at zero until all five gates have evidence.
A3: Question | B3: Count | C3: How to read it
A4: Tasks | B4: =COUNTA(TaskRegister[Task ID]) -> 770 | C4: The frozen universe.
A5: MVP (current P0) | B5: =COUNTIF(TaskRegister[Release gate],"MVP") -> 102 | C5: Pilot scope to approve or cut. Release gate is not frozen until you sign it.
A6: Pilot (core P1, RUN or CONTROL) | B6: =COUNTIF(TaskRegister[Release gate],"Pilot") -> 447 | C6: Comes after MVP. This is a rule, not a target of 290.
A7: Later | B7: =COUNTIF(TaskRegister[Release gate],"Later") -> 221 | C7: Hidden from the pilot board. Still in the register.
A8: MVP with a passing test | B8: =COUNTIFS(TaskRegister[Release gate],"MVP",TaskRegister[Verification result],"Pass") -> 40 | C8: Go / no-go numerator. Threshold is a decision, not a formula.
A9: MVP with a test id | B9: =COUNTIFS(TaskRegister[Release gate],"MVP",TaskRegister[Test case ID],"<>") -> 94 | C9: Linked tests that have not been scored as a pass.
A10: Open gaps | B10: =COUNTIF(TaskRegister[Work status],"Gap") -> 92 | C10: Mechanism not found. Do not claim these.
A11: Built, only partly | B11: =COUNTIF(TaskRegister[Work status],"Built - partial") -> 256 | C11: The partial claims.
A12: Tasks with no owner | B12: =COUNTBLANK(TaskRegister[Owner]) -> 770 | C12: Fill owners on MVP rows first.
A13: Tasks with no test id | B13: =COUNTBLANK(TaskRegister[Test case ID]) -> 658 | C13: Validation status does not fill this.
A14: Tasks marked OS ready | B14: =COUNTIF(TaskRegister[OS ready],"Yes") -> 0 | C14: Stays at zero until G1 to G5 each have evidence.
A16: Four-week routine
A17: Week 1. Fill Decision owner and Decision date on P0 gap decisions. Approve or edit Proposed priority, then treat Release gate as frozen.
A18: Week 2. The compliance gaps stay open until someone builds them: admin second factor, a nightly invariant check with an alert, and an audit event test per posting action. This sheet does not mark them done.
A19: Week 3. Add one Test case ID per MVP task, money and stock and tax first. Set Verification result to Pass only when that test passes. Re-run the Postgres concurrency tests; they are still Not verified.
A20: Week 4. Fill Performance SLA actuals from a large-tenant seed, and Customer evidence from one pilot. Competitive targets stay hypotheses until then.
A22: Day to day
A23: Sprint planning | B23: Filter Task Register: Release gate = MVP, Work status = Gap or Built - unverified or Claimed - unverified, sort by Risk score.
A24: Pilot go / no-go | B24: MVP with a passing test, divided by MVP. Pick the threshold in the room. The sheet does not invent 90 percent.
A25: Due diligence | B25: Share P0 gap decisions, Security assurance, and Business integrity. The Not verified labels are the point.
A26: Hiring | B26: Role rollup names the area. Owner on the register names the person.
A27: Release notes | B27: Verification result = Pass. Validation status alone is an author or review label.

Sheet Pilot readiness
A1: Pilot readiness
A2: Three personas only, counted on Persona canonical so every distributor variant is included. Gate counts are MVP tasks with evidence for that gate. G4 and G5 are entered per task on Task Register. OS ready is a formula and needs all five gates.
A3: Persona (canonical) | B3: Tasks | C3: MVP tasks | D3: G1 functional | E3: G2 integrity | F3: G3 resilience and security | G3: G4 user validated | H3: G5 outcome | I3: All five gates (OS ready)
A4: Kirana / Small Retailer | B4: =COUNTIF(TaskRegister[Persona canonical],A4) -> 39 | C4: =COUNTIFS(TaskRegister[Persona canonical],$A4,TaskRegister[Release gate],"MVP") -> 6 | D4: =COUNTIFS(TaskRegister[Persona canonical],$A4,TaskRegister[Release gate],"MVP",TaskRegister[Verification result],"Pass") -> 3 | E4: =COUNTIFS(TaskRegister[Persona canonical],$A4,TaskRegister[Release gate],"MVP",TaskRegister[Integrity evidence],"<>Not verified") -> 0 | F4: =COUNTIFS(TaskRegister[Persona canonical],$A4,TaskRegister[Release gate],"MVP",TaskRegister[Recovery evidence],"<>Not verified",TaskRegister[Security evidence],"<>Not verified",TaskRegister[Concurrency evidence],"<>Not verified") -> 0 | G4: =COUNTIFS(TaskRegister[Persona canonical],$A4,TaskRegister[Release gate],"MVP",TaskRegister[G4 user validated],"Yes") -> 0 | H4: =COUNTIFS(TaskRegister[Persona canonical],$A4,TaskRegister[Release gate],"MVP",TaskRegister[G5 outcome measured],"Yes") -> 0 | I4: =COUNTIFS(TaskRegister[Persona canonical],$A4,TaskRegister[Release gate],"MVP",TaskRegister[OS ready],"Yes") -> 0
A5: Distributor | B5: =COUNTIF(TaskRegister[Persona canonical],A5) -> 37 | C5: =COUNTIFS(TaskRegister[Persona canonical],$A5,TaskRegister[Release gate],"MVP") -> 3 | D5: =COUNTIFS(TaskRegister[Persona canonical],$A5,TaskRegister[Release gate],"MVP",TaskRegister[Verification result],"Pass") -> 1 | E5: =COUNTIFS(TaskRegister[Persona canonical],$A5,TaskRegister[Release gate],"MVP",TaskRegister[Integrity evidence],"<>Not verified") -> 0 | F5: =COUNTIFS(TaskRegister[Persona canonical],$A5,TaskRegister[Release gate],"MVP",TaskRegister[Recovery evidence],"<>Not verified",TaskRegister[Security evidence],"<>Not verified",TaskRegister[Concurrency evidence],"<>Not verified") -> 0 | G5: =COUNTIFS(TaskRegister[Persona canonical],$A5,TaskRegister[Release gate],"MVP",TaskRegister[G4 user validated],"Yes") -> 0 | H5: =COUNTIFS(TaskRegister[Persona canonical],$A5,TaskRegister[Release gate],"MVP",TaskRegister[G5 outcome measured],"Yes") -> 0 | I5: =COUNTIFS(TaskRegister[Persona canonical],$A5,TaskRegister[Release gate],"MVP",TaskRegister[OS ready],"Yes") -> 0
A6: Accountant / Finance | B6: =COUNTIF(TaskRegister[Persona canonical],A6) -> 146 | C6: =COUNTIFS(TaskRegister[Persona canonical],$A6,TaskRegister[Release gate],"MVP") -> 17 | D6: =COUNTIFS(TaskRegister[Persona canonical],$A6,TaskRegister[Release gate],"MVP",TaskRegister[Verification result],"Pass") -> 9 | E6: =COUNTIFS(TaskRegister[Persona canonical],$A6,TaskRegister[Release gate],"MVP",TaskRegister[Integrity evidence],"<>Not verified") -> 0 | F6: =COUNTIFS(TaskRegister[Persona canonical],$A6,TaskRegister[Release gate],"MVP",TaskRegister[Recovery evidence],"<>Not verified",TaskRegister[Security evidence],"<>Not verified",TaskRegister[Concurrency evidence],"<>Not verified") -> 0 | G6: =COUNTIFS(TaskRegister[Persona canonical],$A6,TaskRegister[Release gate],"MVP",TaskRegister[G4 user validated],"Yes") -> 0 | H6: =COUNTIFS(TaskRegister[Persona canonical],$A6,TaskRegister[Release gate],"MVP",TaskRegister[G5 outcome measured],"Yes") -> 0 | I6: =COUNTIFS(TaskRegister[Persona canonical],$A6,TaskRegister[Release gate],"MVP",TaskRegister[OS ready],"Yes") -> 0
A8: Why these three | B8: Kirana owner, distributor, and accountant are the first pilot desks. Other personas stay in the register and are not in this go / no-go.

Sheet P0 gap decisions
A1: Open gap decisions
A2: One row per open or corrected claim, P0 first. Recommended decision is a proposal from the 2026-10-04 review. A decision owner and date must be entered by the founder.
A3: Task ID | B3: Claim | C3: Priority | D3: Status now | E3: Evidence checked | F3: Recommended decision | G3: Needs freeze exception | H3: Target release | I3: Decision | J3: Decision owner | K3: Decision date
A4: P-0115 | B4: Maintain an audit trail | C4: P0 | D4: Partial | E4: Hash chain and append-only guard exist. Coverage of every transaction type is not shown. | F4: Ship the gap: list every posting action, assert each writes an AuditEvent, add one test per action. | G4: Yes - compliance | H4: MVP | I4: Build in MVP (3 days) | J4: Founder (delegated to Claude) | K4: 46299 | L4: Status now (2026-10-05)
A5: X-0432 | B5: Critical transaction to immutable audit trail | C5: P0 | D5: Partial | E5: Same evidence as P-0115. | F5: Ship with P-0115. Close both together. | G5: Yes - compliance | H5: MVP | I5: Build in MVP (with P-0115) | J5: Founder (delegated to Claude) | K5: 46299 | L5: WI-002: Built and tests pass. Human review pending.
A6: P-0507 | B6: MCA Rule 11(g) immutable audit trail | C6: P0 | D6: Partial | E6: Hash chain exists. Rule 11(g) needs an edit log on every accounting record. Mapping not verified. | F6: Have the CA map Rule 11(g) to AuditEvent coverage. Ship any missing edit-log events. | G6: Yes - compliance | H6: MVP | I6: Build in MVP (2 days, CA sign-off) | J6: Founder (delegated to Claude) | K6: 46299 | L6: WI-003: Partial. Missing: Coverage map and certification export exist, but the export does not list the periods logging was on (it returns logging_on=True or refuses). Nothing writes LoggingWindow rows automatically. No edit log (before/after) on every accounting record, only per-action audit events. No test asserts every AUDIT_COVERAGE event is actually emitted.. Human review pending.
A7: S-0561 | B7: Background trial balance zero-sum worker | C7: P0 | D7: Partial | E7: check_invariants management command and trial_balance_balanced exist. No scheduled worker found. | F7: Re-scope to: schedule check_invariants nightly and alert on failure. Do not build a new worker. | G7: Yes - integrity | H7: MVP | I7: Build in MVP (3 days): full worker with quarantine | J7: Founder (delegated to Claude) | K7: 46299 | L7: WI-005: Partial. Missing: No invariant for payment allocations within payment amounts; no registered invariant for ledger output tax equals invoice tax (only a one-off test); AR/AP control vs outstanding only as dashboard-vs-aging projection checks; quarantine block wired to GST soft-close and GSTR export but not to accounting period lock; ops mailbox is only a log line; no test that the nightly run creates the quarantine row end to end; test_plan_s_0561.py absent.. Human review pending.
A8: S-0579 | B8: Cryptographic hash chain on audit trail | C8: P0 | D8: Code Complete & Verified | E8: Built and tested. Sealing is a nightly batch, so recent events sit in a window. | F8: Close as built after confirming the nightly seal is scheduled in production. | G8: No | H8: MVP | I8: Close as built after confirming the nightly seal runs in production, then add a monitoring alert | J8: Founder (delegated to Claude) | K8: 46299 | L8: WI-034: Partial. Missing: No drill log in qos/evidence; the task-level gap path (running seal_audit_chain_task with a stale heartbeat) is not tested directly.. Human review pending.
A9: C-0603 | B9: Section 16(4) time-barring alert and ITC exclusion engine | C9: P0 | D9: Partial | E9: Deadline clock, flags and alert exist and test. No exclusion engine. | F9: Ship the alert as the pilot answer. Defer the exclusion engine to GA unless a pilot customer needs it. | G9: Yes if pulled into pilot | H9: Pilot | I9: Build in MVP (3 days): alert tiers and exclusion engine | J9: Founder (delegated to Claude) | K9: 46299 | L9: WI-017: Partial. Missing: 60 and 7 day warnings only fire when someone POSTs /plan/itc/summary/; no scheduled task; DUE_60/DUE_7 statuses and alert sending are untested; test_plan_c_0603.py absent.. Human review pending.
A10: SEC-0624 | B10: TOTP 2FA for admin roles | C10: P0 | D10: Partial | E10: TOTP, recovery codes and encrypted secrets exist and test. Opt-in only. | F10: Make 2FA mandatory for admin and owner roles. Small change on top of existing code. | G10: Yes - security | H10: MVP | I10: Build in MVP (1.5 days) | J10: Founder (delegated to Claude) | K10: 46299 | L10: WI-010: Built and tests pass. Human review pending.
A11: GOS-0721 | B11: Inbound lead exact-match deduplication | C11: P0 | D11: Code Complete & Verified | E11: Growth OS claim. Name found in code. | F11: Add one end-to-end test and move to Validated. | G11: No | H11: Pilot | I11: Add end-to-end test and validate before Pilot | J11: Founder (delegated to Claude) | K11: 46299 | L11: WI-047: Built and tests pass. Human review pending.
A12: GOS-0737 | B12: Complaint to credit note, return or replacement | C12: P0 | D12: Code Complete & Verified | E12: Growth OS claim. Name found in code. | F12: Add one end-to-end test with stock and ledger check, then validate. | G12: No | H12: Pilot | I12: Add end-to-end test with stock and ledger check, validate before Pilot | J12: Founder (delegated to Claude) | K12: 46299 | L12: WI-048: Partial. Missing: Tests work from draft invoices and assert no stock movement or ledger/journal effect; credit note exactly-once is asserted (second POST returns the same id); test_plan_gos_0737.py absent.. Human review pending.
A13: GOS-0739 | B13: Supplier complaint to purchase debit note | C13: P0 | D13: Code Complete & Verified | E13: Growth OS claim. Name found in code. | F13: Same as GOS-0737. | G13: No | H13: Pilot | I13: Add end-to-end test with stock and ledger check, validate before Pilot | J13: Founder (delegated to Claude) | K13: 46299 | L13: WI-049: Partial. Missing: Complaint to draft debit note flow is tested end to end, but there is no stock-movement or ledger assertion: the note is set COMPLETED by direct save, not through the completion service. backend/tests/test_plan_gos_0739.py does not exist.. Human review pending.
A14: C-0614 | B14: Section 206AB / 206CCA PAN utility check | C14: P1 | D14: Mechanism not found | E14: Not in code. | F14: Defer. Pilot customers verify non-filers manually. Record the risk. | G14: No | H14: GA | I14: Build in GA (3 days): PAN utility check | J14: Founder (delegated to Claude) | K14: 46299 | L14: No plan item maps to this task.
A15: X-0522 | B15: Higher TDS/TCS rate for non-filers | C15: P1 | D15: Mechanism not found | E15: Not in code. Depends on C-0614. | F15: Defer with C-0614. | G15: No | H15: GA | I15: Build in GA (2 days, with C-0614) | J15: Founder (delegated to Claude) | K15: 46299 | L15: No plan item maps to this task.
... A23: UX-0591 | B23: Privacy mask for rupee figures | C23: P3 | D23: Mechanism not found | E23: Not found. | F23: Defer to GA. | G23: No | H23: GA | I23: Build in Pilot (1 day) | J23: Founder (delegated to Claude) | K23: 46299 | L23: WI-057: Partial. Missing: No test; only components using MoneyText are masked, other rupee displays may not be.. Human review pending.

Sheet MVP scope after review
A1: MVP scope after review
A2: MVP tasks that the code review found Partial or absent. Each needs a decision before the pilot: cut it from MVP, build it, or accept and document the limit.
A3: Task ID | B3: Task | C3: Capability class | D3: Work status | E3: Review verdict | F3: What the code shows | G3: Options | H3: Decision | I3: Decision owner | J3: Effort (days) | K3: Why / what quality means | L3: Status now (2026-10-05)
A4: P-0046 | B4: Search medicines while billing | C4: Core | D4: Built - partial | E4: Partial | F4: Product search matches name, SKU, barcode, HSN and custom fields; no native salt/composition or manufacturer field. | G4: Cut from MVP, build, or accept the limit | H4: Build in Pilot | I4: Founder (delegated to Claude) | J4: 2 | K4: Native salt/composition and manufacturer fields, searchable at billing. | L4: WI-036: Partial. Missing: No test searches by salt, composition or manufacturer; no query-budget test within the checkout latency budget.. Human review pending.
A5: P-0052 | B5: Create bulk sales invoices | C5: Core | D5: Built - partial | E5: Partial | F5: Invoices apply price lists and post stock, AR and GST; bulk CSV entry for invoices not found. | G5: Cut from MVP, build, or accept the limit | H5: Build in Pilot | I5: Founder (delegated to Claude) | J5: 4 | K5: Bulk invoice CSV import with validation and per-row errors. | L5: WI-037: Partial. Missing: CSV columns for invoice date and due date, barcode lookup and warehouse are not handled (SKU only, no warehouse or dates). The 2,000-row cap is not tested. Idempotent re-upload is not asserted after a committed run.. Human review pending.
A6: P-0081 | B6: Transfer stock between godowns | C6: Core | D6: Built - partial | E6: Partial | F6: Transfers exist with DRAFT/COMPLETED/CANCELLED only; no dispatch, in-transit, insurance or separate receipt confirmation stages. | G6: Cut from MVP, build, or accept the limit | H6: Build in Pilot | I6: Founder (delegated to Claude) | J6: 6 | K6: Dispatch, in-transit and receipt-confirmation stages for stock transfers. | L6: WI-038: Built and tests pass. Human review pending.
A7: P-0089 | B7: View all shops from one dashboard | C7: Core | D7: Built - partial | E7: Partial | F7: Dashboard shows company-wide totals over all godowns; no outlet switching or per-outlet breakdown found. | G7: Cut from MVP, build, or accept the limit | H7: Build in Pilot | I7: Founder (delegated to Claude) | J7: 5 | K7: Per-outlet breakdown and outlet switching on the dashboard. | L7: WI-039: Partial. Missing: Only an API listing on-hand and reserved stock per warehouse; no web DashboardPage integration or warehouse switching; no query-budget test.. Human review pending.
A8: P-0115 | B8: Maintain an audit trail | C8: Core | D8: Built - partial | E8: Partial | F8: Immutable hash-chained AuditEvent log exists, but it has no IP or before/after value columns and no simple_history; per-transaction coverage is unproven. | G8: Cut from MVP, build, or accept the limit | H8: Build in MVP | I8: Founder (delegated to Claude) | J8: 3 | K8: Audit event on every posting action (journal post, purchase complete with books off included); add IP and before/after values; one test per action; drop the xfail. | L8: WI-001: Built and tests pass. Human review pending.
A9: P-0119 | B9: Identify overdue payments | C9: Core | D9: Built - partial | E9: Partial | F9: Overdue invoices with days_overdue and collection worklist exist; no interest exposure or bad-debt risk calculation. | G9: Cut from MVP, build, or accept the limit | H9: Build in Pilot | I9: Founder (delegated to Claude) | J9: 3 | K9: Interest exposure and bad-debt risk on overdue customers. | L9: WI-040: Built and tests pass. Human review pending.
A10: P-0128 | B10: Approve important business actions | C10: Core | D10: Built - partial | E10: Partial | F10: Owner credit-limit and GST-guard overrides record who and why, but no general pending-approval queue or approve/reject workflow exists. | G10: Cut from MVP, build, or accept the limit | H10: Build in MVP | I10: Founder (delegated to Claude) | J10: 5 | K10: General pending-approval queue with approve and reject and an audit trail. | L10: WI-025: Partial. Missing: The approval queue is enforced only for invoice cancel and large stock adjustment; not wired for credit-limit override (separate unlock), invoice amend, discount, returns/credit notes, backdating/period reopen, supplier payment, write-off or bulk import commit; no per-action configurable approver; no web UI.. Human review pending.
A11: P-0152 | B11: Adjust stock with authorization | C11: Core | D11: Built - partial | E11: Partial | F11: Adjustment needs a mandatory reason and inventory-manage permission and posts ADJUSTMENT; no dual-approval workflow. | G11: Cut from MVP, build, or accept the limit | H11: Build in MVP | I11: Founder (delegated to Claude) | J11: 2 | K11: Dual approval for stock adjustments above a threshold, on the approval queue. | L11: WI-026: Built and tests pass. Human review pending.
A12: P-0180 | B12: Configure branches/godowns | C12: Core | D12: Built - partial | E12: Partial | F12: Warehouse has name, code, address and default flag; no contact fields or user-to-location mapping. | G12: Cut from MVP, build, or accept the limit | H12: Build in Pilot | I12: Founder (delegated to Claude) | J12: 2 | K12: Contact fields and user-to-location mapping on warehouses. | L12: WI-041: Partial. Missing: Contact name and phone are blank=True (not required); the user-to-warehouse mapping is stored but nothing enforces or reads it; no test covers the mapping or the default rule.. Human review pending.
A13: X-0432 | B13: Critical transaction → immutable audit trail exists | C13: Core | D13: Built - partial | E13: Partial | F13: AuditEvent is hash-chained and guarded against update/delete, but coverage of every critical transaction is not shown and SimpleHistory is not used. | G13: Cut from MVP, build, or accept the limit | H13: Build in MVP | I13: Founder (delegated to Claude) | J13: 0 | K13: Delivered with P-0115. | L13: WI-002: Built and tests pass. Human review pending.
A14: P-0503 | B14: Audit 2A/2B vs Books reconciliation and verify eligible vs blocked ITC | C14: Core | D14: Built - partial | E14: Partial | F14: 2B matching and eligible/ineligible flags exist, but no Section 17(5) blocked-credit classification. | G14: Cut from MVP, build, or accept the limit | H14: Build in MVP | I14: Founder (delegated to Claude) | J14: 3 | K14: Section 17(5) blocked-credit classification in the 2A/2B reconciliation. | L14: WI-019: Partial. Missing: Blocked-credit classification is not added to the existing reporting/gstr2b.py reconciliation of uploaded 2B files; it only scores caller-supplied rows via /plan/gstr2b/score/ with a caller-supplied blocked_credit flag.. Human review pending.
A15: P-0507 | B15: Audit MCA mandated immutable audit trail (Rule 11(g) Companies Audit Rules) | C15: Core | D15: Built - partial | E15: Partial | F15: Hash-chained audit events with verify exist; not django-simple-history, and no certification report or Rule 11(g) coverage of all records. | G15: Cut from MVP, build, or accept the limit | H15: Build in MVP | I15: Founder (delegated to Claude) | J15: 2 | K15: Rule 11(g) coverage map signed off by the CA, edit log on every accounting record, certification export. | L15: WI-003: Partial. Missing: Coverage map and certification export exist, but the export does not list the periods logging was on (it returns logging_on=True or refuses). Nothing writes LoggingWindow rows automatically. No edit log (before/after) on every accounting record, only per-action audit events. No test asserts every AUDIT_COVERAGE event is actually emitted.. Human review pending.
... A49: X-0715 | B49: Customer changes legal name and registered address: system updates master while preserving historical invoices | C49: Core | D49: Built - partial | E49: Partial | F49: Only GSTIN and place of supply are frozen at completion; customer name and address are read live so history can change. | G49: Cut from MVP, build, or accept the limit | H49: Build in MVP | I49: Founder (delegated to Claude) | J49: 2 | K49: Snapshot customer name and address on the invoice at completion; backfill existing invoices. | L49: WI-014: Partial. Missing: Backfill copies current master data and does not use the audit-history name as of the invoice date; snapshot tests cover sales invoices only, not credit/debit notes or purchase bills.. Human review pending.

Sheet Plan guide
A1: Implementation plan: guide
A2: How the plan is built, what each column means and how to keep it current.
A4: Plan start (Monday) | B4: 46307
A5: Agent lanes assumed | B5: 2
A6: Contingency buffer | B6: 0.2
A7: Working days per week | B7: 5
A10: What this is | B10: One row per piece of work for the quality-first decisions of 2026-10-04. Revised after the 63 pre-implementation questions: see the Plan decisions sheet for every answer and what it changed. Each row has five stages (Design, Build, Tests, Review, Register sync); Status, percent done, days late and RAG are formulas driven by the stage cells and actual dates.
A11: Team assumption | B11: One human owner plus agents (default; confirm). Two agent lanes run in parallel only on independent items, each in its own git worktree and Postgres database. Decisions and external reviews sit outside the lanes. Change LANES in build_plan.py if the real team is different.
A12: Dates | B12: Scheduled for the lanes above, Monday to Friday, skipping these holidays: 20 Oct 2026, 09 Nov 2026, 11 Nov 2026, 24 Nov 2026, 25 Dec 2026, 26 Jan 2027. Each estimate carries a 20% buffer, each dependency leaves one clear day for review, and each milestone adds one week before it is called. Dates are fixed text; re-run qos/evidence/build_plan.py to reschedule.
A13: Waves | B13: Wave 1 = Build in MVP, wave 2 = Build in Pilot, wave 3 = Build in GA. Every wave 2 item depends on VER-1 and every wave 3 item on VER-2, so a later wave never starts before the earlier gate closes.
A14: Freeze | B14: The plan does not override docs/FREEZE_SCOPE.md. Live NIC e-way, GSTR-2B API, Tally and WhatsApp Cloud stay behind their flags, default off, and are built against fakes and offline inputs. Flipping a flag is a separate freeze exception.
A15: What you edit | B15: Only the cream cells: Owner, the five stage cells, Actual start, Actual done, Blocked reason, PR / branch and Evidence.
A16: Stage values | B16: Not started, In progress, Done, Blocked, N/A. Use N/A when a stage does not apply.
A17: Definition of done | B17: An item is Done when all five stages are Done or N/A. What each stage means depends on the item's Kind (column AG): see the Acceptance criteria column, which states the item's own pass condition, its rejecting case and the done rule for its kind. Features: tests for the touched apps on Postgres, lint and types clean, register_sync scores the test. Web: Vitest or Playwright, tsc -b, ESLint, accessibility check. Performance: benchmark job report. Drill: recorded timings. Decision and external: recorded decision or written sign-off. Gate: checklist.
A18: Reviewer rule | B18: The author never signs their own Review. Agent-built work gets an agent code-review pass, then the human signs. Human-built work gets an agent review, then the human signs after a day. Compliance items also need the CA; pharmacy items a licensed pharmacist.
A19: When tests run | B19: Each pull request: tests for the touched apps plus lint and type checks. Full backend suite on Postgres: nightly and at each verification gate. Performance and load tests: their own scheduled job, never in the pull-request run.
A20: Source of truth | B20: Bizboard_Product_Task_Universe_Master.xlsx is the source of truth and the file register_sync.py updates. Bizboard_Master_Task_Register_Enhanced.xlsx is a mirror written by recalc_xlsx.ps1 -Mirror. Archives are read-only.
A21: Other plans | B21: Production bugs jump the queue, capped at 20% of capacity, and each interrupt is logged in Plan change log. This plan preempts the bug-remediation, UX, FMEA and ISO 25010 plans for new work; items there that duplicate a work item here are merged into it.
... A25: Weekly routine | B25: Monday: set stages and actual dates, record blockers, rerun register_sync.py after a test run, recalculate the workbook (qos/tools/recalc_xlsx.ps1), review Plan rollup and Plan by week, and log any date or scope change in Plan change log.

Sheet Plan decisions
A1: Plan decisions: the 63 pre-implementation questions
A2: Status: Decided = settled here; Confirm = default chosen, founder confirms before the item starts; External = needs a CA, pharmacist, host or other outside input; Dropped = removed from the plan.
A4: Q | B4: Topic | C4: Items | D4: Status | E4: Answer | F4: What changed in the plan | G4: Founder confirmed (date)
A5: 1 | B5: Team and parallelism | C5: All | D5: Confirm | E5: Plan for one human owner plus agents. Two agent lanes run in parallel only on independent items, each in its own git worktree and its own Postgres database. The human decides, reviews and signs. Start moves to Monday 12 Oct 2026, not 5 Oct. If the real team is larger, change DEVS in build_plan.py and regenerate. | F5: Developers 3 to 2 lanes; start 12 Oct; owners Agent 1, Agent 2, Human reviewer.
A6: 2 | B6: Feature freeze | C6: WI-027, 029-032, 060, 061 | D6: Decided | E6: The plan does not override the freeze. Everything touching live NIC, GSTR-2B API, Tally and WhatsApp Cloud is built behind its existing flag, default off, against a fake adapter and offline inputs. Flipping a flag is a separate freeze exception and is not part of any item. WI-027 becomes an in-app token; WI-029-031 become stub actions plus stored fields; WI-032 computes validity from entered distance only; PIN-to-PIN lookup is deferred. | F6: Scope of WI-027, 029, 030, 031, 032, 060, 061 rewritten; flags stay off.
A7: 3 | B7: Second reviewer | C7: All | D7: Confirm | E7: Rule: the author never signs their own Review. Agent-built work gets an agent code-review pass first, then the human signs. Human-built work gets an agent review, then the human signs after a day's gap. Compliance items also need the CA, pharmacy items a licensed pharmacist. If you want a named human second reviewer, add them as Owner on the Review stage. | F7: Definition of done: reviewer rule added to Plan guide.
A8: 4 | B8: Source-of-truth workbook | C8: All | D8: Decided | E8: Bizboard_Product_Task_Universe_Master.xlsx is the source of truth and the file register_sync.py updates by default. Bizboard_Master_Task_Register_Enhanced.xlsx is a mirror written by recalc_xlsx.ps1 -Mirror. Archives are read-only. The _UPDATED file is renamed over the Master once Excel releases it. | F8: Plan guide states the rule.
A9: 5 | B9: Other open plans | C9: All | D9: Decided | E9: Production bugs jump the queue, capped at 20% of capacity, and each interrupt is logged in the change log. This plan preempts the bug-remediation, UX, FMEA and ISO 25010 plans for new work, but any item in those plans that duplicates a work item here is merged into it rather than done twice. | F9: 20% interrupt allowance noted in Plan guide.
A10: 6 | B10: Postgres host and backup keys | C10: WI-007 | D10: External | E10: Recommended default: managed Postgres in an India region with built-in point-in-time recovery, RPO 5 minutes, RTO 1 hour for the pilot. Backup encryption keys live in the provider's key service, administered by the founder, with a sealed break-glass copy held separately. WI-007 cannot be designed until you pick the provider, so a new decision item DEC-HOST comes first and WI-007 depends on it. | F10: New item DEC-HOST (owner Founder); WI-007 depends on it.
A11: 7 | B11: Chartered accountant for Rule 11(g) | C11: WI-003, 004 | D11: External | E11: Build the coverage map now and sign later. A new external item CA-SIGN follows WI-003. If no CA is named by 2 Nov 2026, M1 still closes technically but is marked 'pilot with documented residual: Rule 11(g) sign-off pending'. The same CA reviews the tax rule tables in WI-016 to WI-020, so a new item DEC-CA (engage the CA) precedes them. | F11: New items DEC-CA and CA-SIGN.
A12: 8 | B12: Item-specific pass conditions | C12: All | D12: Decided | E12: Every item now has its own pass condition and rejecting case, written in the plan, and the definition of done depends on the item's kind: feature, web, performance, infrastructure drill, decision or process gate. The four pasted lines are gone. | F12: Acceptance criteria rewritten per item; new Kind column.
A13: 9 | B13: Frontend tests and register sync | C13: WI-043, 052-057 | D13: Decided | E13: Web items are done on Vitest component tests, a Playwright flow where there is a flow, tsc -b, ESLint with zero errors and an accessibility check. They do not need the backend suite. register_sync.py is extended to read Vitest and Playwright JUnit output (new item REG-WEB, first in the plan), and web test references become real file paths. | F13: New item REG-WEB; web items depend on it; test globs replaced with files.
A14: 10 | B14: WI-002 and WI-004 | C14: WI-002, 004 | D14: Decided | E14: Yes. Their remaining work is Review plus the register update. Evidence is the parent item's tests (WI-001 and WI-003). Design, Build and Tests stay N/A. | F14: Done condition for these items: parent Done and register row updated.
A15: 11 | B15: Items with no register task | C15: WI-033, 035, 058, 067 | D15: Decided | E15: Verification gates have no register row and are done when their checklist passes. WI-033 gets a new register row (next free X- number) created when the item starts, so it can be scored. | F15: Done condition by kind; WI-033 gets a register row at start.
A16: 12 | B16: Test file for SEC-0624 | C16: WI-010 | D16: Decided | E16: The existing test_mfa.py stays as the regression base. A new test_mfa_mandatory.py covers enforcement and first-login enrolment. The strict xfail test in test_register_integrity_gaps.py becomes a normal passing test. WI-005 keeps test_register_integrity_gaps.py for the invariant tests only. | F16: Planned test files corrected.
... A67: 63 | B67: Section 171 anti-profiteering | C67: WI-066 | D67: Dropped | E67: Dropped from the plan, kept in the register as On request, because enforcement has been wound down as far as I know. CA to confirm. If it comes back: count rate-cut notifications as events, with the last price before the cut as the baseline. | F67: WI-066 removed.

Sheet Implementation plan
A1: Implementation plan
A2: One row per work item. Cream cells are inputs; everything else is a formula or fixed plan text. Filter on Wave, Owner, Status, RAG or Kind.
A4: WI ID | B4: Register task | C4: Work item | D4: Wave | E4: Release gate | F4: Workstream | G4: Layer | H4: Scope (quality-first) | I4: Acceptance criteria | J4: Planned test file | K4: Depends on | L4: Owner | M4: Estimate (days) | N4: Planned days (with buffer) | O4: Planned start | P4: Planned due | Q4: Design | R4: Build | S4: Tests | T4: Review | U4: Register sync | V4: Status | W4: % done | X4: Actual start | Y4: Actual done | Z4: Days late | AA4: RAG | AB4: Blocked reason | AC4: PR / branch | AD4: Evidence (test ids, run id) | AE4: Register work status | AF4: Register verification | AG4: Kind | AH4: Cut line | AI4: Decision refs (Q) | AJ4: Plan key
A5: WI-068 | C5: Extend register_sync.py to score Vitest and Playwright results | D5: 1 | E5: MVP | F5: Platform & reliability | G5: Tooling | H5: Parse Vitest and Playwright JUnit, map web test file paths to register rows, unit-test the parser against real output. | I5: Pass: register_sync.py scores Vitest and Playwright results onto register rows. Rejecting case: A web test that fails marks its row Fail; an unknown path is reported as unmatched. Done means: the tool runs on real output from the suites, its parser has unit tests, and the reviewer signs. | J5: qos/tools/tests/test_register_sync_web.py | L5: Agent 1 | M5: 1 | N5: =ROUNDUP(M5*(1+'Plan guide'!$B$6),0) -> 2 | O5: 46307 | P5: 46308 | Q5: Done | R5: Done | S5: In progress | T5: In progress | U5: Not started | V5: =IF(COUNTIF(Q5:U5,"Blocked")>0,"Blocked",IF(COUNTIF(Q5:U5,"Done")+COUNTIF(Q5:U5,"N/A")=5,"Done",IF(COUNTIF(Q5:U5,"Done")+COUNTIF(Q5:U5,"In progress")>0,"In progress","Not started"))) -> In progress | W5: =IF(5-COUNTIF(Q5:U5,"N/A")=0,1,COUNTIF(Q5:U5,"Done")/(5-COUNTIF(Q5:U5,"N/A"))) -> 0.4 | Z5: =IF(V5="Done",IF(Y5="",0,MAX(0,Y5-P5)),MAX(0,TODAY()-P5)) -> 0 | AA5: =IF(V5="Done","Done",IF(V5="Blocked","Red",IF(Z5>0,"Red",IF(AND(O5<=TODAY(),P5-TODAY()<=3,W5<0.5),"Amber","Green")))) -> Green | AB5: Agent review done; human sign-off pending | AC5: uncommitted working tree | AD5: Tests: qos/tools/tests/test_register_sync_web.py::test_parser_reads_pytest_vitest_and_playwright [not in run]; qos/tools/tests/test_register_sync_web.py::test_failed_web_test_marks_the_row_fail_and_unknown_path_is_unmatched [not in run] | Code: qos/tools/register_sync.py:load_junit; qos/tools/register_sync.py:merge_junit | Run: pytest on SQLite 2026-10-05 (Postgres-only tests skipped) | AG5: tooling | AI5: 9 | AJ5: REG-WEB
A6: WI-069 | C6: Decide Postgres host, RPO/RTO and backup-key custody | D6: 1 | E6: MVP | F6: Platform & reliability | G6: Process | H6: Founder chooses the provider (default: managed Postgres in an India region with point-in-time recovery), confirms RPO 5 min and RTO 1 h, and names the key administrator. | I6: Pass: Provider, RPO, RTO and key administrator recorded. Rejecting case: S-0570 does not start until this is recorded. Done means: the decision is recorded in the Plan decisions sheet with date and owner. | L6: Founder | M6: 0.5 | N6: =ROUNDUP(M6*(1+'Plan guide'!$B$6),0) -> 1 | O6: 46307 | P6: 46307 | Q6: Not started | R6: N/A | S6: N/A | T6: Not started | U6: N/A | V6: =IF(COUNTIF(Q6:U6,"Blocked")>0,"Blocked",IF(COUNTIF(Q6:U6,"Done")+COUNTIF(Q6:U6,"N/A")=5,"Done",IF(COUNTIF(Q6:U6,"Done")+COUNTIF(Q6:U6,"In progress")>0,"In progress","Not started"))) -> Not started | W6: =IF(5-COUNTIF(Q6:U6,"N/A")=0,1,COUNTIF(Q6:U6,"Done")/(5-COUNTIF(Q6:U6,"N/A"))) -> 0 | Z6: =IF(V6="Done",IF(Y6="",0,MAX(0,Y6-P6)),MAX(0,TODAY()-P6)) -> 0 | AA6: =IF(V6="Done","Done",IF(V6="Blocked","Red",IF(Z6>0,"Red",IF(AND(O6<=TODAY(),P6-TODAY()<=3,W6<0.5),"Amber","Green")))) -> Green | AB6: Gap: No file records the provider choice, RPO 5 min / RTO 1 h confirmation or key administrator; the plan only states a recommended default. | AC6: uncommitted working tree | AD6: Run: pytest on SQLite 2026-10-05 (Postgres-only tests skipped) | AG6: decision | AI6: 6 | AJ6: DEC-HOST
A7: WI-070 | C7: Engage a chartered accountant for Rule 11(g) and the tax rule tables | D7: 1 | E7: MVP | F7: GST & compliance | G7: Process | H7: Name the CA and agree the review scope: Rule 11(g) coverage, s.16(2), s.16(4), s.17(5), s.50 tables, e-way validity slabs, bad-debt buckets. | I7: Pass: CA named and review scope agreed in writing. Rejecting case: Tax rule items do not close without CA review. Done means: the decision is recorded in the Plan decisions sheet with date and owner. | L7: Founder | M7: 0.5 | N7: =ROUNDUP(M7*(1+'Plan guide'!$B$6),0) -> 1 | O7: 46307 | P7: 46307 | Q7: Not started | R7: N/A | S7: N/A | T7: Not started | U7: N/A | V7: =IF(COUNTIF(Q7:U7,"Blocked")>0,"Blocked",IF(COUNTIF(Q7:U7,"Done")+COUNTIF(Q7:U7,"N/A")=5,"Done",IF(COUNTIF(Q7:U7,"Done")+COUNTIF(Q7:U7,"In progress")>0,"In progress","Not started"))) -> Not started | W7: =IF(5-COUNTIF(Q7:U7,"N/A")=0,1,COUNTIF(Q7:U7,"Done")/(5-COUNTIF(Q7:U7,"N/A"))) -> 0 | Z7: =IF(V7="Done",IF(Y7="",0,MAX(0,Y7-P7)),MAX(0,TODAY()-P7)) -> 0 | AA7: =IF(V7="Done","Done",IF(V7="Blocked","Red",IF(Z7>0,"Red",IF(AND(O7<=TODAY(),P7-TODAY()<=3,W7<0.5),"Amber","Green")))) -> Green | AB7: Gap: No file records a named CA or an agreed review scope. | AC7: uncommitted working tree | AD7: Run: pytest on SQLite 2026-10-05 (Postgres-only tests skipped) | AG7: decision | AI7: 7 | AJ7: DEC-CA
A8: WI-001 | B8: P-0115 | C8: Maintain an audit trail | D8: 1 | E8: MVP | F8: Audit & integrity | G8: Backend | H8: Audit event with actor, IP and before/after values on: sales invoice complete, cancel, amend; sales return; credit and debit notes; purchase invoice complete (books on and off); purchase return; customer receipt; supplier payment; journal post and reverse; stock adjustment, transfer, goods receipt; payroll finalise; period lock and reopen. One test per action; remove the xfails. | I8: Pass: Every action in the scope list writes exactly one AuditEvent with actor, IP and before/after; the chain verifies. Rejecting case: A journal post or a purchase complete with books off that writes no event fails its test (the current xfails); a tampered event fails verification. Done means: tests for the touched apps pass on Postgres 17 with lint and type checks clean and any strict xfail for the item removed; the reviewer (not the author) signs; register_sync.py scores the test and the register row reads Built - tested / Pass; the full suite runs nightly and at the wave gate. | J8: backend/tests/test_register_audit_coverage.py | L8: Agent 2 | M8: 3 | N8: =ROUNDUP(M8*(1+'Plan guide'!$B$6),0) -> 4 | O8: 46307 | P8: 46310 | Q8: Done | R8: Done | S8: Done | T8: In progress | U8: Done | V8: =IF(COUNTIF(Q8:U8,"Blocked")>0,"Blocked",IF(COUNTIF(Q8:U8,"Done")+COUNTIF(Q8:U8,"N/A")=5,"Done",IF(COUNTIF(Q8:U8,"Done")+COUNTIF(Q8:U8,"In progress")>0,"In progress","Not started"))) -> In progress | W8: =IF(5-COUNTIF(Q8:U8,"N/A")=0,1,COUNTIF(Q8:U8,"Done")/(5-COUNTIF(Q8:U8,"N/A"))) -> 0.8 | Z8: =IF(V8="Done",IF(Y8="",0,MAX(0,Y8-P8)),MAX(0,TODAY()-P8)) -> 0 | AA8: =IF(V8="Done","Done",IF(V8="Blocked","Red",IF(Z8>0,"Red",IF(AND(O8<=TODAY(),P8-TODAY()<=3,W8<0.5),"Amber","Green")))) -> Green | AB8: Agent review done; human sign-off pending | AC8: uncommitted working tree | AD8: Tests: tests/test_register_audit_coverage.py::test_sales_invoice_complete_writes_audit_event [pass]; tests/test_plan_above_items.py::test_period_lock_and_reopen_name_the_actor [pass]; tests/test_plan_above_items.py::test_payroll_finalise_writes_an_audit_event [pass]; tests/test_plan_above_items.py::test_amended_invoice_uses_the_coverage_event_name [pass] | Code: backend/core/services/audit.py:before_status_for_event; backend/planwave/services.py:AUDIT_COVERAGE | Run: pytest on SQLite 2026-10-05 (Postgres-only tests skipped) | AE8: =IFERROR(INDEX('Task Register'!$AJ$2:$AJ$771,MATCH(B8,'Task Register'!$A$2:$A$771,0)),"") -> Built - tested | AF8: =IFERROR(INDEX('Task Register'!$AU$2:$AU$771,MATCH(B8,'Task Register'!$A$2:$A$771,0)),"") -> Pass | AG8: feature | AI8: 19 | AJ8: P-0115
A9: WI-002 | B9: X-0432 | C9: Critical transaction → immutable audit trail exists | D9: 1 | E9: MVP | F9: Audit & integrity | G9: Backend | H9: Delivered with P-0115. | I9: Pass: Parent P-0115 is Done and its tests pass. Rejecting case: Same rejecting cases as P-0115. Done means: tests for the touched apps pass on Postgres 17 with lint and type checks clean and any strict xfail for the item removed; the reviewer (not the author) signs; register_sync.py scores the test and the register row reads Built - tested / Pass; the full suite runs nightly and at the wave gate. | J9: backend/tests/test_register_audit_coverage.py | K9: WI-001 | L9: Agent 2 | M9: 0 | N9: =ROUNDUP(M9*(1+'Plan guide'!$B$6),0) -> 0 | O9: 46314 | P9: 46314 | Q9: N/A | R9: N/A | S9: N/A | T9: In progress | U9: Done | V9: =IF(COUNTIF(Q9:U9,"Blocked")>0,"Blocked",IF(COUNTIF(Q9:U9,"Done")+COUNTIF(Q9:U9,"N/A")=5,"Done",IF(COUNTIF(Q9:U9,"Done")+COUNTIF(Q9:U9,"In progress")>0,"In progress","Not started"))) -> In progress | W9: =IF(5-COUNTIF(Q9:U9,"N/A")=0,1,COUNTIF(Q9:U9,"Done")/(5-COUNTIF(Q9:U9,"N/A"))) -> 0.5 | Z9: =IF(V9="Done",IF(Y9="",0,MAX(0,Y9-P9)),MAX(0,TODAY()-P9)) -> 0 | AA9: =IF(V9="Done","Done",IF(V9="Blocked","Red",IF(Z9>0,"Red",IF(AND(O9<=TODAY(),P9-TODAY()<=3,W9<0.5),"Amber","Green")))) -> Green | AB9: Agent review done; human sign-off pending | AC9: uncommitted working tree | AD9: Tests: tests/test_register_audit_coverage.py::test_sales_invoice_complete_writes_audit_event [pass]; tests/test_register_audit_coverage.py::test_supplier_payment_post_writes_audit_event [pass]; tests/test_register_audit_coverage.py::test_stock_adjustment_writes_audit_event [pass]; tests/test_audit_append_only.py::test_saving_an_existing_event_is_refused [pass] | Code: backend/core/services/audit.py:record_document_event; backend/planwave/services.py:AUDIT_COVERAGE | Run: pytest on SQLite 2026-10-05 (Postgres-only tests skipped) | AE9: =IFERROR(INDEX('Task Register'!$AJ$2:$AJ$771,MATCH(B9,'Task Register'!$A$2:$A$771,0)),"") -> Built - tested | AF9: =IFERROR(INDEX('Task Register'!$AU$2:$AU$771,MATCH(B9,'Task Register'!$A$2:$A$771,0)),"") -> Pass | AG9: feature | AI9: 10 | AJ9: X-0432
A10: WI-003 | B10: P-0507 | C10: Audit MCA mandated immutable audit trail (Rule 11(g) Companies Audit Rules) | D10: 1 | E10: MVP | F10: Audit & integrity | G10: Backend | H10: Rule 11(g) coverage map (action to audit event) built now; edit log on every accounting record; certification export listing the periods in which logging was on. CA sign-off is the separate CA-SIGN item. | I10: Pass: Coverage map lists every accounting record with its event; certification export shows logging on for the whole year. Rejecting case: Export refuses to certify when the chain has a gap or logging was off in a period. Done means: tests for the touched apps pass on Postgres 17 with lint and type checks clean and any strict xfail for the item removed; the reviewer (not the author) signs; register_sync.py scores the test and the register row reads Built - tested / Pass; the full suite runs nightly and at the wave gate. | J10: backend/tests/test_plan_p_0507.py | K10: WI-001 | L10: Agent 1 | M10: 2 | N10: =ROUNDUP(M10*(1+'Plan guide'!$B$6),0) -> 3 | O10: 46314 | P10: 46317 | Q10: Done | R10: In progress | S10: In progress | T10: Not started | U10: Not started | V10: =IF(COUNTIF(Q10:U10,"Blocked")>0,"Blocked",IF(COUNTIF(Q10:U10,"Done")+COUNTIF(Q10:U10,"N/A")=5,"Done",IF(COUNTIF(Q10:U10,"Done")+COUNTIF(Q10:U10,"In progress")>0,"In progress","Not started"))) -> In progress | W10: =IF(5-COUNTIF(Q10:U10,"N/A")=0,1,COUNTIF(Q10:U10,"Done")/(5-COUNTIF(Q10:U10,"N/A"))) -> 0.2 | Z10: =IF(V10="Done",IF(Y10="",0,MAX(0,Y10-P10)),MAX(0,TODAY()-P10)) -> 0 | AA10: =IF(V10="Done","Done",IF(V10="Blocked","Red",IF(Z10>0,"Red",IF(AND(O10<=TODAY(),P10-TODAY()<=3,W10<0.5),"Amber","Green")))) -> Green | AB10: Gap: Coverage map and certification export exist, but the export does not list the periods logging was on (it returns logging_on=True or refuses). Nothing writes LoggingWindow rows automatically. No edit log (before/after) on every accounting record, only per-action audit events. No test asserts every AUDIT_COVERAGE event is actually emitted. | AC10: uncommitted working tree | AD10: Tests: tests/test_planwave_remaining.py::test_certification_refuses_a_dark_window [pass]; tests/test_register_audit_coverage.py::test_sales_invoice_complete_writes_audit_event [pass]; tests/test_plan_above_items.py::test_period_lock_and_reopen_name_the_actor [pass] | Code: backend/planwave/services.py:certification_export; backend/planwave/services.py:AUDIT_COVERAGE; backend/planwave/models.py:LoggingWindow; backend/planwave/views.py:CertificationView | Run: pytest on SQLite 2026-10-05 (Postgres-only tests skipped) | AE10: =IFERROR(INDEX('Task Register'!$AJ$2:$AJ$771,MATCH(B10,'Task Register'!$A$2:$A$771,0)),"") -> Built - partial | AF10: =IFERROR(INDEX('Task Register'!$AU$2:$AU$771,MATCH(B10,'Task Register'!$A$2:$A$771,0)),"") -> Partial | AG10: feature | AI10: 7, 10 | AJ10: P-0507
A11: WI-004 | B11: C-0616 | C11: Companies (Accounts) Rules Rule 3(1) and Rule 11(g) audit trail compliance certification | D11: 1 | E11: MVP | F11: Audit & integrity | G11: Backend | H11: Delivered with P-0507: report certifying logging was never disabled. | I11: Pass: Report certifies logging was never disabled for the financial year. Rejecting case: Report flags any window in which logging was disabled. Done means: tests for the touched apps pass on Postgres 17 with lint and type checks clean and any strict xfail for the item removed; the reviewer (not the author) signs; register_sync.py scores the test and the register row reads Built - tested / Pass; the full suite runs nightly and at the wave gate. | J11: backend/tests/test_plan_c_0616.py | K11: WI-003 | L11: Agent 1 | M11: 0 | N11: =ROUNDUP(M11*(1+'Plan guide'!$B$6),0) -> 0 | O11: 46321 | P11: 46321 | Q11: N/A | R11: N/A | S11: N/A | T11: In progress | U11: Done | V11: =IF(COUNTIF(Q11:U11,"Blocked")>0,"Blocked",IF(COUNTIF(Q11:U11,"Done")+COUNTIF(Q11:U11,"N/A")=5,"Done",IF(COUNTIF(Q11:U11,"Done")+COUNTIF(Q11:U11,"In progress")>0,"In progress","Not started"))) -> In progress | W11: =IF(5-COUNTIF(Q11:U11,"N/A")=0,1,COUNTIF(Q11:U11,"Done")/(5-COUNTIF(Q11:U11,"N/A"))) -> 0.5 | Z11: =IF(V11="Done",IF(Y11="",0,MAX(0,Y11-P11)),MAX(0,TODAY()-P11)) -> 0 | AA11: =IF(V11="Done","Done",IF(V11="Blocked","Red",IF(Z11>0,"Red",IF(AND(O11<=TODAY(),P11-TODAY()<=3,W11<0.5),"Amber","Green")))) -> Green | AB11: Agent review done; human sign-off pending | AC11: uncommitted working tree | AD11: Tests: tests/test_planwave_remaining.py::test_certification_refuses_a_dark_window [pass] | Code: backend/planwave/services.py:certification_export; backend/planwave/views.py:CertificationView; backend/planwave/models.py:LoggingWindow | Run: pytest on SQLite 2026-10-05 (Postgres-only tests skipped) | AE11: =IFERROR(INDEX('Task Register'!$AJ$2:$AJ$771,MATCH(B11,'Task Register'!$A$2:$A$771,0)),"") -> Built - tested | AF11: =IFERROR(INDEX('Task Register'!$AU$2:$AU$771,MATCH(B11,'Task Register'!$A$2:$A$771,0)),"") -> Pass | AG11: feature | AJ11: C-0616
A12: WI-005 | B12: S-0561 | C12: Automated background trial balance zero-sum verification worker | D12: 1 | E12: MVP | F12: Audit & integrity | G12: Backend | H12: Nightly worker runs these invariants: trial balance zero; every journal balanced; AR/AP control accounts equal customer/supplier outstanding; stock ledger equals movements; allocations within payments; ledger output tax equals invoice tax. A violation creates a quarantine record, blocks period close and GST export until cleared (billing continues), and alerts Owner, Accountant and the ops mailbox. | I12: Pass: Nightly task runs every listed invariant; a violation creates a quarantine record, blocks period close and GST export and alerts. Rejecting case: An unbalanced journal inserted through the ORM is caught on the next run and blocks period close. Done means: tests for the touched apps pass on Postgres 17 with lint and type checks clean and any strict xfail for the item removed; the reviewer (not the author) signs; register_sync.py scores the test and the register row reads Built - tested / Pass; the full suite runs nightly and at the wave gate. | J12: backend/tests/test_plan_s_0561.py; backend/tests/test_register_integrity_gaps.py (invariant tests) | L12: Agent 2 | M12: 3 | N12: =ROUNDUP(M12*(1+'Plan guide'!$B$6),0) -> 4 | O12: 46311 | P12: 46317 | Q12: Done | R12: In progress | S12: In progress | T12: Not started | U12: Not started | V12: =IF(COUNTIF(Q12:U12,"Blocked")>0,"Blocked",IF(COUNTIF(Q12:U12,"Done")+COUNTIF(Q12:U12,"N/A")=5,"Done",IF(COUNTIF(Q12:U12,"Done")+COUNTIF(Q12:U12,"In progress")>0,"In progress","Not started"))) -> In progress | W12: =IF(5-COUNTIF(Q12:U12,"N/A")=0,1,COUNTIF(Q12:U12,"Done")/(5-COUNTIF(Q12:U12,"N/A"))) -> 0.2 | Z12: =IF(V12="Done",IF(Y12="",0,MAX(0,Y12-P12)),MAX(0,TODAY()-P12)) -> 0 | AA12: =IF(V12="Done","Done",IF(V12="Blocked","Red",IF(Z12>0,"Red",IF(AND(O12<=TODAY(),P12-TODAY()<=3,W12<0.5),"Amber","Green")))) -> Green | AB12: Gap: No invariant for payment allocations within payment amounts; no registered invariant for ledger output tax equals invoice tax (only a one-off test); AR/AP control vs outstanding only as dashboard-vs-aging projection checks; quarantine block wired to GST soft-close and GSTR export but not to accounting period lock; ops mailbox is only a log line; no test that the nightly run creates the quarantine row end to end; test_plan_s_0561.py absent. | AC12: uncommitted working tree | AD12: Tests: tests/test_planwave_remaining.py::test_quarantine_blocks_close_and_clears [pass]; tests/test_code_review_2026_10_05.py::test_one_open_quarantine_row_per_company [pass]; tests/test_fmea_mitigations.py::test_tc_fmea_010_a_failed_invariant_notifies_the_owner_in_app [pass]; tests/test_register_integrity_gaps.py::test_output_tax_in_ledger_equals_sum_of_completed_invoice_tax [pass] | Code: backend/core/tasks.py:nightly_invariants_task; backend/planwave/services.py:open_quarantine; backend/planwave/services.py:assert_books_clear; backend/reporting/gst_periods.py:soft_close_period | Run: pytest on SQLite 2026-10-05 (Postgres-only tests skipped) | AE12: =IFERROR(INDEX('Task Register'!$AJ$2:$AJ$771,MATCH(B12,'Task Register'!$A$2:$A$771,0)),"") -> Built - partial | AF12: =IFERROR(INDEX('Task Register'!$AU$2:$AU$771,MATCH(B12,'Task Register'!$A$2:$A$771,0)),"") -> Partial | AG12: feature | AI12: 22 | AJ12: S-0561
A13: WI-006 | B13: S-0568 | C13: Database foreign key cascade deletion defense and soft-delete enforcement | D13: 1 | E13: MVP | F13: Audit & integrity | G13: Backend | H13: is_deleted on Customer, Supplier, Product, Warehouse and PriceList; restore by Owner/Admin; ledger accounts keep their guard; transactions are cancelled, never soft-deleted. Cascades onto transactional rows become PROTECT; existing child rows untouched; an orphan report is produced before the migration. | I13: Pass: Soft-deleted masters vanish from lists, reports and search and Owner/Admin can restore them with history intact. Rejecting case: Hard delete of a master that has transactions raises; deleting a parent no longer cascades onto transactional rows. Done means: tests for the touched apps pass on Postgres 17 with lint and type checks clean and any strict xfail for the item removed; the reviewer (not the author) signs; register_sync.py scores the test and the register row reads Built - tested / Pass; the full suite runs nightly and at the wave gate. | J13: backend/tests/test_plan_s_0568.py | L13: Agent 1 | M13: 4 | N13: =ROUNDUP(M13*(1+'Plan guide'!$B$6),0) -> 5 | O13: 46318 | P13: 46324 | Q13: Done | R13: In progress | S13: In progress | T13: Not started | U13: Not started | V13: =IF(COUNTIF(Q13:U13,"Blocked")>0,"Blocked",IF(COUNTIF(Q13:U13,"Done")+COUNTIF(Q13:U13,"N/A")=5,"Done",IF(COUNTIF(Q13:U13,"Done")+COUNTIF(Q13:U13,"In progress")>0,"In progress","Not started"))) -> In progress | W13: =IF(5-COUNTIF(Q13:U13,"N/A")=0,1,COUNTIF(Q13:U13,"Done")/(5-COUNTIF(Q13:U13,"N/A"))) -> 0.2 | Z13: =IF(V13="Done",IF(Y13="",0,MAX(0,Y13-P13)),MAX(0,TODAY()-P13)) -> 0 | AA13: =IF(V13="Done","Done",IF(V13="Blocked","Red",IF(Z13>0,"Red",IF(AND(O13<=TODAY(),P13-TODAY()<=3,W13<0.5),"Amber","Green")))) -> Green | AB13: Gap: Soft delete exists on Customer, Supplier, Product, Warehouse, PriceList and sales FKs are PROTECT, but some child FKs to Customer/Product/Warehouse remain CASCADE (payments dunning/portal/promise, warehouse reorder/running costs). orphan_report and its management command have no test. Restore permission is Owner/Manager/Accountant, not Owner/Admin only. Only Customer is tested for soft-delete and restore. | AC13: uncommitted working tree | AD13: Tests: tests/test_planwave_remaining.py::test_soft_deleted_customer_hides_and_hard_delete_is_refused [pass]; tests/test_planwave_finish.py::test_restore_brings_a_customer_back [pass] | Code: backend/core/models.py:SoftDeleteFields; backend/planwave/finish.py:restore_master; backend/planwave/finish.py:orphan_report; backend/planwave/views.py:RestoreMasterView | Run: pytest on SQLite 2026-10-05 (Postgres-only tests skipped) | AE13: =IFERROR(INDEX('Task Register'!$AJ$2:$AJ$771,MATCH(B13,'Task Register'!$A$2:$A$771,0)),"") -> Built - partial | AF13: =IFERROR(INDEX('Task Register'!$AU$2:$AU$771,MATCH(B13,'Task Register'!$A$2:$A$771,0)),"") -> Partial | AG13: feature | AI13: 23 | AJ13: S-0568
A14: WI-007 | B14: S-0570 | C14: Automated continuous WAL archiving and daily encrypted PostgreSQL pg_dump snapshot | D14: 1 | E14: MVP | F14: Platform & reliability | G14: Infra | H14: Provider-specific design after DEC-HOST: WAL archiving and point-in-time recovery plus the daily encrypted dump, RPO 5 min and RTO 1 h by default, keys held in the provider key service. Restore drill into a non-production copy, timed. | I14: Pass: Timed restore drill reaches a chosen target time within the RTO; the encrypted dump restores. Rejecting case: Restore with the wrong key fails; a gap in archived WAL raises an alert. Done means: the drill is executed on a non-production copy and its timings and steps are attached; the reviewer signs. | J14: drill log in qos/evidence/ (restore or alert drill) | K14: WI-069 | L14: Agent 2 | M14: 3 | N14: =ROUNDUP(M14*(1+'Plan guide'!$B$6),0) -> 4 | O14: 46318 | P14: 46323 | Q14: Done | R14: In progress | S14: Not started | T14: Not started | U14: Not started | V14: =IF(COUNTIF(Q14:U14,"Blocked")>0,"Blocked",IF(COUNTIF(Q14:U14,"Done")+COUNTIF(Q14:U14,"N/A")=5,"Done",IF(COUNTIF(Q14:U14,"Done")+COUNTIF(Q14:U14,"In progress")>0,"In progress","Not started"))) -> In progress | W14: =IF(5-COUNTIF(Q14:U14,"N/A")=0,1,COUNTIF(Q14:U14,"Done")/(5-COUNTIF(Q14:U14,"N/A"))) -> 0.2 | Z14: =IF(V14="Done",IF(Y14="",0,MAX(0,Y14-P14)),MAX(0,TODAY()-P14)) -> 0 | AA14: =IF(V14="Done","Done",IF(V14="Blocked","Red",IF(Z14>0,"Red",IF(AND(O14<=TODAY(),P14-TODAY()<=3,W14<0.5),"Amber","Green")))) -> Green | AB14: Gap: No WAL archiving or point-in-time recovery, no RPO 5 min / RTO 1 h configuration, no provider key-service integration (GPG/age recipient only), and no timed restore drill log in qos/evidence. | AC14: uncommitted working tree | AD14: Code: scripts/backup.sh; scripts/restore_drill.sh; .github/workflows/backup-restore-drill.yml | Run: pytest on SQLite 2026-10-05 (Postgres-only tests skipped) | AE14: =IFERROR(INDEX('Task Register'!$AJ$2:$AJ$771,MATCH(B14,'Task Register'!$A$2:$A$771,0)),"") -> Built - partial | AF14: =IFERROR(INDEX('Task Register'!$AU$2:$AU$771,MATCH(B14,'Task Register'!$A$2:$A$771,0)),"") -> Partial | AG14: infra drill | AI14: 6 | AJ14: S-0570
A15: WI-008 | B15: S-0572 | C15: Distributed Redis token bucket rate limiting on public-facing API endpoints | D15: 1 | E15: MVP | F15: Security | G15: Infra | H15: Redis token bucket. Login 10/min per IP and 5/min per account; OTP 3/min and 10/h per target; register 5/h per IP; portal 60/min per token; authenticated API 600/min per tenant (burst 100); webhooks signature-verified with a higher limit. Redis down: login and OTP fail closed on a strict in-process limit, the general API fails open, with an alert. | I15: Pass: Each public route enforces its limit with 429 and Retry-After. Rejecting case: The 11th login attempt in a minute is refused; with Redis stopped, login still refuses over-limit attempts and the general API stays up. Done means: tests for the touched apps pass on Postgres 17 with lint and type checks clean and any strict xfail for the item removed; the reviewer (not the author) signs; register_sync.py scores the test and the register row reads Built - tested / Pass; the full suite runs nightly and at the wave gate. | J15: backend/tests/test_plan_s_0572.py | L15: Agent 2 | M15: 2 | N15: =ROUNDUP(M15*(1+'Plan guide'!$B$6),0) -> 3 | O15: 46324 | P15: 46328 | Q15: Done | R15: In progress | S15: In progress | T15: Not started | U15: Not started | V15: =IF(COUNTIF(Q15:U15,"Blocked")>0,"Blocked",IF(COUNTIF(Q15:U15,"Done")+COUNTIF(Q15:U15,"N/A")=5,"Done",IF(COUNTIF(Q15:U15,"Done")+COUNTIF(Q15:U15,"In progress")>0,"In progress","Not started"))) -> In progress | W15: =IF(5-COUNTIF(Q15:U15,"N/A")=0,1,COUNTIF(Q15:U15,"Done")/(5-COUNTIF(Q15:U15,"N/A"))) -> 0.2 | Z15: =IF(V15="Done",IF(Y15="",0,MAX(0,Y15-P15)),MAX(0,TODAY()-P15)) -> 0 | AA15: =IF(V15="Done","Done",IF(V15="Blocked","Red",IF(Z15>0,"Red",IF(AND(O15<=TODAY(),P15-TODAY()<=3,W15<0.5),"Amber","Green")))) -> Green | AB15: Gap: Authenticated API is limited per credential at 100 per 10 s plus 1500/min per IP, not 600/min per tenant; fixed-window cache counter, not a token bucket; webhook limit is per IP and signature verification is separate; Redis-down alert is a single log line; no tests for register 5/h, portal 60/min, or the API limits. | AC15: uncommitted working tree | AD15: Tests: tests/test_planwave_remaining.py::test_rate_limit_refuses_the_eleventh_login [pass]; tests/test_planwave_remaining.py::test_same_account_login_stops_at_six [pass]; tests/test_planwave_remaining.py::test_cache_down_closes_login_and_leaves_api_up [pass]; tests/test_plan_above_items.py::test_otp_limit_follows_the_phone_not_the_ip [pass] | Code: backend/planwave/ratelimit.py:rules_for; backend/planwave/ratelimit.py:_hit; backend/planwave/ratelimit.py:PlanRateLimitMiddleware | Run: pytest on SQLite 2026-10-05 (Postgres-only tests skipped) | AE15: =IFERROR(INDEX('Task Register'!$AJ$2:$AJ$771,MATCH(B15,'Task Register'!$A$2:$A$771,0)),"") -> Built - partial | AF15: =IFERROR(INDEX('Task Register'!$AU$2:$AU$771,MATCH(B15,'Task Register'!$A$2:$A$771,0)),"") -> Partial | AG15: feature | AI15: 24 | AJ15: S-0572
A16: WI-009 | B16: SEC-0622 | C16: Field-level role masking for sensitive commercial margins and cost prices | D16: 1 | E16: MVP | F16: Security | G16: Backend | H16: Omit purchase_price and margin (never blank or zero) in API, exports and PDFs for Cashier, Salesperson and Godown custodian; visible to Owner, Admin, Accountant, Purchase Manager, Inventory Manager. POS shows a server-computed below-cost warning, not the cost. | I16: Pass: Cashier, Salesperson and Godown custodian never receive purchase price or margin from API, exports, PDFs or POS. Rejecting case: A request from those roles for cost fields gets the field omitted, with one test per surface. Done means: tests for the touched apps pass on Postgres 17 with lint and type checks clean and any strict xfail for the item removed; the reviewer (not the author) signs; register_sync.py scores the test and the register row reads Built - tested / Pass; the full suite runs nightly and at the wave gate. | J16: backend/tests/test_plan_sec_0622.py | L16: Agent 1 | M16: 2 | N16: =ROUNDUP(M16*(1+'Plan guide'!$B$6),0) -> 3 | O16: 46325 | P16: 46329 | Q16: Done | R16: In progress | S16: In progress | T16: Not started | U16: Not started | V16: =IF(COUNTIF(Q16:U16,"Blocked")>0,"Blocked",IF(COUNTIF(Q16:U16,"Done")+COUNTIF(Q16:U16,"N/A")=5,"Done",IF(COUNTIF(Q16:U16,"Done")+COUNTIF(Q16:U16,"In progress")>0,"In progress","Not started"))) -> In progress | W16: =IF(5-COUNTIF(Q16:U16,"N/A")=0,1,COUNTIF(Q16:U16,"Done")/(5-COUNTIF(Q16:U16,"N/A"))) -> 0.2 | Z16: =IF(V16="Done",IF(Y16="",0,MAX(0,Y16-P16)),MAX(0,TODAY()-P16)) -> 0 | AA16: =IF(V16="Done","Done",IF(V16="Blocked","Red",IF(Z16>0,"Red",IF(AND(O16<=TODAY(),P16-TODAY()<=3,W16<0.5),"Amber","Green")))) -> Green | AB16: Gap: Masking is applied only to the Product serializer and the plan catalogue CSV/PDF. Margin and cost on invoice-profit reports, purchase lines, other exports and PDFs are not masked via this helper. Role set uses OWNER/ACCOUNTANT/MANAGER; no Purchase Manager or Inventory Manager distinction and INVENTORY_STAFF is masked. Below-cost warning is only a product-level flag, not a POS server check. | AC16: uncommitted working tree | AD16: Tests: tests/test_planwave_remaining.py::test_product_api_omits_cost_for_sales_staff [pass]; tests/test_planwave_remaining.py::test_cost_fields_are_omitted_for_sales_staff [pass]; tests/test_plan_above_items.py::test_catalogue_export_omits_cost_for_sales_staff [pass] | Code: backend/planwave/services.py:mask_commercial; backend/masters/serializers.py:ProductSerializer.to_representation; backend/planwave/finish.py:catalog_rows; backend/planwave/finish.py:catalog_pdf | Run: pytest on SQLite 2026-10-05 (Postgres-only tests skipped) | AE16: =IFERROR(INDEX('Task Register'!$AJ$2:$AJ$771,MATCH(B16,'Task Register'!$A$2:$A$771,0)),"") -> Built - partial | AF16: =IFERROR(INDEX('Task Register'!$AU$2:$AU$771,MATCH(B16,'Task Register'!$A$2:$A$771,0)),"") -> Partial | AG16: feature | AI16: 25 | AJ16: SEC-0622
A17: WI-010 | B17: SEC-0624 | C17: Time-based One-Time Password (TOTP) two-factor authentication (2FA) for admin roles | D17: 1 | E17: MVP | F17: Security | G17: Full stack | H17: Gap-fill, not a rebuild. Enforcement already defaults on in production and staging for OWNER and ACCOUNTANT, with first-login enrolment and recovery codes. There is no separate Admin role (OWNER is Owner/Admin) and no can_manage_users flag. Extend the same enforcement to any membership with can_post_journals (MANAGER by default). Leave SALES_STAFF, inventory staff, auditor and viewer out. | I17: Pass: OWNER, ACCOUNTANT and a membership with can_post_journals cannot get a normal session without TOTP, are forced to enrol at first login, and recovery codes work once. Rejecting case: Password-only login for those memberships yields no session; SALES_STAFF can still sign in with a password. Done means: tests for the touched apps pass on Postgres 17 with lint and type checks clean and any strict xfail for the item removed; the reviewer (not the author) signs; register_sync.py scores the test and the register row reads Built - tested / Pass; the full suite runs nightly and at the wave gate. | J17: backend/tests/test_mfa.py; backend/tests/test_mfa_mandatory.py; backend/tests/test_register_integrity_gaps.py (xfail test) | L17: Agent 2 | M17: 4 | N17: =ROUNDUP(M17*(1+'Plan guide'!$B$6),0) -> 5 | O17: 46329 | P17: 46336 | Q17: Done | R17: Done | S17: Done | T17: In progress | U17: Done | V17: =IF(COUNTIF(Q17:U17,"Blocked")>0,"Blocked",IF(COUNTIF(Q17:U17,"Done")+COUNTIF(Q17:U17,"N/A")=5,"Done",IF(COUNTIF(Q17:U17,"Done")+COUNTIF(Q17:U17,"In progress")>0,"In progress","Not started"))) -> In progress | W17: =IF(5-COUNTIF(Q17:U17,"N/A")=0,1,COUNTIF(Q17:U17,"Done")/(5-COUNTIF(Q17:U17,"N/A"))) -> 0.8 | Z17: =IF(V17="Done",IF(Y17="",0,MAX(0,Y17-P17)),MAX(0,TODAY()-P17)) -> 0 | AA17: =IF(V17="Done","Done",IF(V17="Blocked","Red",IF(Z17>0,"Red",IF(AND(O17<=TODAY(),P17-TODAY()<=3,W17<0.5),"Amber","Green")))) -> Green | AB17: Agent review done; human sign-off pending | AC17: uncommitted working tree | AD17: Tests: tests/test_mfa.py::test_flag_on_journal_poster_must_enrol [pass]; tests/test_mfa.py::test_flag_on_sales_staff_still_gets_a_session [pass]; tests/test_mfa.py::test_flag_on_owner_without_mfa_must_enrol [pass]; tests/test_register_integrity_gaps.py::test_owner_without_mfa_cannot_complete_login_with_password_alone [pass] | Code: backend/accounts/mfa_service.py:user_has_money_role; backend/accounts/mfa_service.py:enrolment_required; backend/config/settings.py:_assert_mfa_enforcement | Run: pytest on SQLite 2026-10-05 (Postgres-only tests skipped) | AE17: =IFERROR(INDEX('Task Register'!$AJ$2:$AJ$771,MATCH(B17,'Task Register'!$A$2:$A$771,0)),"") -> Built - tested | AF17: =IFERROR(INDEX('Task Register'!$AU$2:$AU$771,MATCH(B17,'Task Register'!$A$2:$A$771,0)),"") -> Pass | AG17: feature | AI17: 12, 18 | AJ17: SEC-0624
A18: WI-011 | B18: SEC-0625 | C18: Instant user deactivation and immediate JWT session revocation | D18: 1 | E18: MVP | F18: Security | G18: Backend | H18: Per-user session version checked on each request (Redis with database fallback) plus the existing refresh blacklist, so access and refresh tokens both die on deactivation. Websocket drop only if a channel layer exists. | I18: Pass: Deactivating a user invalidates access and refresh tokens at the next request. Rejecting case: A deactivated user's existing access token is answered 401. Done means: tests for the touched apps pass on Postgres 17 with lint and type checks clean and any strict xfail for the item removed; the reviewer (not the author) signs; register_sync.py scores the test and the register row reads Built - tested / Pass; the full suite runs nightly and at the wave gate. | J18: backend/tests/test_plan_sec_0625.py | L18: Agent 1 | M18: 3 | N18: =ROUNDUP(M18*(1+'Plan guide'!$B$6),0) -> 4 | O18: 46330 | P18: 46336 | Q18: Done | R18: Done | S18: Done | T18: In progress | U18: Done | V18: =IF(COUNTIF(Q18:U18,"Blocked")>0,"Blocked",IF(COUNTIF(Q18:U18,"Done")+COUNTIF(Q18:U18,"N/A")=5,"Done",IF(COUNTIF(Q18:U18,"Done")+COUNTIF(Q18:U18,"In progress")>0,"In progress","Not started"))) -> In progress | W18: =IF(5-COUNTIF(Q18:U18,"N/A")=0,1,COUNTIF(Q18:U18,"Done")/(5-COUNTIF(Q18:U18,"N/A"))) -> 0.8 | Z18: =IF(V18="Done",IF(Y18="",0,MAX(0,Y18-P18)),MAX(0,TODAY()-P18)) -> 0 | AA18: =IF(V18="Done","Done",IF(V18="Blocked","Red",IF(Z18>0,"Red",IF(AND(O18<=TODAY(),P18-TODAY()<=3,W18<0.5),"Amber","Green")))) -> Green | AB18: Agent review done; human sign-off pending | AC18: uncommitted working tree | AD18: Tests: tests/test_plan_audit_seal_session.py::test_deactivated_user_access_token_is_rejected [pass]; tests/test_planwave_remaining.py::test_socket_drop_is_a_no_op_without_channels [pass] | Code: backend/core/authentication.py:get_user; backend/accounts/views.py:_revoke_sessions_if_last_active_membership; backend/planwave/sockets.py:drop_user_sockets | Run: pytest on SQLite 2026-10-05 (Postgres-only tests skipped) | AE18: =IFERROR(INDEX('Task Register'!$AJ$2:$AJ$771,MATCH(B18,'Task Register'!$A$2:$A$771,0)),"") -> Built - tested | AF18: =IFERROR(INDEX('Task Register'!$AU$2:$AU$771,MATCH(B18,'Task Register'!$A$2:$A$771,0)),"") -> Pass | AG18: feature | AI18: 26 | AJ18: SEC-0625
A19: WI-012 | B19: SEC-0626 | C19: Cross-Site Scripting (XSS) and SQL injection sanitization on document notes and inputs | D19: 1 | E19: MVP | F19: Security | G19: Backend | H19: Strip HTML tags on save from plain-text fields (notes, descriptions, names, addresses, remarks, complaint text, imported cells); escape on render and in PDF templates; a guard test fails on string-built raw SQL. | I19: Pass: HTML is stripped on save from the listed fields and output is escaped in the UI and PDFs. Rejecting case: A stored script tag never executes or appears raw; string-built raw SQL fails the guard test. Done means: tests for the touched apps pass on Postgres 17 with lint and type checks clean and any strict xfail for the item removed; the reviewer (not the author) signs; register_sync.py scores the test and the register row reads Built - tested / Pass; the full suite runs nightly and at the wave gate. | J19: backend/tests/test_plan_sec_0626.py | L19: Agent 1 | M19: 2 | N19: =ROUNDUP(M19*(1+'Plan guide'!$B$6),0) -> 3 | O19: 46338 | P19: 46342 | Q19: Done | R19: In progress | S19: In progress | T19: Not started | U19: Not started | V19: =IF(COUNTIF(Q19:U19,"Blocked")>0,"Blocked",IF(COUNTIF(Q19:U19,"Done")+COUNTIF(Q19:U19,"N/A")=5,"Done",IF(COUNTIF(Q19:U19,"Done")+COUNTIF(Q19:U19,"In progress")>0,"In progress","Not started"))) -> In progress | W19: =IF(5-COUNTIF(Q19:U19,"N/A")=0,1,COUNTIF(Q19:U19,"Done")/(5-COUNTIF(Q19:U19,"N/A"))) -> 0.2 | Z19: =IF(V19="Done",IF(Y19="",0,MAX(0,Y19-P19)),MAX(0,TODAY()-P19)) -> 0 | AA19: =IF(V19="Done","Done",IF(V19="Blocked","Red",IF(Z19>0,"Red",IF(AND(O19<=TODAY(),P19-TODAY()<=3,W19<0.5),"Amber","Green")))) -> Green | AB19: Gap: Tag stripping is wired to only six models (Customer, Supplier, Product, SalesInvoice, PurchaseInvoice, Complaint); customer and supplier names are deliberately not stripped; other models are not covered. No test for escaping in PDF templates or for imported cells. | AC19: uncommitted working tree | AD19: Tests: tests/test_planwave_remaining.py::test_html_is_stripped_on_customer_notes [pass]; tests/test_planwave_remaining.py::test_plain_text_tags_are_stripped_on_save [pass]; tests/test_planwave_remaining.py::test_no_string_built_raw_sql [pass]; tests/test_code_review_2026_10_05.py::test_the_sanitiser_strips_tags_but_keeps_comparisons [pass] | Code: backend/planwave/sanitize.py:strip_plain_text; backend/planwave/apps.py:PlanwaveConfig.ready; backend/masters/serializers.py:ProductSerializer; backend/sales/pdf/helpers.py | Run: pytest on SQLite 2026-10-05 (Postgres-only tests skipped) | AE19: =IFERROR(INDEX('Task Register'!$AJ$2:$AJ$771,MATCH(B19,'Task Register'!$A$2:$A$771,0)),"") -> Built - partial | AF19: =IFERROR(INDEX('Task Register'!$AU$2:$AU$771,MATCH(B19,'Task Register'!$A$2:$A$771,0)),"") -> Partial | AG19: feature | AH19: 10 | AI19: 27 | AJ19: SEC-0626
A20: WI-013 | B20: SEC-0628 | C20: Cryptographic AES-256 encryption for stored bank account numbers and tax credentials | D20: 1 | E20: MVP | F20: Security | G20: Backend | H20: AES-256-GCM with a key id for bank account numbers and tax-portal secrets; move existing gateway credentials off Fernet. IFSC stays plain. Batch migration of plaintext rows (reversible), last four digits kept for display. Keys from the host secret store. | I20: Pass: Bank account numbers and portal secrets are AES-256-GCM encrypted with a key id and migrated from plaintext. Rejecting case: Tampered ciphertext fails authentication; the wrong key is rejected; no plaintext column remains. Done means: tests for the touched apps pass on Postgres 17 with lint and type checks clean and any strict xfail for the item removed; the reviewer (not the author) signs; register_sync.py scores the test and the register row reads Built - tested / Pass; the full suite runs nightly and at the wave gate. | J20: backend/tests/test_plan_sec_0628.py | L20: Agent 2 | M20: 3 | N20: =ROUNDUP(M20*(1+'Plan guide'!$B$6),0) -> 4 | O20: 46338 | P20: 46343 | Q20: Done | R20: In progress | S20: In progress | T20: Not started | U20: Not started | V20: =IF(COUNTIF(Q20:U20,"Blocked")>0,"Blocked",IF(COUNTIF(Q20:U20,"Done")+COUNTIF(Q20:U20,"N/A")=5,"Done",IF(COUNTIF(Q20:U20,"Done")+COUNTIF(Q20:U20,"In progress")>0,"In progress","Not started"))) -> In progress | W20: =IF(5-COUNTIF(Q20:U20,"N/A")=0,1,COUNTIF(Q20:U20,"Done")/(5-COUNTIF(Q20:U20,"N/A"))) -> 0.2 | Z20: =IF(V20="Done",IF(Y20="",0,MAX(0,Y20-P20)),MAX(0,TODAY()-P20)) -> 0 | AA20: =IF(V20="Done","Done",IF(V20="Blocked","Red",IF(Z20>0,"Red",IF(AND(O20<=TODAY(),P20-TODAY()<=3,W20<0.5),"Amber","Green")))) -> Green | AB20: Gap: AES-GCM with key id covers company and customer bank accounts only; tax-portal secrets are not sealed in storage, encrypt_gsp_credentials still writes Fernet and nothing batch-migrates existing gateway blobs (only a reseal helper); the seal_bank_accounts command has no reverse path; last4 helper exists but no display field uses it. | AC20: uncommitted working tree | AD20: Tests: tests/test_planwave_remaining.py::test_bank_account_seals_and_rejects_tamper [pass]; tests/test_plan_partials.py::test_party_bank_account_is_sealed_and_revealed [pass]; tests/test_planwave_remaining.py::test_fernet_gateway_blob_moves_to_gcm [pass] | Code: backend/planwave/crypto.py:seal; backend/planwave/apps.py; backend/planwave/management/commands/seal_bank_accounts.py; backend/planwave/services.py:reseal_fernet_blob | Run: pytest on SQLite 2026-10-05 (Postgres-only tests skipped) | AE20: =IFERROR(INDEX('Task Register'!$AJ$2:$AJ$771,MATCH(B20,'Task Register'!$A$2:$A$771,0)),"") -> Built - partial | AF20: =IFERROR(INDEX('Task Register'!$AU$2:$AU$771,MATCH(B20,'Task Register'!$A$2:$A$771,0)),"") -> Partial | AG20: feature | AI20: 20 | AJ20: SEC-0628
A21: WI-014 | B21: X-0715 | C21: Customer changes legal name and registered address: system updates master while preserving historical invoices | D21: 1 | E21: MVP | F21: Audit & integrity | G21: Backend | H21: Snapshot legal name, trade name, billing and shipping address and GSTIN at completion on sales invoices, credit and debit notes and purchase bills. Backfill flags rows as backfill_from_master and uses the audit-history name as of the invoice date where a rename exists. | I21: Pass: Completed documents keep the party details as at completion. Rejecting case: Renaming the customer afterwards does not change the issued PDF or ledger view. Done means: tests for the touched apps pass on Postgres 17 with lint and type checks clean and any strict xfail for the item removed; the reviewer (not the author) signs; register_sync.py scores the test and the register row reads Built - tested / Pass; the full suite runs nightly and at the wave gate. | J21: backend/tests/test_plan_x_0715.py | L21: Agent 1 | M21: 2 | N21: =ROUNDUP(M21*(1+'Plan guide'!$B$6),0) -> 3 | O21: 46343 | P21: 46345 | Q21: Done | R21: In progress | S21: In progress | T21: Not started | U21: Not started | V21: =IF(COUNTIF(Q21:U21,"Blocked")>0,"Blocked",IF(COUNTIF(Q21:U21,"Done")+COUNTIF(Q21:U21,"N/A")=5,"Done",IF(COUNTIF(Q21:U21,"Done")+COUNTIF(Q21:U21,"In progress")>0,"In progress","Not started"))) -> In progress | W21: =IF(5-COUNTIF(Q21:U21,"N/A")=0,1,COUNTIF(Q21:U21,"Done")/(5-COUNTIF(Q21:U21,"N/A"))) -> 0.2 | Z21: =IF(V21="Done",IF(Y21="",0,MAX(0,Y21-P21)),MAX(0,TODAY()-P21)) -> 0 | AA21: =IF(V21="Done","Done",IF(V21="Blocked","Red",IF(Z21>0,"Red",IF(AND(O21<=TODAY(),P21-TODAY()<=3,W21<0.5),"Amber","Green")))) -> Green | AB21: Gap: Backfill copies current master data and does not use the audit-history name as of the invoice date; snapshot tests cover sales invoices only, not credit/debit notes or purchase bills. | AC21: uncommitted working tree | AD21: Tests: tests/test_planwave_remaining.py::test_party_snapshot_survives_rename [pass]; tests/test_code_review_2026_10_05.py::test_a_backfill_never_overwrites_an_issued_snapshot [pass] | Code: backend/planwave/services.py:stamp_party; backend/planwave/management/commands/backfill_party_snapshots.py; backend/sales/services.py; backend/purchases/notes_services.py | Run: pytest on SQLite 2026-10-05 (Postgres-only tests skipped) | AE21: =IFERROR(INDEX('Task Register'!$AJ$2:$AJ$771,MATCH(B21,'Task Register'!$A$2:$A$771,0)),"") -> Built - partial | AF21: =IFERROR(INDEX('Task Register'!$AU$2:$AU$771,MATCH(B21,'Task Register'!$A$2:$A$771,0)),"") -> Partial | AG21: feature | AI21: 28 | AJ21: X-0715
A22: WI-015 | B22: C-0609 | C22: Schedule H and Schedule X restricted drug sales register and doctor prescription logging | D22: 1 | E22: MVP | F22: GST & compliance | G22: Full stack | H22: Per-tenant pharmacy flag, default off. Schedule H/H1/X sale cannot complete without patient and prescriber name and registration no.; Schedule X keeps a prescription copy. Inspector layout (date, patient, prescriber, drug, batch, quantity, invoice no.) as PDF and CSV; retention default 3 years, configurable. A licensed pharmacist reviews layout and retention before any pharmacy goes live. | I22: Pass: A Schedule H/H1/X sale cannot complete without the required details and the register prints in inspector layout. Rejecting case: A sale without the details is rejected; a tenant without the pharmacy flag is unaffected. Done means: tests for the touched apps pass on Postgres 17 with lint and type checks clean and any strict xfail for the item removed; the reviewer (not the author) signs; register_sync.py scores the test and the register row reads Built - tested / Pass; the full suite runs nightly and at the wave gate. | J22: backend/tests/test_plan_c_0609.py | K22: WI-070 | L22: Agent 2 | M22: 5 | N22: =ROUNDUP(M22*(1+'Plan guide'!$B$6),0) -> 6 | O22: 46344 | P22: 46352 | Q22: Done | R22: Done | S22: Done | T22: In progress | U22: Done | V22: =IF(COUNTIF(Q22:U22,"Blocked")>0,"Blocked",IF(COUNTIF(Q22:U22,"Done")+COUNTIF(Q22:U22,"N/A")=5,"Done",IF(COUNTIF(Q22:U22,"Done")+COUNTIF(Q22:U22,"In progress")>0,"In progress","Not started"))) -> In progress | W22: =IF(5-COUNTIF(Q22:U22,"N/A")=0,1,COUNTIF(Q22:U22,"Done")/(5-COUNTIF(Q22:U22,"N/A"))) -> 0.8 | Z22: =IF(V22="Done",IF(Y22="",0,MAX(0,Y22-P22)),MAX(0,TODAY()-P22)) -> 0 | AA22: =IF(V22="Done","Done",IF(V22="Blocked","Red",IF(Z22>0,"Red",IF(AND(O22<=TODAY(),P22-TODAY()<=3,W22<0.5),"Amber","Green")))) -> Green | AB22: Agent review done; human sign-off pending | AC22: uncommitted working tree | AD22: Tests: tests/test_planwave_remaining.py::test_pharmacy_flag_gates_schedule_x [pass]; tests/test_planwave_remaining.py::test_pharmacy_blocks_sale_complete [pass]; tests/test_planwave_finish.py::test_pharmacy_register_lists_the_dispense [pass]; tests/test_plan_remaining_open.py::test_pharmacy_register_pdf_names_the_patient [pass] | Code: backend/planwave/services.py:assert_pharmacy_sale; backend/planwave/finish.py:pharmacy_register_csv; backend/planwave/finish.py:pharmacy_register_pdf; backend/planwave/models.py:PharmacyDispense | Run: pytest on SQLite 2026-10-05 (Postgres-only tests skipped) | AE22: =IFERROR(INDEX('Task Register'!$AJ$2:$AJ$771,MATCH(B22,'Task Register'!$A$2:$A$771,0)),"") -> Built - tested | AF22: =IFERROR(INDEX('Task Register'!$AU$2:$AU$771,MATCH(B22,'Task Register'!$A$2:$A$771,0)),"") -> Pass | AG22: feature | AI22: 29 | AJ22: C-0609
A23: WI-016 | B23: C-0602 | C23: Section 16(2) CGST Act 4-condition statutory Input Tax Credit entitlement verification | D23: 1 | E23: MVP | F23: GST & compliance | G23: Full stack | H23: Per-bill checklist: invoice held and goods received and 180-day payment are system-proven; supplier-paid-tax and return-filed are user-attested (GSTR-2B is outside the freeze). Unconfirmed bills warn and drop out of the claimable ITC summary; posting is not blocked. CA reviews wording. | I23: Pass: The checklist shows on every purchase bill with proven and attested conditions. Rejecting case: A bill with an unconfirmed condition is excluded from the claimable ITC summary. Done means: tests for the touched apps pass on Postgres 17 with lint and type checks clean and any strict xfail for the item removed; the reviewer (not the author) signs; register_sync.py scores the test and the register row reads Built - tested / Pass; the full suite runs nightly and at the wave gate. | J23: backend/tests/test_plan_c_0602.py | K23: WI-070 | L23: Agent 1 | M23: 4 | N23: =ROUNDUP(M23*(1+'Plan guide'!$B$6),0) -> 5 | O23: 46346 | P23: 46353 | Q23: Done | R23: In progress | S23: In progress | T23: Not started | U23: Not started | V23: =IF(COUNTIF(Q23:U23,"Blocked")>0,"Blocked",IF(COUNTIF(Q23:U23,"Done")+COUNTIF(Q23:U23,"N/A")=5,"Done",IF(COUNTIF(Q23:U23,"Done")+COUNTIF(Q23:U23,"In progress")>0,"In progress","Not started"))) -> In progress | W23: =IF(5-COUNTIF(Q23:U23,"N/A")=0,1,COUNTIF(Q23:U23,"Done")/(5-COUNTIF(Q23:U23,"N/A"))) -> 0.2 | Z23: =IF(V23="Done",IF(Y23="",0,MAX(0,Y23-P23)),MAX(0,TODAY()-P23)) -> 0 | AA23: =IF(V23="Done","Done",IF(V23="Blocked","Red",IF(Z23>0,"Red",IF(AND(O23<=TODAY(),P23-TODAY()<=3,W23<0.5),"Amber","Green")))) -> Green | AB23: Gap: Only the negative case is tested (no test that a fully attested bill is claimable or that the 180-day check works); no per-bill warning or checklist UI in the web app; ITC attestation API untested. | AC23: uncommitted working tree | AD23: Tests: tests/test_planwave_finish.py::test_unconfirmed_bill_is_excluded_from_claimable_itc [pass] | Code: backend/planwave/models.py:ItcBillCheck; backend/planwave/finish.py:classify_purchase_bill; backend/planwave/finish.py:itc_summary; backend/planwave/services.py:itc_claimable | Run: pytest on SQLite 2026-10-05 (Postgres-only tests skipped) | AE23: =IFERROR(INDEX('Task Register'!$AJ$2:$AJ$771,MATCH(B23,'Task Register'!$A$2:$A$771,0)),"") -> Built - partial | AF23: =IFERROR(INDEX('Task Register'!$AU$2:$AU$771,MATCH(B23,'Task Register'!$A$2:$A$771,0)),"") -> Partial | AG23: feature | AI23: 30 | AJ23: C-0602
A24: WI-017 | B24: C-0603 | C24: Section 16(4) time-barring automated alert and ITC exclusion engine | D24: 1 | E24: MVP | F24: GST & compliance | G24: Full stack | H24: Warnings 60 and 7 days before the s.16(4) deadline (30 Nov after the invoice's financial year, or annual return date if earlier); TIME_BARRED after it for unclaimed ITC, excluded from claimable. Claimed ITC is flagged for the CA, not reversed. | I24: Pass: Warnings appear at 60 and 7 days before the deadline; barred ITC is marked TIME_BARRED. Rejecting case: TIME_BARRED ITC cannot be claimed; ITC already claimed is flagged, not reversed. Done means: tests for the touched apps pass on Postgres 17 with lint and type checks clean and any strict xfail for the item removed; the reviewer (not the author) signs; register_sync.py scores the test and the register row reads Built - tested / Pass; the full suite runs nightly and at the wave gate. | J24: backend/tests/test_plan_c_0603.py | K24: WI-016 | L24: Agent 1 | M24: 3 | N24: =ROUNDUP(M24*(1+'Plan guide'!$B$6),0) -> 4 | O24: 46357 | P24: 46360 | Q24: Done | R24: In progress | S24: In progress | T24: Not started | U24: Not started | V24: =IF(COUNTIF(Q24:U24,"Blocked")>0,"Blocked",IF(COUNTIF(Q24:U24,"Done")+COUNTIF(Q24:U24,"N/A")=5,"Done",IF(COUNTIF(Q24:U24,"Done")+COUNTIF(Q24:U24,"In progress")>0,"In progress","Not started"))) -> In progress | W24: =IF(5-COUNTIF(Q24:U24,"N/A")=0,1,COUNTIF(Q24:U24,"Done")/(5-COUNTIF(Q24:U24,"N/A"))) -> 0.2 | Z24: =IF(V24="Done",IF(Y24="",0,MAX(0,Y24-P24)),MAX(0,TODAY()-P24)) -> 0 | AA24: =IF(V24="Done","Done",IF(V24="Blocked","Red",IF(Z24>0,"Red",IF(AND(O24<=TODAY(),P24-TODAY()<=3,W24<0.5),"Amber","Green")))) -> Green | AB24: Gap: 60 and 7 day warnings only fire when someone POSTs /plan/itc/summary/; no scheduled task; DUE_60/DUE_7 statuses and alert sending are untested; test_plan_c_0603.py absent. | AC24: uncommitted working tree | AD24: Tests: tests/test_planwave_remaining.py::test_gst_rules [pass]; tests/test_planwave_finish.py::test_unconfirmed_bill_is_excluded_from_claimable_itc [pass] | Code: backend/planwave/services.py:section_16_4_status; backend/planwave/finish.py:refresh_itc_status; backend/planwave/finish.py:alert_itc_deadlines; backend/planwave/finish.py:itc_summary | Run: pytest on SQLite 2026-10-05 (Postgres-only tests skipped) | AE24: =IFERROR(INDEX('Task Register'!$AJ$2:$AJ$771,MATCH(B24,'Task Register'!$A$2:$A$771,0)),"") -> Built - partial | AF24: =IFERROR(INDEX('Task Register'!$AU$2:$AU$771,MATCH(B24,'Task Register'!$A$2:$A$771,0)),"") -> Partial | AG24: feature | AI24: 31 | AJ24: C-0603
A25: WI-018 | B25: C-0604 | C25: Section 17(5) blocked credit automated identification and accounting reclassification | D25: 1 | E25: MVP | F25: GST & compliance | G25: Full stack | H25: Data-driven s.17(5) rule table with effective dates covering the full blocked list; match on HSN/SAC plus expense category (keywords only suggest); blocked GST posts to expense or asset, not ITC receivable; override by Owner or Accountant with reason, audited. CA approves the table. | I25: Pass: Blocked purchases post GST to expense or asset; the rule table covers the full list. Rejecting case: Claiming a blocked category without an authorised override and reason is refused. Done means: tests for the touched apps pass on Postgres 17 with lint and type checks clean and any strict xfail for the item removed; the reviewer (not the author) signs; register_sync.py scores the test and the register row reads Built - tested / Pass; the full suite runs nightly and at the wave gate. | J25: backend/tests/test_plan_c_0604.py | K25: WI-070 | L25: Agent 2 | M25: 5 | N25: =ROUNDUP(M25*(1+'Plan guide'!$B$6),0) -> 6 | O25: 46353 | P25: 46360 | Q25: Done | R25: In progress | S25: In progress | T25: Not started | U25: Not started | V25: =IF(COUNTIF(Q25:U25,"Blocked")>0,"Blocked",IF(COUNTIF(Q25:U25,"Done")+COUNTIF(Q25:U25,"N/A")=5,"Done",IF(COUNTIF(Q25:U25,"Done")+COUNTIF(Q25:U25,"In progress")>0,"In progress","Not started"))) -> In progress | W25: =IF(5-COUNTIF(Q25:U25,"N/A")=0,1,COUNTIF(Q25:U25,"Done")/(5-COUNTIF(Q25:U25,"N/A"))) -> 0.2 | Z25: =IF(V25="Done",IF(Y25="",0,MAX(0,Y25-P25)),MAX(0,TODAY()-P25)) -> 0 | AA25: =IF(V25="Done","Done",IF(V25="Blocked","Red",IF(Z25>0,"Red",IF(AND(O25<=TODAY(),P25-TODAY()<=3,W25<0.5),"Amber","Green")))) -> Green | AB25: Gap: Rule table is only six seeded rows (food, motor vehicles, club, works contract, personal, exempt) and not the full s.17(5) list. Blocked bills are only flagged on ItcBillCheck; GST is not posted to expense/asset instead of ITC receivable. No Owner/Accountant override with reason. Category match is by product category name. No test of classify_purchase_bill blocking or of effective-date handling beyond one HSN match. | AC25: uncommitted working tree | AD25: Tests: tests/test_planwave_remaining.py::test_gst_rules [pass] | Code: backend/planwave/services.py:blocked_credit_match; backend/planwave/services.py:SECTION_17_RULES; backend/planwave/models.py:BlockedCreditRule; backend/planwave/finish.py:classify_purchase_bill | Run: pytest on SQLite 2026-10-05 (Postgres-only tests skipped) | AE25: =IFERROR(INDEX('Task Register'!$AJ$2:$AJ$771,MATCH(B25,'Task Register'!$A$2:$A$771,0)),"") -> Built - partial | AF25: =IFERROR(INDEX('Task Register'!$AU$2:$AU$771,MATCH(B25,'Task Register'!$A$2:$A$771,0)),"") -> Partial | AG25: feature | AH25: 6 | AI25: 32 | AJ25: C-0604
A26: WI-019 | B26: P-0503 | C26: Audit 2A/2B vs Books reconciliation and verify eligible vs blocked ITC | D26: 1 | E26: MVP | F26: GST & compliance | G26: Full stack | H26: Add the blocked-credit classification to the existing 2A/2B reconciliation using uploaded 2B files. No new reconciliation, no GSTN call. | I26: Pass: The 2B reconciliation shows the blocked-credit classification. Rejecting case: A blocked invoice is never counted as eligible ITC. Done means: tests for the touched apps pass on Postgres 17 with lint and type checks clean and any strict xfail for the item removed; the reviewer (not the author) signs; register_sync.py scores the test and the register row reads Built - tested / Pass; the full suite runs nightly and at the wave gate. | J26: backend/tests/test_plan_p_0503.py | K26: WI-018 | L26: Agent 1 | M26: 3 | N26: =ROUNDUP(M26*(1+'Plan guide'!$B$6),0) -> 4 | O26: 46364 | P26: 46367 | Q26: Done | R26: In progress | S26: In progress | T26: Not started | U26: Not started | V26: =IF(COUNTIF(Q26:U26,"Blocked")>0,"Blocked",IF(COUNTIF(Q26:U26,"Done")+COUNTIF(Q26:U26,"N/A")=5,"Done",IF(COUNTIF(Q26:U26,"Done")+COUNTIF(Q26:U26,"In progress")>0,"In progress","Not started"))) -> In progress | W26: =IF(5-COUNTIF(Q26:U26,"N/A")=0,1,COUNTIF(Q26:U26,"Done")/(5-COUNTIF(Q26:U26,"N/A"))) -> 0.2 | Z26: =IF(V26="Done",IF(Y26="",0,MAX(0,Y26-P26)),MAX(0,TODAY()-P26)) -> 0 | AA26: =IF(V26="Done","Done",IF(V26="Blocked","Red",IF(Z26>0,"Red",IF(AND(O26<=TODAY(),P26-TODAY()<=3,W26<0.5),"Amber","Green")))) -> Green | AB26: Gap: Blocked-credit classification is not added to the existing reporting/gstr2b.py reconciliation of uploaded 2B files; it only scores caller-supplied rows via /plan/gstr2b/score/ with a caller-supplied blocked_credit flag. | AC26: uncommitted working tree | AD26: Tests: tests/test_planwave_finish.py::test_2b_blocked_invoice_is_not_eligible [pass] | Code: backend/planwave/finish.py:score_2b_rows; backend/planwave/services.py:blocked_credit_match; backend/planwave/models.py:BlockedCreditRule | Run: pytest on SQLite 2026-10-05 (Postgres-only tests skipped) | AE26: =IFERROR(INDEX('Task Register'!$AJ$2:$AJ$771,MATCH(B26,'Task Register'!$A$2:$A$771,0)),"") -> Built - partial | AF26: =IFERROR(INDEX('Task Register'!$AU$2:$AU$771,MATCH(B26,'Task Register'!$A$2:$A$771,0)),"") -> Partial | AG26: feature | AH26: 7 | AI26: 33 | AJ26: P-0503
A27: WI-020 | B27: C-0607 | C27: Section 50 CGST Act delayed tax payment interest calculator (18% & 24% p.a.) | D27: 1 | E27: MVP | F27: GST & compliance | G27: Full stack | H27: Section 50 worksheet and CSV: 18% a year on late-paid tax, 24% on undue or excess ITC; net cash liability basis for late-filed returns (Rule 88B), unpaid amount otherwise. Rates in a dated table. No journal posted. CA confirms. | I27: Pass: Worksheet interest matches hand-calculated cases for each rate and period. Rejecting case: A date outside the rate table is refused; no journal is posted. Done means: tests for the touched apps pass on Postgres 17 with lint and type checks clean and any strict xfail for the item removed; the reviewer (not the author) signs; register_sync.py scores the test and the register row reads Built - tested / Pass; the full suite runs nightly and at the wave gate. | J27: backend/tests/test_plan_c_0607.py | K27: WI-070 | L27: Agent 2 | M27: 3 | N27: =ROUNDUP(M27*(1+'Plan guide'!$B$6),0) -> 4 | O27: 46363 | P27: 46366 | Q27: Done | R27: In progress | S27: In progress | T27: Not started | U27: Not started | V27: =IF(COUNTIF(Q27:U27,"Blocked")>0,"Blocked",IF(COUNTIF(Q27:U27,"Done")+COUNTIF(Q27:U27,"N/A")=5,"Done",IF(COUNTIF(Q27:U27,"Done")+COUNTIF(Q27:U27,"In progress")>0,"In progress","Not started"))) -> In progress | W27: =IF(5-COUNTIF(Q27:U27,"N/A")=0,1,COUNTIF(Q27:U27,"Done")/(5-COUNTIF(Q27:U27,"N/A"))) -> 0.2 | Z27: =IF(V27="Done",IF(Y27="",0,MAX(0,Y27-P27)),MAX(0,TODAY()-P27)) -> 0 | AA27: =IF(V27="Done","Done",IF(V27="Blocked","Red",IF(Z27>0,"Red",IF(AND(O27<=TODAY(),P27-TODAY()<=3,W27<0.5),"Amber","Green")))) -> Green | AB27: Gap: No Rule 88B net cash liability basis for late-filed returns; inputs are typed in rather than derived from late-paid tax; rates table has a single dated row; no CA-confirmation marker. | AC27: uncommitted working tree | AD27: Tests: tests/test_planwave_remaining.py::test_gst_rules [pass]; tests/test_planwave_finish.py::test_section_50_csv_posts_no_journal [pass] | Code: backend/planwave/services.py:section_50_interest; backend/planwave/finish.py:section_50_csv; backend/planwave/views.py:Section50CsvView | Run: pytest on SQLite 2026-10-05 (Postgres-only tests skipped) | AE27: =IFERROR(INDEX('Task Register'!$AJ$2:$AJ$771,MATCH(B27,'Task Register'!$A$2:$A$771,0)),"") -> Built - partial | AF27: =IFERROR(INDEX('Task Register'!$AU$2:$AU$771,MATCH(B27,'Task Register'!$A$2:$A$771,0)),"") -> Partial | AG27: feature | AI27: 34 | AJ27: C-0607
A28: WI-021 | B28: X-0527 | C28: Automatic debtor account freeze and delivery block on chronic overdue accounts | D28: 1 | E28: MVP | F28: Payments & credit | G28: Full stack | H28: Keep the existing hold and add the chronic rule; the stricter one wins. Existing, always on: invoice complete blocks when credit_limit > 0 and exposure plus the invoice exceeds it. Existing, opt-in and default off (auto_credit_hold_on_severe_overdue): invoice complete also blocks stop_credit (outstanding above the limit) or overdue_severe (any overdue and either 90-plus days or average payment delay over 21 days). New, per company: any invoice over 60 days overdue and an over-60-day total of at least Rs 5,000 also blocks credit-sale completion, sales-order confirmation and delivery challans. Cash and prepaid still allowed. Single-use unlock code valid 24 h from the Owner or credit-override role, with reason. | I28: Pass: Chronic customers are blocked from credit sale, order confirmation and challan; cash sales pass; the existing hold still works. Rejecting case: A used or expired unlock code fails; a blocked customer cannot take a credit sale. Done means: tests for the touched apps pass on Postgres 17 with lint and type checks clean and any strict xfail for the item removed; the reviewer (not the author) signs; register_sync.py scores the test and the register row reads Built - tested / Pass; the full suite runs nightly and at the wave gate. | J28: backend/tests/test_plan_x_0527.py | L28: Agent 2 | M28: 3 | N28: =ROUNDUP(M28*(1+'Plan guide'!$B$6),0) -> 4 | O28: 46367 | P28: 46372 | Q28: Done | R28: In progress | S28: In progress | T28: Not started | U28: Not started | V28: =IF(COUNTIF(Q28:U28,"Blocked")>0,"Blocked",IF(COUNTIF(Q28:U28,"Done")+COUNTIF(Q28:U28,"N/A")=5,"Done",IF(COUNTIF(Q28:U28,"Done")+COUNTIF(Q28:U28,"In progress")>0,"In progress","Not started"))) -> In progress | W28: =IF(5-COUNTIF(Q28:U28,"N/A")=0,1,COUNTIF(Q28:U28,"Done")/(5-COUNTIF(Q28:U28,"N/A"))) -> 0.2 | Z28: =IF(V28="Done",IF(Y28="",0,MAX(0,Y28-P28)),MAX(0,TODAY()-P28)) -> 0 | AA28: =IF(V28="Done","Done",IF(V28="Blocked","Red",IF(Z28>0,"Red",IF(AND(O28<=TODAY(),P28-TODAY()<=3,W28<0.5),"Amber","Green")))) -> Green | AB28: Gap: No API or role check for issuing the unlock code (issue_unlock accepts any user, no Owner/credit-override check, no endpoint). No per-company toggle for the chronic rule. Delivery challan block is wired but only the sales-order path is tested. | AC28: uncommitted working tree | AD28: Tests: tests/test_planwave_remaining.py::test_chronic_credit_blocks_and_unlock_is_single_use [pass]; tests/test_planwave_remaining.py::test_chronic_order_and_challan_are_blocked [pass]; tests/test_code_review_2026_10_05.py::test_a_paid_old_invoice_does_not_hold_credit [pass] | Code: backend/planwave/services.py:chronic_overdue; backend/planwave/services.py:assert_chronic_credit_allowed; backend/planwave/services.py:issue_unlock; backend/sales/services.py:complete_invoice credit hold | Run: pytest on SQLite 2026-10-05 (Postgres-only tests skipped) | AE28: =IFERROR(INDEX('Task Register'!$AJ$2:$AJ$771,MATCH(B28,'Task Register'!$A$2:$A$771,0)),"") -> Built - partial | AF28: =IFERROR(INDEX('Task Register'!$AU$2:$AU$771,MATCH(B28,'Task Register'!$A$2:$A$771,0)),"") -> Partial | AG28: feature | AH28: 8 | AI28: 35 | AJ28: X-0527
A29: WI-022 | B29: X-0530 | C29: Handle bounced / dishonoured cheque: reverse invoice settlement, add bank fee, alert owner | D29: 1 | E29: MVP | F29: Payments & credit | G29: Full stack | H29: Bounce voids the receipt, reverses allocations, debits the bank fee (amount from the bank memo, suggested Rs 500) to the customer and alerts the owner. GST on the recovery is a configurable flag, default off. | I29: Pass: A bounce voids the receipt, reopens the invoice, debits the fee and alerts the owner. Rejecting case: Bouncing the same receipt twice is rejected. Done means: tests for the touched apps pass on Postgres 17 with lint and type checks clean and any strict xfail for the item removed; the reviewer (not the author) signs; register_sync.py scores the test and the register row reads Built - tested / Pass; the full suite runs nightly and at the wave gate. | J29: backend/tests/test_plan_x_0530.py | L29: Agent 1 | M29: 3 | N29: =ROUNDUP(M29*(1+'Plan guide'!$B$6),0) -> 4 | O29: 46370 | P29: 46373 | Q29: Done | R29: In progress | S29: In progress | T29: Not started | U29: Not started | V29: =IF(COUNTIF(Q29:U29,"Blocked")>0,"Blocked",IF(COUNTIF(Q29:U29,"Done")+COUNTIF(Q29:U29,"N/A")=5,"Done",IF(COUNTIF(Q29:U29,"Done")+COUNTIF(Q29:U29,"In progress")>0,"In progress","Not started"))) -> In progress | W29: =IF(5-COUNTIF(Q29:U29,"N/A")=0,1,COUNTIF(Q29:U29,"Done")/(5-COUNTIF(Q29:U29,"N/A"))) -> 0.2 | Z29: =IF(V29="Done",IF(Y29="",0,MAX(0,Y29-P29)),MAX(0,TODAY()-P29)) -> 0 | AA29: =IF(V29="Done","Done",IF(V29="Blocked","Red",IF(Z29>0,"Red",IF(AND(O29<=TODAY(),P29-TODAY()<=3,W29<0.5),"Amber","Green")))) -> Green | AB29: Gap: No configurable GST-on-recovery flag (code explicitly adds no GST); no Rs 500 suggestion (fee defaults to 0 unless a bank charge or cheque_dishonour_charge flag is set); owner alert is sent but no test asserts it. | AC29: uncommitted working tree | AD29: Tests: tests/test_bug_open_pay.py::test_bug_pay_001_fee_post_is_atomic [pass]; tests/test_cheque_payment.py::test_cheque_receipt_starts_pending_and_bounce_voids [pass]; tests/test_cheque_payment.py::test_set_cheque_status_http_bounce_voids [pass] | Code: backend/payments/services.py:PaymentService.set_cheque_status; backend/payments/services.py:PaymentService._post_dishonour_fee | Run: pytest on SQLite 2026-10-05 (Postgres-only tests skipped) | AE29: =IFERROR(INDEX('Task Register'!$AJ$2:$AJ$771,MATCH(B29,'Task Register'!$A$2:$A$771,0)),"") -> Built - partial | AF29: =IFERROR(INDEX('Task Register'!$AU$2:$AU$771,MATCH(B29,'Task Register'!$A$2:$A$771,0)),"") -> Partial | AG29: feature | AI29: 36 | AJ29: X-0530
A30: WI-023 | B30: X-0713 | C30: Customer cheque dishonoured after 5 days: automated accounting reversal and bank fee debit | D30: 1 | E30: MVP | F30: Payments & credit | G30: Full stack | H30: Section 138 notice draft only: written demand within 30 days of the bank memo, 15 days to pay, dates from the memo, disclaimer that an advocate must review. No reversal or fee logic here. | I30: Pass: Notice draft carries the right dates and the disclaimer. Rejecting case: Dates outside the statutory sequence are refused. Done means: tests for the touched apps pass on Postgres 17 with lint and type checks clean and any strict xfail for the item removed; the reviewer (not the author) signs; register_sync.py scores the test and the register row reads Built - tested / Pass; the full suite runs nightly and at the wave gate. | J30: backend/tests/test_plan_x_0713.py | K30: WI-022 | L30: Agent 1 | M30: 2 | N30: =ROUNDUP(M30*(1+'Plan guide'!$B$6),0) -> 3 | O30: 46377 | P30: 46379 | Q30: Done | R30: Done | S30: Done | T30: In progress | U30: Done | V30: =IF(COUNTIF(Q30:U30,"Blocked")>0,"Blocked",IF(COUNTIF(Q30:U30,"Done")+COUNTIF(Q30:U30,"N/A")=5,"Done",IF(COUNTIF(Q30:U30,"Done")+COUNTIF(Q30:U30,"In progress")>0,"In progress","Not started"))) -> In progress | W30: =IF(5-COUNTIF(Q30:U30,"N/A")=0,1,COUNTIF(Q30:U30,"Done")/(5-COUNTIF(Q30:U30,"N/A"))) -> 0.8 | Z30: =IF(V30="Done",IF(Y30="",0,MAX(0,Y30-P30)),MAX(0,TODAY()-P30)) -> 0 | AA30: =IF(V30="Done","Done",IF(V30="Blocked","Red",IF(Z30>0,"Red",IF(AND(O30<=TODAY(),P30-TODAY()<=3,W30<0.5),"Amber","Green")))) -> Green | AB30: Agent review done; human sign-off pending | AC30: uncommitted working tree | AD30: Tests: tests/test_planwave_remaining.py::test_section_138_dates_and_provision [pass]; tests/test_bug_open_pay.py::test_bug_pay_001_bounce_levies_fee_and_stores_section_138_notice [pass] | Code: backend/payments/services.py:_store_section_138_notice; backend/planwave/services.py:section_138_dates | Run: pytest on SQLite 2026-10-05 (Postgres-only tests skipped) | AE30: =IFERROR(INDEX('Task Register'!$AJ$2:$AJ$771,MATCH(B30,'Task Register'!$A$2:$A$771,0)),"") -> Built - tested | AF30: =IFERROR(INDEX('Task Register'!$AU$2:$AU$771,MATCH(B30,'Task Register'!$A$2:$A$771,0)),"") -> Pass | AG30: feature | AH30: 4 | AI30: 36 | AJ30: X-0713
A31: WI-024 | B31: X-0707 | C31: Supplier cancelled GSTIN after issuing invoice: system blocks ITC and alerts purchase team | D31: 1 | E31: MVP | F31: Payments & credit | G31: Full stack | H31: Status from the existing alert source plus a manual flag. New ITC blocked for invoices dated on or after the cancellation effective date; availed ITC flagged for the CA; payment hold overridable by Owner or Accountant with reason, audited. | I31: Pass: Invoices dated on or after the cancellation date are excluded from ITC and the supplier payment is held. Rejecting case: A held payment cannot post without an authorised override. Done means: tests for the touched apps pass on Postgres 17 with lint and type checks clean and any strict xfail for the item removed; the reviewer (not the author) signs; register_sync.py scores the test and the register row reads Built - tested / Pass; the full suite runs nightly and at the wave gate. | J31: backend/tests/test_plan_x_0707.py | L31: Agent 2 | M31: 3 | N31: =ROUNDUP(M31*(1+'Plan guide'!$B$6),0) -> 4 | O31: 46373 | P31: 46378 | Q31: Done | R31: In progress | S31: In progress | T31: Not started | U31: Not started | V31: =IF(COUNTIF(Q31:U31,"Blocked")>0,"Blocked",IF(COUNTIF(Q31:U31,"Done")+COUNTIF(Q31:U31,"N/A")=5,"Done",IF(COUNTIF(Q31:U31,"Done")+COUNTIF(Q31:U31,"In progress")>0,"In progress","Not started"))) -> In progress | W31: =IF(5-COUNTIF(Q31:U31,"N/A")=0,1,COUNTIF(Q31:U31,"Done")/(5-COUNTIF(Q31:U31,"N/A"))) -> 0.2 | Z31: =IF(V31="Done",IF(Y31="",0,MAX(0,Y31-P31)),MAX(0,TODAY()-P31)) -> 0 | AA31: =IF(V31="Done","Done",IF(V31="Blocked","Red",IF(Z31>0,"Red",IF(AND(O31<=TODAY(),P31-TODAY()<=3,W31<0.5),"Amber","Green")))) -> Green | AB31: Gap: Cancelled status comes only from a manual Supplier.gstin_cancelled_on field; it is not fed from the existing GSTIN alert source. Availed ITC is not flagged for the CA (only blocked_credit on new bills). Purchase-team alert has no direct test assertion. | AC31: uncommitted working tree | AD31: Tests: tests/test_planwave_remaining.py::test_cancelled_gstin_holds_supplier_payment [pass]; tests/test_planwave_remaining.py::test_cancelled_supplier_gstin_blocks_purchase [pass]; tests/test_planwave_finish.py::test_gstin_override_is_audited [pass]; tests/test_planwave_finish.py::test_sales_staff_cannot_release_a_gstin_hold [pass] | Code: backend/planwave/services.py:supplier_itc_blocked; backend/planwave/services.py:assert_gstin_override; backend/payments/services.py:create_supplier_payment gstin hold; backend/purchases/services.py:complete gstin_cancelled_on check | Run: pytest on SQLite 2026-10-05 (Postgres-only tests skipped) | AE31: =IFERROR(INDEX('Task Register'!$AJ$2:$AJ$771,MATCH(B31,'Task Register'!$A$2:$A$771,0)),"") -> Built - partial | AF31: =IFERROR(INDEX('Task Register'!$AU$2:$AU$771,MATCH(B31,'Task Register'!$A$2:$A$771,0)),"") -> Partial | AG31: feature | AH31: 5 | AI31: 37 | AJ31: X-0707
A32: WI-025 | B32: P-0128 | C32: Approve important business actions | D32: 1 | E32: MVP | F32: Payments & credit | G32: Full stack | H32: Queue for: credit-limit override, stock adjustment above threshold, invoice cancel or amend after completion, discount above threshold, return or credit note above threshold, backdated posting or period reopen, supplier payment above threshold, write-off, bulk import commit. Default approver Owner, configurable per action; no self-approval except a flagged Owner exception; 72 h expiry counts as rejected. | I32: Pass: Listed actions enter the queue; approve and reject are audited; requests expire at 72 h. Rejecting case: A requester cannot approve their own request (except the flagged Owner exception). Done means: tests for the touched apps pass on Postgres 17 with lint and type checks clean and any strict xfail for the item removed; the reviewer (not the author) signs; register_sync.py scores the test and the register row reads Built - tested / Pass; the full suite runs nightly and at the wave gate. | J32: backend/tests/test_plan_p_0128.py | L32: Agent 2 | M32: 5 | N32: =ROUNDUP(M32*(1+'Plan guide'!$B$6),0) -> 6 | O32: 46379 | P32: 46387 | Q32: Done | R32: In progress | S32: In progress | T32: Not started | U32: Not started | V32: =IF(COUNTIF(Q32:U32,"Blocked")>0,"Blocked",IF(COUNTIF(Q32:U32,"Done")+COUNTIF(Q32:U32,"N/A")=5,"Done",IF(COUNTIF(Q32:U32,"Done")+COUNTIF(Q32:U32,"In progress")>0,"In progress","Not started"))) -> In progress | W32: =IF(5-COUNTIF(Q32:U32,"N/A")=0,1,COUNTIF(Q32:U32,"Done")/(5-COUNTIF(Q32:U32,"N/A"))) -> 0.2 | Z32: =IF(V32="Done",IF(Y32="",0,MAX(0,Y32-P32)),MAX(0,TODAY()-P32)) -> 0 | AA32: =IF(V32="Done","Done",IF(V32="Blocked","Red",IF(Z32>0,"Red",IF(AND(O32<=TODAY(),P32-TODAY()<=3,W32<0.5),"Amber","Green")))) -> Green | AB32: Gap: The approval queue is enforced only for invoice cancel and large stock adjustment; not wired for credit-limit override (separate unlock), invoice amend, discount, returns/credit notes, backdating/period reopen, supplier payment, write-off or bulk import commit; no per-action configurable approver; no web UI. | AC32: uncommitted working tree | AD32: Tests: tests/test_plan_partials.py::test_completed_invoice_cancel_waits_for_a_second_owner [pass]; tests/test_planwave_remaining.py::test_large_stock_adjustment_waits_for_a_second_user [pass]; tests/test_planwave_remaining.py::test_approvals_reject_self_and_expired_tokens [pass] | Code: backend/planwave/models.py:ApprovalRequest; backend/planwave/services.py:_consume_approval; backend/sales/views.py:SalesInvoiceViewSet.cancel; backend/inventory/views.py | Run: pytest on SQLite 2026-10-05 (Postgres-only tests skipped) | AE32: =IFERROR(INDEX('Task Register'!$AJ$2:$AJ$771,MATCH(B32,'Task Register'!$A$2:$A$771,0)),"") -> Built - partial | AF32: =IFERROR(INDEX('Task Register'!$AU$2:$AU$771,MATCH(B32,'Task Register'!$A$2:$A$771,0)),"") -> Partial | AG32: feature | AI32: 38 | AJ32: P-0128
A33: WI-026 | B33: P-0152 | C33: Adjust stock with authorization | D33: 1 | E33: MVP | F33: Payments & credit | G33: Full stack | H33: Stock adjustment needs a second user when value at cost is Rs 10,000 or more, or quantity is 10% or more of on-hand (both configurable per company), using the approval queue. | I33: Pass: An adjustment over threshold needs a second user's approval. Rejecting case: The same user approving is rejected. Done means: tests for the touched apps pass on Postgres 17 with lint and type checks clean and any strict xfail for the item removed; the reviewer (not the author) signs; register_sync.py scores the test and the register row reads Built - tested / Pass; the full suite runs nightly and at the wave gate. | J33: backend/tests/test_plan_p_0152.py | K33: WI-025 | L33: Agent 1 | M33: 2 | N33: =ROUNDUP(M33*(1+'Plan guide'!$B$6),0) -> 3 | O33: 46391 | P33: 46393 | Q33: Done | R33: Done | S33: Done | T33: In progress | U33: Done | V33: =IF(COUNTIF(Q33:U33,"Blocked")>0,"Blocked",IF(COUNTIF(Q33:U33,"Done")+COUNTIF(Q33:U33,"N/A")=5,"Done",IF(COUNTIF(Q33:U33,"Done")+COUNTIF(Q33:U33,"In progress")>0,"In progress","Not started"))) -> In progress | W33: =IF(5-COUNTIF(Q33:U33,"N/A")=0,1,COUNTIF(Q33:U33,"Done")/(5-COUNTIF(Q33:U33,"N/A"))) -> 0.8 | Z33: =IF(V33="Done",IF(Y33="",0,MAX(0,Y33-P33)),MAX(0,TODAY()-P33)) -> 0 | AA33: =IF(V33="Done","Done",IF(V33="Blocked","Red",IF(Z33>0,"Red",IF(AND(O33<=TODAY(),P33-TODAY()<=3,W33<0.5),"Amber","Green")))) -> Green | AB33: Agent review done; human sign-off pending | AC33: uncommitted working tree | AD33: Tests: tests/test_planwave_remaining.py::test_large_stock_adjustment_waits_for_a_second_user [pass]; tests/test_planwave_remaining.py::test_approvals_reject_self_and_expired_tokens [pass]; tests/test_code_review_2026_10_05.py::test_an_adjustment_on_zero_stock_needs_a_second_person [pass] | Code: backend/planwave/services.py:stock_adjustment_needs_second; backend/inventory/views.py; backend/planwave/services.py:consume_stock_approval | Run: pytest on SQLite 2026-10-05 (Postgres-only tests skipped) | AE33: =IFERROR(INDEX('Task Register'!$AJ$2:$AJ$771,MATCH(B33,'Task Register'!$A$2:$A$771,0)),"") -> Built - tested | AF33: =IFERROR(INDEX('Task Register'!$AU$2:$AU$771,MATCH(B33,'Task Register'!$A$2:$A$771,0)),"") -> Pass | AG33: feature | AI33: 39 | AJ33: P-0152
A34: WI-027 | B34: X-0702 | C34: Credit limit breach during bulk invoice: owner sends temporary one-time authorization token | D34: 1 | E34: MVP | F34: Payments & credit | G34: Full stack | H34: In-app single-use 15-minute token bound to the invoice batch and requester (WhatsApp only when the freeze flag is flipped). No response: over-limit invoices stay Awaiting approval, others proceed, expiry counts as rejected, never auto-approved. | I34: Pass: A single-use 15-minute token releases the over-limit invoices. Rejecting case: A reused or expired token fails; no response leaves the invoice held, never approved. Done means: tests for the touched apps pass on Postgres 17 with lint and type checks clean and any strict xfail for the item removed; the reviewer (not the author) signs; register_sync.py scores the test and the register row reads Built - tested / Pass; the full suite runs nightly and at the wave gate. | J34: backend/tests/test_plan_x_0702.py | K34: WI-025 | L34: Agent 2 | M34: 3 | N34: =ROUNDUP(M34*(1+'Plan guide'!$B$6),0) -> 4 | O34: 46391 | P34: 46394 | Q34: Done | R34: In progress | S34: In progress | T34: Not started | U34: Not started | V34: =IF(COUNTIF(Q34:U34,"Blocked")>0,"Blocked",IF(COUNTIF(Q34:U34,"Done")+COUNTIF(Q34:U34,"N/A")=5,"Done",IF(COUNTIF(Q34:U34,"Done")+COUNTIF(Q34:U34,"In progress")>0,"In progress","Not started"))) -> In progress | W34: =IF(5-COUNTIF(Q34:U34,"N/A")=0,1,COUNTIF(Q34:U34,"Done")/(5-COUNTIF(Q34:U34,"N/A"))) -> 0.2 | Z34: =IF(V34="Done",IF(Y34="",0,MAX(0,Y34-P34)),MAX(0,TODAY()-P34)) -> 0 | AA34: =IF(V34="Done","Done",IF(V34="Blocked","Red",IF(Z34>0,"Red",IF(AND(O34<=TODAY(),P34-TODAY()<=3,W34<0.5),"Amber","Green")))) -> Green | AB34: Gap: Token service exists (single-use, 15 minutes, bound to batch) but is not wired into any bulk invoice or credit-limit flow and has no endpoint. Not bound to the requester on redeem. No Awaiting approval invoice status, so over-limit invoices are not held while others proceed. Expiry path is not asserted. | AC34: uncommitted working tree | AD34: Tests: tests/test_planwave_remaining.py::test_approvals_reject_self_and_expired_tokens [pass]; tests/test_code_review_2026_10_05.py::test_a_blank_token_cannot_redeem_an_ordinary_approval [pass] | Code: backend/planwave/services.py:issue_credit_token; backend/planwave/services.py:redeem_credit_token; backend/planwave/models.py:ApprovalRequest | Run: pytest on SQLite 2026-10-05 (Postgres-only tests skipped) | AE34: =IFERROR(INDEX('Task Register'!$AJ$2:$AJ$771,MATCH(B34,'Task Register'!$A$2:$A$771,0)),"") -> Built - partial | AF34: =IFERROR(INDEX('Task Register'!$AU$2:$AU$771,MATCH(B34,'Task Register'!$A$2:$A$771,0)),"") -> Partial | AG34: feature | AI34: 40 | AJ34: X-0702
A35: WI-028 | B35: R-0636 | C35: Sub-200ms POS billing checkout latency under continuous queue load | D35: 1 | E35: MVP | F35: Inventory & POS | G35: Backend | H35: Benchmark harness and recorded baseline for POS checkout complete (tax, stock and ledger included): 2 vCPU 4 GB container, local Postgres, 20,000 SKUs, 3-line cart, p95. Runs on its own nightly job, never in the pull-request run. | I35: Pass: Harness produces a repeatable p95 on the stated hardware and catalogue and records the baseline. Rejecting case: A run that regresses more than 15% against the baseline fails the nightly job (not the pull-request run). Done means: the benchmark job (outside the pull-request run) records the p95 against baseline and target and the report is attached as evidence; the reviewer signs. | J35: backend/perf/test_r_0636_benchmark.py (nightly job) | L35: Agent 1 | M35: 2 | N35: =ROUNDUP(M35*(1+'Plan guide'!$B$6),0) -> 3 | O35: 46394 | P35: 46398 | Q35: Done | R35: In progress | S35: In progress | T35: Not started | U35: Not started | V35: =IF(COUNTIF(Q35:U35,"Blocked")>0,"Blocked",IF(COUNTIF(Q35:U35,"Done")+COUNTIF(Q35:U35,"N/A")=5,"Done",IF(COUNTIF(Q35:U35,"Done")+COUNTIF(Q35:U35,"In progress")>0,"In progress","Not started"))) -> In progress | W35: =IF(5-COUNTIF(Q35:U35,"N/A")=0,1,COUNTIF(Q35:U35,"Done")/(5-COUNTIF(Q35:U35,"N/A"))) -> 0.2 | Z35: =IF(V35="Done",IF(Y35="",0,MAX(0,Y35-P35)),MAX(0,TODAY()-P35)) -> 0 | AA35: =IF(V35="Done","Done",IF(V35="Blocked","Red",IF(Z35>0,"Red",IF(AND(O35<=TODAY(),P35-TODAY()<=3,W35<0.5),"Amber","Green")))) -> Green | AB35: Gap: baseline_p95_ms is null so no baseline has been recorded; the benchmark skips unless POS_BENCH=1; the 2 vCPU / 4 GB container constraint is not evidenced. | AC35: uncommitted working tree | AD35: Tests: perf/test_r_0636_benchmark.py::test_checkout_p95_on_the_catalogue [not in run]; tests/test_plan_above_items.py::test_checkout_p95_regression_is_fifteen_percent [pass] | Code: backend/perf/checkout_bench.py:exceeds_baseline; backend/perf/test_r_0636_benchmark.py; qos/evidence/pos_checkout_baseline.json; .github/workflows/pos-checkout-nightly.yml | Run: pytest on SQLite 2026-10-05 (Postgres-only tests skipped) | AE35: =IFERROR(INDEX('Task Register'!$AJ$2:$AJ$771,MATCH(B35,'Task Register'!$A$2:$A$771,0)),"") -> Built - partial | AF35: =IFERROR(INDEX('Task Register'!$AU$2:$AU$771,MATCH(B35,'Task Register'!$A$2:$A$771,0)),"") -> Partial | AG35: perf | AI35: 41 | AJ35: R-0636
A36: WI-029 | B36: X-0514 | C36: Update transport vehicle number / Transporter ID on active E-Way Bill during breakdown | D36: 1 | E36: MVP | F36: GST & compliance | G36: Full stack | H36: Part B vehicle update as a stub action against the GSP adapter interface with a fake provider, plus stored vehicle history, behind GSP_LIVE_ENABLED=0. Live use needs sandbox credentials and a freeze exception. | I36: Pass: Part B update stored with history; stub action works against the fake provider. Rejecting case: Update on a cancelled or expired bill is refused. Done means: tests for the touched apps pass on Postgres 17 with lint and type checks clean and any strict xfail for the item removed; the reviewer (not the author) signs; register_sync.py scores the test and the register row reads Built - tested / Pass; the full suite runs nightly and at the wave gate. | J36: backend/tests/test_plan_x_0514.py | L36: Agent 2 | M36: 2 | N36: =ROUNDUP(M36*(1+'Plan guide'!$B$6),0) -> 3 | O36: 46395 | P36: 46399 | Q36: Done | R36: Done | S36: Done | T36: In progress | U36: Done | V36: =IF(COUNTIF(Q36:U36,"Blocked")>0,"Blocked",IF(COUNTIF(Q36:U36,"Done")+COUNTIF(Q36:U36,"N/A")=5,"Done",IF(COUNTIF(Q36:U36,"Done")+COUNTIF(Q36:U36,"In progress")>0,"In progress","Not started"))) -> In progress | W36: =IF(5-COUNTIF(Q36:U36,"N/A")=0,1,COUNTIF(Q36:U36,"Done")/(5-COUNTIF(Q36:U36,"N/A"))) -> 0.8 | Z36: =IF(V36="Done",IF(Y36="",0,MAX(0,Y36-P36)),MAX(0,TODAY()-P36)) -> 0 | AA36: =IF(V36="Done","Done",IF(V36="Blocked","Red",IF(Z36>0,"Red",IF(AND(O36<=TODAY(),P36-TODAY()<=3,W36<0.5),"Amber","Green")))) -> Green | AB36: Agent review done; human sign-off pending | AC36: uncommitted working tree | AD36: Tests: tests/test_bug_open_gst.py::test_bug_gst_001_part_b_and_validity [pass]; tests/test_planwave_remaining.py::test_eway_stub_and_distance [pass]; tests/test_code_review_2026_10_05.py::test_a_live_eway_provider_refuses_a_part_b_update_it_cannot_send [pass] | Code: backend/sales/einvoice_eway_actions.py:update_eway_vehicle; backend/core/services/gsp_adapters.py:update_vehicle; backend/planwave/services.py:record_eway_stub; backend/config/settings.py:GSP_LIVE_ENABLED | Run: pytest on SQLite 2026-10-05 (Postgres-only tests skipped) | AE36: =IFERROR(INDEX('Task Register'!$AJ$2:$AJ$771,MATCH(B36,'Task Register'!$A$2:$A$771,0)),"") -> Built - tested | AF36: =IFERROR(INDEX('Task Register'!$AU$2:$AU$771,MATCH(B36,'Task Register'!$A$2:$A$771,0)),"") -> Pass | AG36: feature | AI36: 42 | AJ36: X-0514
A37: WI-030 | B37: X-0515 | C37: Extend E-Way Bill validity before expiry due to transit delay or traffic accident | D37: 1 | E37: MVP | F37: GST & compliance | G37: Full stack | H37: Validity extension as a stub action plus stored fields, same adapter and flag rule as X-0514. | I37: Pass: Extension stored and allowed inside its window. Rejecting case: Extension outside the window is refused. Done means: tests for the touched apps pass on Postgres 17 with lint and type checks clean and any strict xfail for the item removed; the reviewer (not the author) signs; register_sync.py scores the test and the register row reads Built - tested / Pass; the full suite runs nightly and at the wave gate. | J37: backend/tests/test_plan_x_0515.py | K37: WI-029 | L37: Agent 1 | M37: 2 | N37: =ROUNDUP(M37*(1+'Plan guide'!$B$6),0) -> 3 | O37: 46401 | P37: 46405 | Q37: Done | R37: Done | S37: Done | T37: In progress | U37: Done | V37: =IF(COUNTIF(Q37:U37,"Blocked")>0,"Blocked",IF(COUNTIF(Q37:U37,"Done")+COUNTIF(Q37:U37,"N/A")=5,"Done",IF(COUNTIF(Q37:U37,"Done")+COUNTIF(Q37:U37,"In progress")>0,"In progress","Not started"))) -> In progress | W37: =IF(5-COUNTIF(Q37:U37,"N/A")=0,1,COUNTIF(Q37:U37,"Done")/(5-COUNTIF(Q37:U37,"N/A"))) -> 0.8 | Z37: =IF(V37="Done",IF(Y37="",0,MAX(0,Y37-P37)),MAX(0,TODAY()-P37)) -> 0 | AA37: =IF(V37="Done","Done",IF(V37="Blocked","Red",IF(Z37>0,"Red",IF(AND(O37<=TODAY(),P37-TODAY()<=3,W37<0.5),"Amber","Green")))) -> Green | AB37: Agent review done; human sign-off pending | AC37: uncommitted working tree | AD37: Tests: tests/test_bug_open_gst.py::test_bug_gst_001_part_b_and_validity [pass] | Code: backend/sales/einvoice_eway_actions.py:extend_eway_validity; backend/planwave/services.py:record_eway_stub; backend/planwave/models.py:EwayStubAction | Run: pytest on SQLite 2026-10-05 (Postgres-only tests skipped) | AE37: =IFERROR(INDEX('Task Register'!$AJ$2:$AJ$771,MATCH(B37,'Task Register'!$A$2:$A$771,0)),"") -> Built - tested | AF37: =IFERROR(INDEX('Task Register'!$AU$2:$AU$771,MATCH(B37,'Task Register'!$A$2:$A$771,0)),"") -> Pass | AG37: feature | AH37: 2 | AI37: 42 | AJ37: X-0515
A38: WI-031 | B38: C-0618 | C38: E-Way Bill Part B vehicle update statutory time-limit and multi-vehicle consignment splitting | D38: 1 | E38: MVP | F38: GST & compliance | G38: Full stack | H38: Part B time-limit alert and multi-vehicle split stored on the bill (stub action, GSP flag off). | I38: Pass: Alert fires at the Part B limit; split stored. Rejecting case: Split quantities above the consignment are rejected. Done means: tests for the touched apps pass on Postgres 17 with lint and type checks clean and any strict xfail for the item removed; the reviewer (not the author) signs; register_sync.py scores the test and the register row reads Built - tested / Pass; the full suite runs nightly and at the wave gate. | J38: backend/tests/test_plan_c_0618.py | K38: WI-029 | L38: Agent 2 | M38: 2 | N38: =ROUNDUP(M38*(1+'Plan guide'!$B$6),0) -> 3 | O38: 46401 | P38: 46405 | Q38: Done | R38: In progress | S38: In progress | T38: Not started | U38: Not started | V38: =IF(COUNTIF(Q38:U38,"Blocked")>0,"Blocked",IF(COUNTIF(Q38:U38,"Done")+COUNTIF(Q38:U38,"N/A")=5,"Done",IF(COUNTIF(Q38:U38,"Done")+COUNTIF(Q38:U38,"In progress")>0,"In progress","Not started"))) -> In progress | W38: =IF(5-COUNTIF(Q38:U38,"N/A")=0,1,COUNTIF(Q38:U38,"Done")/(5-COUNTIF(Q38:U38,"N/A"))) -> 0.2 | Z38: =IF(V38="Done",IF(Y38="",0,MAX(0,Y38-P38)),MAX(0,TODAY()-P38)) -> 0 | AA38: =IF(V38="Done","Done",IF(V38="Blocked","Red",IF(Z38>0,"Red",IF(AND(O38<=TODAY(),P38-TODAY()<=3,W38<0.5),"Amber","Green")))) -> Green | AB38: Gap: No Part B time-limit alert; multi-vehicle split is only a quantity check, with no per-vehicle storage and no test; no link to the e-way bill record or GSP flag. | AC38: uncommitted working tree | AD38: Tests: tests/test_planwave_remaining.py::test_eway_stub_and_distance [pass] | Code: backend/planwave/services.py:record_eway_stub; backend/planwave/models.py:EwayStubAction; backend/planwave/views.py:EwayStubView | Run: pytest on SQLite 2026-10-05 (Postgres-only tests skipped) | AE38: =IFERROR(INDEX('Task Register'!$AJ$2:$AJ$771,MATCH(B38,'Task Register'!$A$2:$A$771,0)),"") -> Built - partial | AF38: =IFERROR(INDEX('Task Register'!$AU$2:$AU$771,MATCH(B38,'Task Register'!$A$2:$A$771,0)),"") -> Partial | AG38: feature | AH38: 1 | AI38: 42 | AJ38: C-0618
A39: WI-032 | B39: C-0606 | C39: Rule 138 CGST Rules mandatory E-Way Bill distance calculation via postal PIN codes | D39: 1 | E39: MVP | F39: GST & compliance | G39: Full stack | H39: Validity computed from the user-entered distance using a configurable slab table with effective dates that the CA confirms. PIN-to-PIN distance lookup is deferred (needs NIC). | I39: Pass: Validity from distance matches the slab table at the 100, 200 and 201 km boundaries. Rejecting case: Zero or negative distance is rejected. Done means: tests for the touched apps pass on Postgres 17 with lint and type checks clean and any strict xfail for the item removed; the reviewer (not the author) signs; register_sync.py scores the test and the register row reads Built - tested / Pass; the full suite runs nightly and at the wave gate. | J39: backend/tests/test_plan_c_0606.py | L39: Agent 1 | M39: 2 | N39: =ROUNDUP(M39*(1+'Plan guide'!$B$6),0) -> 3 | O39: 46406 | P39: 46408 | Q39: Done | R39: In progress | S39: In progress | T39: Not started | U39: Not started | V39: =IF(COUNTIF(Q39:U39,"Blocked")>0,"Blocked",IF(COUNTIF(Q39:U39,"Done")+COUNTIF(Q39:U39,"N/A")=5,"Done",IF(COUNTIF(Q39:U39,"Done")+COUNTIF(Q39:U39,"In progress")>0,"In progress","Not started"))) -> In progress | W39: =IF(5-COUNTIF(Q39:U39,"N/A")=0,1,COUNTIF(Q39:U39,"Done")/(5-COUNTIF(Q39:U39,"N/A"))) -> 0.2 | Z39: =IF(V39="Done",IF(Y39="",0,MAX(0,Y39-P39)),MAX(0,TODAY()-P39)) -> 0 | AA39: =IF(V39="Done","Done",IF(V39="Blocked","Red",IF(Z39>0,"Red",IF(AND(O39<=TODAY(),P39-TODAY()<=3,W39<0.5),"Amber","Green")))) -> Green | AB39: Gap: Validity is a hard-coded ceil(distance/100); no configurable slab table, no effective dates, no CA confirmation. | AC39: uncommitted working tree | AD39: Tests: tests/test_planwave_remaining.py::test_eway_stub_and_distance [pass] | Code: backend/planwave/services.py:eway_validity_days | Run: pytest on SQLite 2026-10-05 (Postgres-only tests skipped) | AE39: =IFERROR(INDEX('Task Register'!$AJ$2:$AJ$771,MATCH(B39,'Task Register'!$A$2:$A$771,0)),"") -> Built - partial | AF39: =IFERROR(INDEX('Task Register'!$AU$2:$AU$771,MATCH(B39,'Task Register'!$A$2:$A$771,0)),"") -> Partial | AG39: feature | AH39: 3 | AI39: 42 | AJ39: C-0606
A40: WI-071 | C40: CA sign-off of the Rule 11(g) coverage map | D40: 1 | E40: MVP | F40: Audit & integrity | G40: Process | H40: CA reviews the coverage map and certification export and signs. Lead time five working days. | I40: Pass: Signed note from the CA attached as evidence. Rejecting case: No sign-off by M1: milestone marked 'pilot with documented residual'. Done means: written sign-off from the external reviewer is attached as evidence. | K40: WI-003, WI-070 | L40: CA / external | M40: 1 | N40: =ROUNDUP(M40*(1+'Plan guide'!$B$6),0) -> 2 | O40: 46321 | P40: 46325 | Q40: Not started | R40: N/A | S40: N/A | T40: Not started | U40: N/A | V40: =IF(COUNTIF(Q40:U40,"Blocked")>0,"Blocked",IF(COUNTIF(Q40:U40,"Done")+COUNTIF(Q40:U40,"N/A")=5,"Done",IF(COUNTIF(Q40:U40,"Done")+COUNTIF(Q40:U40,"In progress")>0,"In progress","Not started"))) -> Not started | W40: =IF(5-COUNTIF(Q40:U40,"N/A")=0,1,COUNTIF(Q40:U40,"Done")/(5-COUNTIF(Q40:U40,"N/A"))) -> 0 | Z40: =IF(V40="Done",IF(Y40="",0,MAX(0,Y40-P40)),MAX(0,TODAY()-P40)) -> 0 | AA40: =IF(V40="Done","Done",IF(V40="Blocked","Red",IF(Z40>0,"Red",IF(AND(O40<=TODAY(),P40-TODAY()<=3,W40<0.5),"Amber","Green")))) -> Green | AB40: Gap: No file records a CA review or signature of the coverage map or certification export. | AC40: uncommitted working tree | AD40: Run: pytest on SQLite 2026-10-05 (Postgres-only tests skipped) | AG40: external | AI40: 7 | AJ40: CA-SIGN
A41: WI-033 | C41: Concurrent customer edits: field merge plus version check | D41: 1 | E41: MVP | F41: Audit & integrity | G41: Backend | H41: PATCH merges changed fields under a row lock so concurrent edits of different fields both persist; PUT requires a version and a stale write returns 409 with the current value. Create the register row when starting. Remove the strict xfail in test_register_race_gaps.py. | I41: Pass: PATCH merges concurrent field edits and PUT with the current version succeeds. Rejecting case: A stale PUT returns 409 and changes nothing (the strict xfail test now passes). Done means: tests for the touched apps pass on Postgres 17 with lint and type checks clean and any strict xfail for the item removed; the reviewer (not the author) signs; register_sync.py scores the test and the register row reads Built - tested / Pass; the full suite runs nightly and at the wave gate. | J41: backend/tests/test_register_race_gaps.py; backend/tests/test_plan_cust_lock.py | L41: Agent 2 | M41: 2 | N41: =ROUNDUP(M41*(1+'Plan guide'!$B$6),0) -> 3 | O41: 46406 | P41: 46408 | Q41: Done | R41: Done | S41: In progress | T41: In progress | U41: Not started | V41: =IF(COUNTIF(Q41:U41,"Blocked")>0,"Blocked",IF(COUNTIF(Q41:U41,"Done")+COUNTIF(Q41:U41,"N/A")=5,"Done",IF(COUNTIF(Q41:U41,"Done")+COUNTIF(Q41:U41,"In progress")>0,"In progress","Not started"))) -> In progress | W41: =IF(5-COUNTIF(Q41:U41,"N/A")=0,1,COUNTIF(Q41:U41,"Done")/(5-COUNTIF(Q41:U41,"N/A"))) -> 0.4 | Z41: =IF(V41="Done",IF(Y41="",0,MAX(0,Y41-P41)),MAX(0,TODAY()-P41)) -> 0 | AA41: =IF(V41="Done","Done",IF(V41="Blocked","Red",IF(Z41>0,"Red",IF(AND(O41<=TODAY(),P41-TODAY()<=3,W41<0.5),"Amber","Green")))) -> Green | AB41: Agent review done; human sign-off pending | AC41: uncommitted working tree | AD41: Tests: tests/test_register_race_gaps.py::test_concurrent_customer_edits_of_different_fields_do_not_lose_updates [skip]; tests/test_planwave_remaining.py::test_stale_customer_put_returns_409 [pass] | Code: backend/masters/views.py:CustomerViewSet.update; backend/masters/views.py:CustomerViewSet.perform_update | Run: pytest on SQLite 2026-10-05 (Postgres-only tests skipped) | AG41: feature | AI41: 11, 43 | AJ41: CUST-LOCK
A42: WI-034 | B42: S-0579 | C42: Production check and alert for the nightly audit-chain seal | D42: 1 | E42: MVP | F42: Platform & reliability | G42: Infra | H42: The seal task is already on the Celery beat at 02:40. A verify failure only logs an error (Sentry if configured); nothing notices a night that never ran, and there is no seal email. Add a missed-run check that logs an error and sends the Owner the same in-app notification the nightly invariant task already uses. | I42: Pass: A missed night logs an error and creates an in-app notification for the Owner. Rejecting case: Disabling the scheduled task in a test makes that alert fire; a successful seal does not. Done means: the drill is executed on a non-production copy and its timings and steps are attached; the reviewer signs. | J42: drill log in qos/evidence/ (restore or alert drill) | L42: Agent 1 | M42: 0.5 | N42: =ROUNDUP(M42*(1+'Plan guide'!$B$6),0) -> 1 | O42: 46409 | P42: 46409 | Q42: Done | R42: In progress | S42: In progress | T42: Not started | U42: Not started | V42: =IF(COUNTIF(Q42:U42,"Blocked")>0,"Blocked",IF(COUNTIF(Q42:U42,"Done")+COUNTIF(Q42:U42,"N/A")=5,"Done",IF(COUNTIF(Q42:U42,"Done")+COUNTIF(Q42:U42,"In progress")>0,"In progress","Not started"))) -> In progress | W42: =IF(5-COUNTIF(Q42:U42,"N/A")=0,1,COUNTIF(Q42:U42,"Done")/(5-COUNTIF(Q42:U42,"N/A"))) -> 0.2 | Z42: =IF(V42="Done",IF(Y42="",0,MAX(0,Y42-P42)),MAX(0,TODAY()-P42)) -> 0 | AA42: =IF(V42="Done","Done",IF(V42="Blocked","Red",IF(Z42>0,"Red",IF(AND(O42<=TODAY(),P42-TODAY()<=3,W42<0.5),"Amber","Green")))) -> Green | AB42: Gap: No drill log in qos/evidence; the task-level gap path (running seal_audit_chain_task with a stale heartbeat) is not tested directly. | AC42: uncommitted working tree | AD42: Tests: tests/test_plan_audit_seal_session.py::test_seal_gap_alerts_the_owner_and_a_fresh_run_does_not [pass]; tests/test_plan_partials.py::test_missed_audit_seal_notifies_the_owner [pass] | Code: backend/core/tasks.py:seal_audit_chain_task; backend/core/tasks.py:alert_missed_seal; backend/core/tasks.py:seal_gap_seconds | Run: pytest on SQLite 2026-10-05 (Postgres-only tests skipped) | AE42: =IFERROR(INDEX('Task Register'!$AJ$2:$AJ$771,MATCH(B42,'Task Register'!$A$2:$A$771,0)),"") -> Built - tested | AF42: =IFERROR(INDEX('Task Register'!$AU$2:$AU$771,MATCH(B42,'Task Register'!$A$2:$A$771,0)),"") -> Partial | AG42: infra drill | AI42: 21 | AJ42: S-0579
A43: WI-028b | C43: Optimise POS checkout toward the 200 ms p95 target | D43: 1 | E43: MVP | F43: Inventory & POS | G43: Backend | H43: Timeboxed to 5 days after the baseline from R-0636: profile, fix the top costs, record the new p95. If the target is not met the remaining gap is reported, not hidden. | I43: Pass: p95 at or below 200 ms, or the remaining gap and its causes are reported. Rejecting case: A change that worsens p95 against the new baseline is rejected by the nightly job. Done means: the benchmark job (outside the pull-request run) records the p95 against baseline and target and the report is attached as evidence; the reviewer signs. | J43: backend/perf/test_r_0636b_benchmark.py (nightly job) | K43: WI-028 | L43: Agent 2 | M43: 5 | N43: =ROUNDUP(M43*(1+'Plan guide'!$B$6),0) -> 6 | O43: 46409 | P43: 46419 | Q43: Not started | R43: Not started | S43: Not started | T43: Not started | U43: Not started | V43: =IF(COUNTIF(Q43:U43,"Blocked")>0,"Blocked",IF(COUNTIF(Q43:U43,"Done")+COUNTIF(Q43:U43,"N/A")=5,"Done",IF(COUNTIF(Q43:U43,"Done")+COUNTIF(Q43:U43,"In progress")>0,"In progress","Not started"))) -> Not started | W43: =IF(5-COUNTIF(Q43:U43,"N/A")=0,1,COUNTIF(Q43:U43,"Done")/(5-COUNTIF(Q43:U43,"N/A"))) -> 0 | Z43: =IF(V43="Done",IF(Y43="",0,MAX(0,Y43-P43)),MAX(0,TODAY()-P43)) -> 0 | AA43: =IF(V43="Done","Done",IF(V43="Blocked","Red",IF(Z43>0,"Red",IF(AND(O43<=TODAY(),P43-TODAY()<=3,W43<0.5),"Amber","Green")))) -> Green | AB43: Gap: backend/perf/test_r_0636b_benchmark.py does not exist; baseline_p95_ms is still null so no baseline, profile or new p95 has been recorded. | AC43: uncommitted working tree | AD43: Code: backend/perf/test_r_0636_benchmark.py; qos/evidence/pos_checkout_baseline.json | Run: pytest on SQLite 2026-10-05 (Postgres-only tests skipped) | AG43: perf | AH43: 9 | AI43: 17, 41 | AJ43: R-0636b
A44: WI-035 | C44: Wave 1 verification: full suite on Postgres, register sync, drift check, MVP gate review | D44: 1 | E44: MVP | F44: Quality gate | G44: Process | H44: Run the full backend suite on Postgres, register_sync.py and register_drift.py, recalculate the workbook and review every wave item against its pass condition. | I44: Pass: Run the full backend suite on Postgres, register_sync.py and register_drift.py, recalculate the workbook and review every wave item against its pass condition.. Rejecting case: invalid input, a wrong-tenant request and a user without permission are each rejected, each with a test. Done means: full backend suite green on Postgres, register_sync.py and register_drift.py clean, workbook recalculated with 0 formula errors, every item in the wave Done and reviewed. | K44: WI-068, WI-069, WI-070, WI-001, WI-002, WI-003, WI-004, WI-005, WI-006, WI-007, WI-008, WI-009, WI-010, WI-011, WI-012, WI-013, WI-014, WI-015, WI-016, WI-017, WI-018, WI-019, WI-020, WI-021, WI-022, WI-023, WI-024, WI-025, WI-026, WI-027, WI-028, WI-029, WI-030, WI-031, WI-032, WI-071, WI-033, WI-034, WI-028b | L44: Agent 1 | M44: 2 | N44: =ROUNDUP(M44*(1+'Plan guide'!$B$6),0) -> 3 | O44: 46421 | P44: 46423 | Q44: N/A | R44: N/A | S44: Not started | T44: Not started | U44: Not started | V44: =IF(COUNTIF(Q44:U44,"Blocked")>0,"Blocked",IF(COUNTIF(Q44:U44,"Done")+COUNTIF(Q44:U44,"N/A")=5,"Done",IF(COUNTIF(Q44:U44,"Done")+COUNTIF(Q44:U44,"In progress")>0,"In progress","Not started"))) -> Not started | W44: =IF(5-COUNTIF(Q44:U44,"N/A")=0,1,COUNTIF(Q44:U44,"Done")/(5-COUNTIF(Q44:U44,"N/A"))) -> 0 | Z44: =IF(V44="Done",IF(Y44="",0,MAX(0,Y44-P44)),MAX(0,TODAY()-P44)) -> 0 | AA44: =IF(V44="Done","Done",IF(V44="Blocked","Red",IF(Z44>0,"Red",IF(AND(O44<=TODAY(),P44-TODAY()<=3,W44<0.5),"Amber","Green")))) -> Green | AB44: Gap: No wave 1 verification record or MVP gate review artefact exists in the repo. | AC44: uncommitted working tree | AD44: Run: pytest on SQLite 2026-10-05 (Postgres-only tests skipped) | AG44: gate | AJ44: VER-1
A45: WI-036 | B45: P-0046 | C45: Search medicines while billing | D45: 2 | E45: Pilot | F45: Inventory & POS | G45: Full stack | H45: Optional salt, composition and manufacturer fields on products, searchable at billing with a trigram index inside the checkout latency budget (query-budget test). | I45: Pass: Optional salt, composition and manufacturer fields on products, searchable at billing with a trigram index inside the checkout latency budget (query-budget test).. Rejecting case: invalid input, a wrong-tenant request and a user without permission are each rejected, each with a test. Done means: tests for the touched apps pass on Postgres 17 with lint and type checks clean and any strict xfail for the item removed; the reviewer (not the author) signs; register_sync.py scores the test and the register row reads Built - tested / Pass; the full suite runs nightly and at the wave gate. | J45: backend/tests/test_plan_p_0046.py | K45: WI-035 | L45: Agent 1 | M45: 2 | N45: =ROUNDUP(M45*(1+'Plan guide'!$B$6),0) -> 3 | O45: 46427 | P45: 46429 | Q45: Done | R45: In progress | S45: Not started | T45: Not started | U45: Not started | V45: =IF(COUNTIF(Q45:U45,"Blocked")>0,"Blocked",IF(COUNTIF(Q45:U45,"Done")+COUNTIF(Q45:U45,"N/A")=5,"Done",IF(COUNTIF(Q45:U45,"Done")+COUNTIF(Q45:U45,"In progress")>0,"In progress","Not started"))) -> In progress | W45: =IF(5-COUNTIF(Q45:U45,"N/A")=0,1,COUNTIF(Q45:U45,"Done")/(5-COUNTIF(Q45:U45,"N/A"))) -> 0.2 | Z45: =IF(V45="Done",IF(Y45="",0,MAX(0,Y45-P45)),MAX(0,TODAY()-P45)) -> 0 | AA45: =IF(V45="Done","Done",IF(V45="Blocked","Red",IF(Z45>0,"Red",IF(AND(O45<=TODAY(),P45-TODAY()<=3,W45<0.5),"Amber","Green")))) -> Green | AB45: Gap: No test searches by salt, composition or manufacturer; no query-budget test within the checkout latency budget. | AC45: uncommitted working tree | AD45: Code: backend/masters/models.py:Product; backend/masters/migrations/0028_product_medicine_trgm.py; backend/masters/views.py | Run: pytest on SQLite 2026-10-05 (Postgres-only tests skipped) | AE45: =IFERROR(INDEX('Task Register'!$AJ$2:$AJ$771,MATCH(B45,'Task Register'!$A$2:$A$771,0)),"") -> Built - partial | AF45: =IFERROR(INDEX('Task Register'!$AU$2:$AU$771,MATCH(B45,'Task Register'!$A$2:$A$771,0)),"") -> Partial | AG45: feature | AI45: 44 | AJ45: P-0046
A46: WI-037 | B46: P-0052 | C46: Create bulk sales invoices | D46: 2 | E46: Pilot | F46: Inventory & POS | G46: Full stack | H46: CSV with invoice ref, customer, dates, SKU or barcode, quantity, rate, discount %, warehouse, notes; dry run, then per-invoice atomic commit; any bad row rejects that invoice and is reported by row; 2,000-row cap; file hash makes re-upload idempotent. | I46: Pass: CSV with invoice ref, customer, dates, SKU or barcode, quantity, rate, discount %, warehouse, notes; dry run, then per-invoice atomic commit; any bad row rejects that invoice and is reported by row; 2,000-row cap; file hash makes re-upload idempotent.. Rejecting case: invalid input, a wrong-tenant request and a user without permission are each rejected, each with a test. Done means: tests for the touched apps pass on Postgres 17 with lint and type checks clean and any strict xfail for the item removed; the reviewer (not the author) signs; register_sync.py scores the test and the register row reads Built - tested / Pass; the full suite runs nightly and at the wave gate. | J46: backend/tests/test_plan_p_0052.py | K46: WI-035 | L46: Agent 2 | M46: 4 | N46: =ROUNDUP(M46*(1+'Plan guide'!$B$6),0) -> 5 | O46: 46427 | P46: 46433 | Q46: Done | R46: In progress | S46: In progress | T46: Not started | U46: Not started | V46: =IF(COUNTIF(Q46:U46,"Blocked")>0,"Blocked",IF(COUNTIF(Q46:U46,"Done")+COUNTIF(Q46:U46,"N/A")=5,"Done",IF(COUNTIF(Q46:U46,"Done")+COUNTIF(Q46:U46,"In progress")>0,"In progress","Not started"))) -> In progress | W46: =IF(5-COUNTIF(Q46:U46,"N/A")=0,1,COUNTIF(Q46:U46,"Done")/(5-COUNTIF(Q46:U46,"N/A"))) -> 0.2 | Z46: =IF(V46="Done",IF(Y46="",0,MAX(0,Y46-P46)),MAX(0,TODAY()-P46)) -> 0 | AA46: =IF(V46="Done","Done",IF(V46="Blocked","Red",IF(Z46>0,"Red",IF(AND(O46<=TODAY(),P46-TODAY()<=3,W46<0.5),"Amber","Green")))) -> Green | AB46: Gap: CSV columns for invoice date and due date, barcode lookup and warehouse are not handled (SKU only, no warehouse or dates). The 2,000-row cap is not tested. Idempotent re-upload is not asserted after a committed run. | AC46: uncommitted working tree | AD46: Tests: tests/test_planwave_finish.py::test_bulk_commit_rejects_only_the_bad_invoice [pass]; tests/test_planwave_remaining.py::test_bulk_import_and_tally_map [pass] | Code: backend/planwave/services.py:parse_bulk_invoices; backend/planwave/finish.py:commit_bulk_invoices; backend/planwave/views.py:BulkCommitView | Run: pytest on SQLite 2026-10-05 (Postgres-only tests skipped) | AE46: =IFERROR(INDEX('Task Register'!$AJ$2:$AJ$771,MATCH(B46,'Task Register'!$A$2:$A$771,0)),"") -> Built - partial | AF46: =IFERROR(INDEX('Task Register'!$AU$2:$AU$771,MATCH(B46,'Task Register'!$A$2:$A$771,0)),"") -> Partial | AG46: feature | AI46: 45 | AJ46: P-0052
A47: WI-038 | B47: P-0081 | C47: Transfer stock between godowns | D47: 2 | E47: Pilot | F47: Inventory & POS | G47: Full stack | H47: In-transit location per transfer: dispatch moves source to in-transit, receipt moves it to destination; partial receipt with shortage or damage reason; no ledger entry for same-company, same-GSTIN transfers. | I47: Pass: In-transit location per transfer: dispatch moves source to in-transit, receipt moves it to destination; partial receipt with shortage or damage reason; no ledger entry for same-company, same-GSTIN transfers.. Rejecting case: invalid input, a wrong-tenant request and a user without permission are each rejected, each with a test. Done means: tests for the touched apps pass on Postgres 17 with lint and type checks clean and any strict xfail for the item removed; the reviewer (not the author) signs; register_sync.py scores the test and the register row reads Built - tested / Pass; the full suite runs nightly and at the wave gate. | J47: backend/tests/test_plan_p_0081.py | K47: WI-035 | L47: Agent 1 | M47: 6 | N47: =ROUNDUP(M47*(1+'Plan guide'!$B$6),0) -> 8 | O47: 46430 | P47: 46441 | Q47: Done | R47: Done | S47: Done | T47: In progress | U47: Done | V47: =IF(COUNTIF(Q47:U47,"Blocked")>0,"Blocked",IF(COUNTIF(Q47:U47,"Done")+COUNTIF(Q47:U47,"N/A")=5,"Done",IF(COUNTIF(Q47:U47,"Done")+COUNTIF(Q47:U47,"In progress")>0,"In progress","Not started"))) -> In progress | W47: =IF(5-COUNTIF(Q47:U47,"N/A")=0,1,COUNTIF(Q47:U47,"Done")/(5-COUNTIF(Q47:U47,"N/A"))) -> 0.8 | Z47: =IF(V47="Done",IF(Y47="",0,MAX(0,Y47-P47)),MAX(0,TODAY()-P47)) -> 0 | AA47: =IF(V47="Done","Done",IF(V47="Blocked","Red",IF(Z47>0,"Red",IF(AND(O47<=TODAY(),P47-TODAY()<=3,W47<0.5),"Amber","Green")))) -> Green | AB47: Agent review done; human sign-off pending | AC47: uncommitted working tree | AD47: Tests: tests/test_bug_wave3.py::test_bug_inv_001_transfer_holds_stock_in_transit [pass]; tests/test_plan_partials.py::test_partial_receipt_records_the_shortage [pass]; tests/test_code_review_2026_10_05_b.py::test_cancel_after_a_short_receipt_restores_stock_and_clears_transit [pass] | Code: backend/inventory/services.py:StockTransferService._move; backend/inventory/services.py:StockTransferService.in_transit_warehouse; backend/inventory/models.py:StockTransferLine | Run: pytest on SQLite 2026-10-05 (Postgres-only tests skipped) | AE47: =IFERROR(INDEX('Task Register'!$AJ$2:$AJ$771,MATCH(B47,'Task Register'!$A$2:$A$771,0)),"") -> Built - tested | AF47: =IFERROR(INDEX('Task Register'!$AU$2:$AU$771,MATCH(B47,'Task Register'!$A$2:$A$771,0)),"") -> Pass | AG47: feature | AI47: 46 | AJ47: P-0081
A48: WI-039 | B48: P-0089 | C48: View all shops from one dashboard | D48: 2 | E48: Pilot | F48: Inventory & POS | G48: Full stack | H48: Per-warehouse breakdown and switching inside one company on the dashboard, inside the dashboard query budget (test). Multi-company GSTIN stays out of scope. | I48: Pass: Per-warehouse breakdown and switching inside one company on the dashboard, inside the dashboard query budget (test). Multi-company GSTIN stays out of scope.. Rejecting case: invalid input, a wrong-tenant request and a user without permission are each rejected, each with a test. Done means: tests for the touched apps pass on Postgres 17 with lint and type checks clean and any strict xfail for the item removed; the reviewer (not the author) signs; register_sync.py scores the test and the register row reads Built - tested / Pass; the full suite runs nightly and at the wave gate. | J48: backend/tests/test_plan_p_0089.py | K48: WI-035 | L48: Agent 2 | M48: 5 | N48: =ROUNDUP(M48*(1+'Plan guide'!$B$6),0) -> 6 | O48: 46434 | P48: 46441 | Q48: Done | R48: In progress | S48: In progress | T48: Not started | U48: Not started | V48: =IF(COUNTIF(Q48:U48,"Blocked")>0,"Blocked",IF(COUNTIF(Q48:U48,"Done")+COUNTIF(Q48:U48,"N/A")=5,"Done",IF(COUNTIF(Q48:U48,"Done")+COUNTIF(Q48:U48,"In progress")>0,"In progress","Not started"))) -> In progress | W48: =IF(5-COUNTIF(Q48:U48,"N/A")=0,1,COUNTIF(Q48:U48,"Done")/(5-COUNTIF(Q48:U48,"N/A"))) -> 0.2 | Z48: =IF(V48="Done",IF(Y48="",0,MAX(0,Y48-P48)),MAX(0,TODAY()-P48)) -> 0 | AA48: =IF(V48="Done","Done",IF(V48="Blocked","Red",IF(Z48>0,"Red",IF(AND(O48<=TODAY(),P48-TODAY()<=3,W48<0.5),"Amber","Green")))) -> Green | AB48: Gap: Only an API listing on-hand and reserved stock per warehouse; no web DashboardPage integration or warehouse switching; no query-budget test. | AC48: uncommitted working tree | AD48: Tests: tests/test_planwave_finish.py::test_godown_dashboard_lists_the_default_warehouse [pass] | Code: backend/planwave/finish.py:godown_dashboard; backend/planwave/views.py:GodownDashboardView | Run: pytest on SQLite 2026-10-05 (Postgres-only tests skipped) | AE48: =IFERROR(INDEX('Task Register'!$AJ$2:$AJ$771,MATCH(B48,'Task Register'!$A$2:$A$771,0)),"") -> Built - partial | AF48: =IFERROR(INDEX('Task Register'!$AU$2:$AU$771,MATCH(B48,'Task Register'!$A$2:$A$771,0)),"") -> Partial | AG48: feature | AI48: 47 | AJ48: P-0089
A49: WI-040 | B49: P-0119 | C49: Identify overdue payments | D49: 2 | E49: Pilot | F49: Payments & credit | G49: Full stack | H49: Report only: interest exposure (default 18% a year simple, per company) and suggested provision by age (0-60 d 0%, 61-90 d 5%, 91-180 d 25%, 181-365 d 50%, over 365 d 100%). No posting. | I49: Pass: Report only: interest exposure (default 18% a year simple, per company) and suggested provision by age (0-60 d 0%, 61-90 d 5%, 91-180 d 25%, 181-365 d 50%, over 365 d 100%). No posting.. Rejecting case: invalid input, a wrong-tenant request and a user without permission are each rejected, each with a test. Done means: tests for the touched apps pass on Postgres 17 with lint and type checks clean and any strict xfail for the item removed; the reviewer (not the author) signs; register_sync.py scores the test and the register row reads Built - tested / Pass; the full suite runs nightly and at the wave gate. | J49: backend/tests/test_plan_p_0119.py | K49: WI-035 | L49: Agent 1 | M49: 3 | N49: =ROUNDUP(M49*(1+'Plan guide'!$B$6),0) -> 4 | O49: 46442 | P49: 46447 | Q49: Done | R49: Done | S49: Done | T49: In progress | U49: Done | V49: =IF(COUNTIF(Q49:U49,"Blocked")>0,"Blocked",IF(COUNTIF(Q49:U49,"Done")+COUNTIF(Q49:U49,"N/A")=5,"Done",IF(COUNTIF(Q49:U49,"Done")+COUNTIF(Q49:U49,"In progress")>0,"In progress","Not started"))) -> In progress | W49: =IF(5-COUNTIF(Q49:U49,"N/A")=0,1,COUNTIF(Q49:U49,"Done")/(5-COUNTIF(Q49:U49,"N/A"))) -> 0.8 | Z49: =IF(V49="Done",IF(Y49="",0,MAX(0,Y49-P49)),MAX(0,TODAY()-P49)) -> 0 | AA49: =IF(V49="Done","Done",IF(V49="Blocked","Red",IF(Z49>0,"Red",IF(AND(O49<=TODAY(),P49-TODAY()<=3,W49<0.5),"Amber","Green")))) -> Green | AB49: Agent review done; human sign-off pending | AC49: uncommitted working tree | AD49: Tests: tests/test_planwave_remaining.py::test_provision_interest_anomaly_cashflow_and_2b [pass]; tests/test_planwave_finish.py::test_overdue_report_suggests_a_provision [pass]; tests/test_code_review_2026_10_05.py::test_overdue_report_lists_only_what_is_still_owed [pass] | Code: backend/planwave/finish.py:overdue_report; backend/planwave/services.py:suggest_provision; backend/planwave/services.py:interest_exposure; backend/planwave/views.py:OverdueReportView | Run: pytest on SQLite 2026-10-05 (Postgres-only tests skipped) | AE49: =IFERROR(INDEX('Task Register'!$AJ$2:$AJ$771,MATCH(B49,'Task Register'!$A$2:$A$771,0)),"") -> Built - tested | AF49: =IFERROR(INDEX('Task Register'!$AU$2:$AU$771,MATCH(B49,'Task Register'!$A$2:$A$771,0)),"") -> Pass | AG49: feature | AI49: 48 | AJ49: P-0119
A50: WI-041 | B50: P-0180 | C50: Configure branches/godowns | D50: 2 | E50: Pilot | F50: Inventory & POS | G50: Full stack | H50: Users map to many warehouses with one default; contact person and phone required, email optional. | I50: Pass: Users map to many warehouses with one default; contact person and phone required, email optional.. Rejecting case: invalid input, a wrong-tenant request and a user without permission are each rejected, each with a test. Done means: tests for the touched apps pass on Postgres 17 with lint and type checks clean and any strict xfail for the item removed; the reviewer (not the author) signs; register_sync.py scores the test and the register row reads Built - tested / Pass; the full suite runs nightly and at the wave gate. | J50: backend/tests/test_plan_p_0180.py | K50: WI-035 | L50: Agent 2 | M50: 2 | N50: =ROUNDUP(M50*(1+'Plan guide'!$B$6),0) -> 3 | O50: 46442 | P50: 46444 | Q50: Done | R50: In progress | S50: Not started | T50: Not started | U50: Not started | V50: =IF(COUNTIF(Q50:U50,"Blocked")>0,"Blocked",IF(COUNTIF(Q50:U50,"Done")+COUNTIF(Q50:U50,"N/A")=5,"Done",IF(COUNTIF(Q50:U50,"Done")+COUNTIF(Q50:U50,"In progress")>0,"In progress","Not started"))) -> In progress | W50: =IF(5-COUNTIF(Q50:U50,"N/A")=0,1,COUNTIF(Q50:U50,"Done")/(5-COUNTIF(Q50:U50,"N/A"))) -> 0.2 | Z50: =IF(V50="Done",IF(Y50="",0,MAX(0,Y50-P50)),MAX(0,TODAY()-P50)) -> 0 | AA50: =IF(V50="Done","Done",IF(V50="Blocked","Red",IF(Z50>0,"Red",IF(AND(O50<=TODAY(),P50-TODAY()<=3,W50<0.5),"Amber","Green")))) -> Green | AB50: Gap: Contact name and phone are blank=True (not required); the user-to-warehouse mapping is stored but nothing enforces or reads it; no test covers the mapping or the default rule. | AC50: uncommitted working tree | AD50: Code: backend/planwave/models.py:UserWarehouseAccess; backend/planwave/finish.py:grant_warehouse; backend/inventory/serializers.py:WarehouseSerializer | Run: pytest on SQLite 2026-10-05 (Postgres-only tests skipped) | AE50: =IFERROR(INDEX('Task Register'!$AJ$2:$AJ$771,MATCH(B50,'Task Register'!$A$2:$A$771,0)),"") -> Built - partial | AF50: =IFERROR(INDEX('Task Register'!$AU$2:$AU$771,MATCH(B50,'Task Register'!$A$2:$A$771,0)),"") -> Partial | AG50: feature | AI50: 49 | AJ50: P-0180
A51: WI-042 | B51: X-0706 | C51: Inter-godown transfer vehicle breakdown: goods transshipped to new tempo with E-Way Bill Part B update | D51: 2 | E51: Pilot | F51: GST & compliance | G51: Full stack | H51: Transfer vehicle-breakdown Part B workflow on stock transfers as a stub action plus stored fields (GSP flag off). | I51: Pass: Transfer Part B update stored. Rejecting case: Update on a completed transfer is refused. Done means: tests for the touched apps pass on Postgres 17 with lint and type checks clean and any strict xfail for the item removed; the reviewer (not the author) signs; register_sync.py scores the test and the register row reads Built - tested / Pass; the full suite runs nightly and at the wave gate. | J51: backend/tests/test_plan_x_0706.py | K51: WI-029, WI-038, WI-035 | L51: Agent 2 | M51: 3 | N51: =ROUNDUP(M51*(1+'Plan guide'!$B$6),0) -> 4 | O51: 46447 | P51: 46450 | Q51: Done | R51: In progress | S51: Not started | T51: Not started | U51: Not started | V51: =IF(COUNTIF(Q51:U51,"Blocked")>0,"Blocked",IF(COUNTIF(Q51:U51,"Done")+COUNTIF(Q51:U51,"N/A")=5,"Done",IF(COUNTIF(Q51:U51,"Done")+COUNTIF(Q51:U51,"In progress")>0,"In progress","Not started"))) -> In progress | W51: =IF(5-COUNTIF(Q51:U51,"N/A")=0,1,COUNTIF(Q51:U51,"Done")/(5-COUNTIF(Q51:U51,"N/A"))) -> 0.2 | Z51: =IF(V51="Done",IF(Y51="",0,MAX(0,Y51-P51)),MAX(0,TODAY()-P51)) -> 0 | AA51: =IF(V51="Done","Done",IF(V51="Blocked","Red",IF(Z51>0,"Red",IF(AND(O51<=TODAY(),P51-TODAY()<=3,W51<0.5),"Amber","Green")))) -> Green | AB51: Gap: TRANSFER_PART_B action and history exist only on the generic stub; no fields on stock transfers, no transfer workflow, no test for TRANSFER_PART_B. | AC51: uncommitted working tree | AD51: Code: backend/planwave/models.py:EwayStubAction; backend/planwave/services.py:record_eway_stub | Run: pytest on SQLite 2026-10-05 (Postgres-only tests skipped) | AE51: =IFERROR(INDEX('Task Register'!$AJ$2:$AJ$771,MATCH(B51,'Task Register'!$A$2:$A$771,0)),"") -> Built - partial | AF51: =IFERROR(INDEX('Task Register'!$AU$2:$AU$771,MATCH(B51,'Task Register'!$A$2:$A$771,0)),"") -> Not run | AG51: feature | AI51: 42 | AJ51: X-0706
A52: WI-043 | B52: UX-0596 | C52: Clear destructive action confirmation dialog with explicit entity name typing | D52: 2 | E52: Pilot | F52: Inventory & POS | G52: Web | H52: Typed-confirmation input on destructive dialogs. | I52: Pass: The destructive button stays disabled until the exact text is typed. Rejecting case: A wrong or partial text keeps it disabled; keyboard and screen-reader path tested. Done means: Vitest (and Playwright where there is a flow) pass, tsc -b and ESLint report zero errors, the accessibility check is clean, and register_sync.py scores the web test; the backend suite is not required; the reviewer signs. | J52: web/src/__tests__/ux_0596.test.tsx | K52: WI-068, WI-035 | L52: Agent 1 | M52: 1 | N52: =ROUNDUP(M52*(1+'Plan guide'!$B$6),0) -> 2 | O52: 46448 | P52: 46449 | Q52: Done | R52: In progress | S52: In progress | T52: Not started | U52: Not started | V52: =IF(COUNTIF(Q52:U52,"Blocked")>0,"Blocked",IF(COUNTIF(Q52:U52,"Done")+COUNTIF(Q52:U52,"N/A")=5,"Done",IF(COUNTIF(Q52:U52,"Done")+COUNTIF(Q52:U52,"In progress")>0,"In progress","Not started"))) -> In progress | W52: =IF(5-COUNTIF(Q52:U52,"N/A")=0,1,COUNTIF(Q52:U52,"Done")/(5-COUNTIF(Q52:U52,"N/A"))) -> 0.2 | Z52: =IF(V52="Done",IF(Y52="",0,MAX(0,Y52-P52)),MAX(0,TODAY()-P52)) -> 0 | AA52: =IF(V52="Done","Done",IF(V52="Blocked","Red",IF(Z52>0,"Red",IF(AND(O52<=TODAY(),P52-TODAY()<=3,W52<0.5),"Amber","Green")))) -> Green | AB52: Gap: Typed confirmation is opt-in and used on only a few dialogs (contracts, campaigns, growth widgets); other destructive dialogs do not require typing. Planned file web/src/__tests__/ux_0596.test.tsx does not exist. | AC52: uncommitted working tree | AD52: Tests: web/src/components/ConfirmDialog.test.tsx::BUG-UI-005 requires the document number before a destructive confirm [not in run]; web/src/components/ConfirmDialog.test.tsx::asks for nothing to be typed unless the caller opts in [not in run] | Code: web/src/components/ConfirmDialog.tsx:requireTyped; web/src/pages/contracts/ContractsPage.tsx; web/src/pages/crm/CampaignsPage.tsx | Run: pytest on SQLite 2026-10-05 (Postgres-only tests skipped) | AE52: =IFERROR(INDEX('Task Register'!$AJ$2:$AJ$771,MATCH(B52,'Task Register'!$A$2:$A$771,0)),"") -> Built - partial | AF52: =IFERROR(INDEX('Task Register'!$AU$2:$AU$771,MATCH(B52,'Task Register'!$A$2:$A$771,0)),"") -> Partial | AG52: web | AI52: 9 | AJ52: UX-0596
A53: WI-044 | B53: I-0651 | C53: ESC/POS thermal receipt printer direct driver integration via USB, Bluetooth & Network | D53: 2 | E53: Pilot | F53: Inventory & POS | G53: Web + device | H53: Network ESC/POS printer through a print bridge, with PDF fallback. Bluetooth deferred. Verified on a real network ESC/POS printer (for example Epson TM-T82) that you provide. | I53: Pass: Network ESC/POS printer through a print bridge, with PDF fallback. Bluetooth deferred. Verified on a real network ESC/POS printer (for example Epson TM-T82) that you provide.. Rejecting case: invalid input keeps the action disabled; keyboard and screen-reader path tested. Done means: Vitest (and Playwright where there is a flow) pass, tsc -b and ESLint report zero errors, the accessibility check is clean, and register_sync.py scores the web test; the backend suite is not required; the reviewer signs. | J53: web/src/__tests__/i_0651.test.tsx | K53: WI-068, WI-035 | L53: Agent 1 | M53: 6 | N53: =ROUNDUP(M53*(1+'Plan guide'!$B$6),0) -> 8 | O53: 46450 | P53: 46461 | Q53: Done | R53: In progress | S53: In progress | T53: Not started | U53: Not started | V53: =IF(COUNTIF(Q53:U53,"Blocked")>0,"Blocked",IF(COUNTIF(Q53:U53,"Done")+COUNTIF(Q53:U53,"N/A")=5,"Done",IF(COUNTIF(Q53:U53,"Done")+COUNTIF(Q53:U53,"In progress")>0,"In progress","Not started"))) -> In progress | W53: =IF(5-COUNTIF(Q53:U53,"N/A")=0,1,COUNTIF(Q53:U53,"Done")/(5-COUNTIF(Q53:U53,"N/A"))) -> 0.2 | Z53: =IF(V53="Done",IF(Y53="",0,MAX(0,Y53-P53)),MAX(0,TODAY()-P53)) -> 0 | AA53: =IF(V53="Done","Done",IF(V53="Blocked","Red",IF(Z53>0,"Red",IF(AND(O53<=TODAY(),P53-TODAY()<=3,W53<0.5),"Amber","Green")))) -> Green | AB53: Gap: The print bridge always returns a PDF fallback and never sends to a network printer; the web path uses native/Bluetooth printEscPos and does not call plan/print; no web/src/__tests__/i_0651.test.tsx; no real printer verification. | AC53: uncommitted working tree | AD53: Tests: tests/test_planwave_finish.py::test_print_bridge_falls_back_without_a_printer [pass] | Code: backend/planwave/views.py:PrintBridgeView; web/src/pages/pos/printPosThermal.ts:printPosThermalOrWarn | Run: pytest on SQLite 2026-10-05 (Postgres-only tests skipped) | AE53: =IFERROR(INDEX('Task Register'!$AJ$2:$AJ$771,MATCH(B53,'Task Register'!$A$2:$A$771,0)),"") -> Built - partial | AF53: =IFERROR(INDEX('Task Register'!$AU$2:$AU$771,MATCH(B53,'Task Register'!$A$2:$A$771,0)),"") -> Partial | AG53: web | AI53: 50 | AJ53: I-0651
A54: WI-045 | B54: I-0655 | C54: Barcode scanner HID USB wedge and 2D QR camera barcode reader | D54: 2 | E54: Pilot | F54: Inventory & POS | G54: Web + device | H54: USB keyboard-wedge timing heuristic. Browser camera scanner deferred (mobile camera scan already works). | I54: Pass: USB keyboard-wedge timing heuristic. Browser camera scanner deferred (mobile camera scan already works).. Rejecting case: invalid input keeps the action disabled; keyboard and screen-reader path tested. Done means: Vitest (and Playwright where there is a flow) pass, tsc -b and ESLint report zero errors, the accessibility check is clean, and register_sync.py scores the web test; the backend suite is not required; the reviewer signs. | J54: web/src/__tests__/i_0655.test.tsx | K54: WI-068, WI-035 | L54: Agent 2 | M54: 2 | N54: =ROUNDUP(M54*(1+'Plan guide'!$B$6),0) -> 3 | O54: 46451 | P54: 46455 | Q54: Done | R54: Done | S54: In progress | T54: In progress | U54: Not started | V54: =IF(COUNTIF(Q54:U54,"Blocked")>0,"Blocked",IF(COUNTIF(Q54:U54,"Done")+COUNTIF(Q54:U54,"N/A")=5,"Done",IF(COUNTIF(Q54:U54,"Done")+COUNTIF(Q54:U54,"In progress")>0,"In progress","Not started"))) -> In progress | W54: =IF(5-COUNTIF(Q54:U54,"N/A")=0,1,COUNTIF(Q54:U54,"Done")/(5-COUNTIF(Q54:U54,"N/A"))) -> 0.4 | Z54: =IF(V54="Done",IF(Y54="",0,MAX(0,Y54-P54)),MAX(0,TODAY()-P54)) -> 0 | AA54: =IF(V54="Done","Done",IF(V54="Blocked","Red",IF(Z54>0,"Red",IF(AND(O54<=TODAY(),P54-TODAY()<=3,W54<0.5),"Amber","Green")))) -> Green | AB54: Agent review done; human sign-off pending | AC54: uncommitted working tree | AD54: Tests: web/src/pages/pos/scanInput.test.ts::BUG-UI-002 treats sub-50ms gaps as a scanner and slower typing as a person [not in run]; web/src/pages/pos/scanInput.test.ts::BUG-UI-003 reads a quantity prefix [not in run] | Code: web/src/pages/pos/scanInput.ts:isScannerBurst; web/src/pages/pos/PosPage.tsx | Run: pytest on SQLite 2026-10-05 (Postgres-only tests skipped) | AE54: =IFERROR(INDEX('Task Register'!$AJ$2:$AJ$771,MATCH(B54,'Task Register'!$A$2:$A$771,0)),"") -> Built - partial | AF54: =IFERROR(INDEX('Task Register'!$AU$2:$AU$771,MATCH(B54,'Task Register'!$A$2:$A$771,0)),"") -> Not run | AG54: web | AI54: 50 | AJ54: I-0655
A55: WI-046 | B55: SaaS-0669 | C55: Automated recurring subscription billing and GST tax invoice generation via Razorpay Subscriptions | D55: 2 | E55: Pilot | F55: Growth & SaaS | G55: Full stack | H55: Bizboard's own GST invoice to the tenant (our GSTIN, place of supply from the tenant's state), generated and emailed when a Cashfree or PayU payment is captured (freeze D3: sandbox, at least one of those two). No gateway SDK inside the invoice generator. Leave the existing Razorpay subscription reconciliation task alone. | I55: Pass: A captured Cashfree or PayU payment produces one GST invoice to the tenant and emails it. Rejecting case: A second delivery of the same capture does not create a second invoice; Razorpay reconciliation is unchanged. Done means: tests for the touched apps pass on Postgres 17 with lint and type checks clean and any strict xfail for the item removed; the reviewer (not the author) signs; register_sync.py scores the test and the register row reads Built - tested / Pass; the full suite runs nightly and at the wave gate. | J55: backend/tests/test_plan_saas_0669.py | K55: WI-035 | L55: Agent 2 | M55: 5 | N55: =ROUNDUP(M55*(1+'Plan guide'!$B$6),0) -> 6 | O55: 46456 | P55: 46463 | Q55: Done | R55: In progress | S55: In progress | T55: Not started | U55: Not started | V55: =IF(COUNTIF(Q55:U55,"Blocked")>0,"Blocked",IF(COUNTIF(Q55:U55,"Done")+COUNTIF(Q55:U55,"N/A")=5,"Done",IF(COUNTIF(Q55:U55,"Done")+COUNTIF(Q55:U55,"In progress")>0,"In progress","Not started"))) -> In progress | W55: =IF(5-COUNTIF(Q55:U55,"N/A")=0,1,COUNTIF(Q55:U55,"Done")/(5-COUNTIF(Q55:U55,"N/A"))) -> 0.2 | Z55: =IF(V55="Done",IF(Y55="",0,MAX(0,Y55-P55)),MAX(0,TODAY()-P55)) -> 0 | AA55: =IF(V55="Done","Done",IF(V55="Blocked","Red",IF(Z55>0,"Red",IF(AND(O55<=TODAY(),P55-TODAY()<=3,W55<0.5),"Amber","Green")))) -> Green | AB55: Gap: The generator has no production caller: nothing invokes issue_platform_gst_invoice on a Cashfree or PayU subscription capture (payments/services.py only comments on it). No PDF is produced and email is a notification body only. | AC55: uncommitted working tree | AD55: Tests: tests/test_plan_remaining_open.py::test_cashfree_capture_issues_one_gst_invoice_and_payu_is_idempotent [pass]; tests/test_plan_remaining_open.py::test_same_state_capture_splits_cgst_and_sgst [pass] | Code: backend/billing/platform_gst.py:issue_platform_gst_invoice; backend/billing/models.py:PlatformGstInvoice | Run: pytest on SQLite 2026-10-05 (Postgres-only tests skipped) | AE55: =IFERROR(INDEX('Task Register'!$AJ$2:$AJ$771,MATCH(B55,'Task Register'!$A$2:$A$771,0)),"") -> Built - partial | AF55: =IFERROR(INDEX('Task Register'!$AU$2:$AU$771,MATCH(B55,'Task Register'!$A$2:$A$771,0)),"") -> Partial | AG55: feature | AI55: 51 | AJ55: SaaS-0669
A56: WI-047 | B56: GOS-0721 | C56: End-to-end test: inbound lead de-duplication | D56: 2 | E56: Pilot | F56: Growth & SaaS | G56: Backend | H56: End-to-end test through the API; fixing a failing flow is in scope up to one day. | I56: Pass: End-to-end test through the API; fixing a failing flow is in scope up to one day.. Rejecting case: invalid input, a wrong-tenant request and a user without permission are each rejected, each with a test. Done means: tests for the touched apps pass on Postgres 17 with lint and type checks clean and any strict xfail for the item removed; the reviewer (not the author) signs; register_sync.py scores the test and the register row reads Built - tested / Pass; the full suite runs nightly and at the wave gate. | J56: backend/tests/test_plan_gos_0721.py | K56: WI-035 | L56: Agent 1 | M56: 1 | N56: =ROUNDUP(M56*(1+'Plan guide'!$B$6),0) -> 2 | O56: 46462 | P56: 46463 | Q56: Done | R56: Done | S56: Done | T56: In progress | U56: Done | V56: =IF(COUNTIF(Q56:U56,"Blocked")>0,"Blocked",IF(COUNTIF(Q56:U56,"Done")+COUNTIF(Q56:U56,"N/A")=5,"Done",IF(COUNTIF(Q56:U56,"Done")+COUNTIF(Q56:U56,"In progress")>0,"In progress","Not started"))) -> In progress | W56: =IF(5-COUNTIF(Q56:U56,"N/A")=0,1,COUNTIF(Q56:U56,"Done")/(5-COUNTIF(Q56:U56,"N/A"))) -> 0.8 | Z56: =IF(V56="Done",IF(Y56="",0,MAX(0,Y56-P56)),MAX(0,TODAY()-P56)) -> 0 | AA56: =IF(V56="Done","Done",IF(V56="Blocked","Red",IF(Z56>0,"Red",IF(AND(O56<=TODAY(),P56-TODAY()<=3,W56<0.5),"Amber","Green")))) -> Green | AB56: Agent review done; human sign-off pending | AC56: uncommitted working tree | AD56: Tests: tests/test_os_vision_plan.py::test_resolve_dedupe_new_clears_pending_review [pass]; tests/test_plan_remaining_open.py::test_duplicate_lead_is_matched_and_not_created_silently [pass]; tests/test_os_vision_plan.py::test_converted_lead_is_not_a_second_party_on_repeat_contact [pass] | Code: backend/crm/pipeline.py:capture_lead; backend/crm/pipeline.py:DedupePrompt | Run: pytest on SQLite 2026-10-05 (Postgres-only tests skipped) | AE56: =IFERROR(INDEX('Task Register'!$AJ$2:$AJ$771,MATCH(B56,'Task Register'!$A$2:$A$771,0)),"") -> Built - tested | AF56: =IFERROR(INDEX('Task Register'!$AU$2:$AU$771,MATCH(B56,'Task Register'!$A$2:$A$771,0)),"") -> Pass | AG56: feature | AI56: 52 | AJ56: GOS-0721
... A62: WI-053 | B62: UX-0582 | C62: Multi-cart hold and recall at POS | D62: 2 | E62: Pilot | F62: Inventory & POS | G62: Web | H62: Hold and recall several carts without losing stock reservations. Reservations use the expiry job from S-0562. | I62: Pass: Hold and recall several carts without losing stock reservations. Reservations use the expiry job from S-0562.. Rejecting case: invalid input keeps the action disabled; keyboard and screen-reader path tested. Done means: Vitest (and Playwright where there is a flow) pass, tsc -b and ESLint report zero errors, the accessibility check is clean, and register_sync.py scores the web test; the backend suite is not required; the reviewer signs. | J62: web/src/__tests__/ux_0582.test.tsx | K62: WI-051, WI-068, WI-035 | L62: Agent 1 | M62: 3 | N62: =ROUNDUP(M62*(1+'Plan guide'!$B$6),0) -> 4 | O62: 46472 | P62: 46477 | Q62: Done | R62: In progress | S62: In progress | T62: Not started | U62: Not started | V62: =IF(COUNTIF(Q62:U62,"Blocked")>0,"Blocked",IF(COUNTIF(Q62:U62,"Done")+COUNTIF(Q62:U62,"N/A")=5,"Done",IF(COUNTIF(Q62:U62,"Done")+COUNTIF(Q62:U62,"In progress")>0,"In progress","Not started"))) -> In progress | W62: =IF(5-COUNTIF(Q62:U62,"N/A")=0,1,COUNTIF(Q62:U62,"Done")/(5-COUNTIF(Q62:U62,"N/A"))) -> 0.2 | Z62: =IF(V62="Done",IF(Y62="",0,MAX(0,Y62-P62)),MAX(0,TODAY()-P62)) -> 0 | AA62: =IF(V62="Done","Done",IF(V62="Blocked","Red",IF(Z62>0,"Red",IF(AND(O62<=TODAY(),P62-TODAY()<=3,W62<0.5),"Amber","Green")))) -> Green | AB62: Gap: Multi-cart hold in the web is client-side sessionStorage only; the backend PosCartHold is not called by the web and creates no stock reservation, so reservation survival is unproven; no web/src/__tests__/ux_0582.test.tsx. | AC62: uncommitted working tree | AD62: Tests: web/src/pages/pos/PosPage.hotkeys.test.tsx (F8 and F9 hold cart and cycle between sessions) [not in run]; tests/test_planwave_finish.py::test_pos_hold_expires_and_the_row_remains [pass] | Code: web/src/pages/pos/PosPage.tsx; backend/planwave/finish.py:hold_pos_cart; backend/planwave/finish.py:release_expired_pos_holds | Run: pytest on SQLite 2026-10-05 (Postgres-only tests skipped) | AE62: =IFERROR(INDEX('Task Register'!$AJ$2:$AJ$771,MATCH(B62,'Task Register'!$A$2:$A$771,0)),"") -> Built - partial | AF62: =IFERROR(INDEX('Task Register'!$AU$2:$AU$771,MATCH(B62,'Task Register'!$A$2:$A$771,0)),"") -> Partial | AG62: web | AI62: 55 | AJ62: UX-0582
A63: WI-054 | B63: UX-0586 | C63: Ctrl+K omnibar | D63: 2 | E63: Pilot | F63: Inventory & POS | G63: Web | H63: Global command palette with search and actions. | I63: Pass: Global command palette with search and actions.. Rejecting case: invalid input keeps the action disabled; keyboard and screen-reader path tested. Done means: Vitest (and Playwright where there is a flow) pass, tsc -b and ESLint report zero errors, the accessibility check is clean, and register_sync.py scores the web test; the backend suite is not required; the reviewer signs. | J63: web/src/__tests__/ux_0586.test.tsx | K63: WI-068, WI-035 | L63: Agent 2 | M63: 2 | N63: =ROUNDUP(M63*(1+'Plan guide'!$B$6),0) -> 3 | O63: 46477 | P63: 46479 | Q63: Done | R63: In progress | S63: Not started | T63: Not started | U63: Not started | V63: =IF(COUNTIF(Q63:U63,"Blocked")>0,"Blocked",IF(COUNTIF(Q63:U63,"Done")+COUNTIF(Q63:U63,"N/A")=5,"Done",IF(COUNTIF(Q63:U63,"Done")+COUNTIF(Q63:U63,"In progress")>0,"In progress","Not started"))) -> In progress | W63: =IF(5-COUNTIF(Q63:U63,"N/A")=0,1,COUNTIF(Q63:U63,"Done")/(5-COUNTIF(Q63:U63,"N/A"))) -> 0.2 | Z63: =IF(V63="Done",IF(Y63="",0,MAX(0,Y63-P63)),MAX(0,TODAY()-P63)) -> 0 | AA63: =IF(V63="Done","Done",IF(V63="Blocked","Red",IF(Z63>0,"Red",IF(AND(O63<=TODAY(),P63-TODAY()<=3,W63<0.5),"Amber","Green")))) -> Green | AB63: Gap: Palette lists navigation routes only; no data search and no actions; no test file. | AC63: uncommitted working tree | AD63: Code: web/src/components/CommandPalette.tsx:CommandPalette; web/src/layouts/AppShell.tsx | Run: pytest on SQLite 2026-10-05 (Postgres-only tests skipped) | AE63: =IFERROR(INDEX('Task Register'!$AJ$2:$AJ$771,MATCH(B63,'Task Register'!$A$2:$A$771,0)),"") -> Built - partial | AF63: =IFERROR(INDEX('Task Register'!$AU$2:$AU$771,MATCH(B63,'Task Register'!$A$2:$A$771,0)),"") -> Not run | AG63: web | AJ63: UX-0586
A64: WI-055 | B64: UX-0588 | C64: Warehouse rack locator badge | D64: 2 | E64: Pilot | F64: Inventory & POS | G64: Web | H64: Rack or bin location on stock and picking views. | I64: Pass: Rack or bin location on stock and picking views.. Rejecting case: invalid input keeps the action disabled; keyboard and screen-reader path tested. Done means: Vitest (and Playwright where there is a flow) pass, tsc -b and ESLint report zero errors, the accessibility check is clean, and register_sync.py scores the web test; the backend suite is not required; the reviewer signs. | J64: web/src/__tests__/ux_0588.test.tsx | K64: WI-068, WI-035 | L64: Agent 1 | M64: 2 | N64: =ROUNDUP(M64*(1+'Plan guide'!$B$6),0) -> 3 | O64: 46478 | P64: 46482 | Q64: Not started | R64: Not started | S64: Not started | T64: Not started | U64: Not started | V64: =IF(COUNTIF(Q64:U64,"Blocked")>0,"Blocked",IF(COUNTIF(Q64:U64,"Done")+COUNTIF(Q64:U64,"N/A")=5,"Done",IF(COUNTIF(Q64:U64,"Done")+COUNTIF(Q64:U64,"In progress")>0,"In progress","Not started"))) -> Not started | W64: =IF(5-COUNTIF(Q64:U64,"N/A")=0,1,COUNTIF(Q64:U64,"Done")/(5-COUNTIF(Q64:U64,"N/A"))) -> 0 | Z64: =IF(V64="Done",IF(Y64="",0,MAX(0,Y64-P64)),MAX(0,TODAY()-P64)) -> 0 | AA64: =IF(V64="Done","Done",IF(V64="Blocked","Red",IF(Z64>0,"Red",IF(AND(O64<=TODAY(),P64-TODAY()<=3,W64<0.5),"Amber","Green")))) -> Green | AB64: Gap: No rack or bin location field on stock models, serializers or the stock and picking views, and no badge component. | AC64: uncommitted working tree | AD64: Run: pytest on SQLite 2026-10-05 (Postgres-only tests skipped) | AE64: =IFERROR(INDEX('Task Register'!$AJ$2:$AJ$771,MATCH(B64,'Task Register'!$A$2:$A$771,0)),"") -> Gap | AF64: =IFERROR(INDEX('Task Register'!$AU$2:$AU$771,MATCH(B64,'Task Register'!$A$2:$A$771,0)),"") -> Not run | AG64: web | AJ64: UX-0588
A65: WI-056 | B65: UX-0590 | C65: Bulk import progress bar with time remaining | D65: 2 | E65: Pilot | F65: Inventory & POS | G65: Web | H65: Progress and ETA for long imports. | I65: Pass: Progress and ETA for long imports.. Rejecting case: invalid input keeps the action disabled; keyboard and screen-reader path tested. Done means: Vitest (and Playwright where there is a flow) pass, tsc -b and ESLint report zero errors, the accessibility check is clean, and register_sync.py scores the web test; the backend suite is not required; the reviewer signs. | J65: web/src/__tests__/ux_0590.test.tsx | K65: WI-068, WI-035 | L65: Agent 2 | M65: 2 | N65: =ROUNDUP(M65*(1+'Plan guide'!$B$6),0) -> 3 | O65: 46482 | P65: 46484 | Q65: Done | R65: In progress | S65: Not started | T65: Not started | U65: Not started | V65: =IF(COUNTIF(Q65:U65,"Blocked")>0,"Blocked",IF(COUNTIF(Q65:U65,"Done")+COUNTIF(Q65:U65,"N/A")=5,"Done",IF(COUNTIF(Q65:U65,"Done")+COUNTIF(Q65:U65,"In progress")>0,"In progress","Not started"))) -> In progress | W65: =IF(5-COUNTIF(Q65:U65,"N/A")=0,1,COUNTIF(Q65:U65,"Done")/(5-COUNTIF(Q65:U65,"N/A"))) -> 0.2 | Z65: =IF(V65="Done",IF(Y65="",0,MAX(0,Y65-P65)),MAX(0,TODAY()-P65)) -> 0 | AA65: =IF(V65="Done","Done",IF(V65="Blocked","Red",IF(Z65>0,"Red",IF(AND(O65<=TODAY(),P65-TODAY()<=3,W65<0.5),"Amber","Green")))) -> Green | AB65: Gap: A progress bar with an ETA exists but is a time-based estimate (0.05 s per row), not server progress, and has no test; no ux_0590.test.tsx. | AC65: uncommitted working tree | AD65: Code: web/src/pages/settings/ImportPage.tsx | Run: pytest on SQLite 2026-10-05 (Postgres-only tests skipped) | AE65: =IFERROR(INDEX('Task Register'!$AJ$2:$AJ$771,MATCH(B65,'Task Register'!$A$2:$A$771,0)),"") -> Built - partial | AF65: =IFERROR(INDEX('Task Register'!$AU$2:$AU$771,MATCH(B65,'Task Register'!$A$2:$A$771,0)),"") -> Not run | AG65: web | AJ65: UX-0590
A66: WI-057 | B66: UX-0591 | C66: Privacy mask for rupee figures | D66: 2 | E66: Pilot | F66: Inventory & POS | G66: Web | H66: Personal on-screen toggle, separate from role masking; not a security control. | I66: Pass: Personal on-screen toggle, separate from role masking; not a security control.. Rejecting case: invalid input keeps the action disabled; keyboard and screen-reader path tested. Done means: Vitest (and Playwright where there is a flow) pass, tsc -b and ESLint report zero errors, the accessibility check is clean, and register_sync.py scores the web test; the backend suite is not required; the reviewer signs. | J66: web/src/__tests__/ux_0591.test.tsx | K66: WI-068, WI-035 | L66: Agent 1 | M66: 1 | N66: =ROUNDUP(M66*(1+'Plan guide'!$B$6),0) -> 2 | O66: 46483 | P66: 46484 | Q66: Done | R66: In progress | S66: Not started | T66: Not started | U66: Not started | V66: =IF(COUNTIF(Q66:U66,"Blocked")>0,"Blocked",IF(COUNTIF(Q66:U66,"Done")+COUNTIF(Q66:U66,"N/A")=5,"Done",IF(COUNTIF(Q66:U66,"Done")+COUNTIF(Q66:U66,"In progress")>0,"In progress","Not started"))) -> In progress | W66: =IF(5-COUNTIF(Q66:U66,"N/A")=0,1,COUNTIF(Q66:U66,"Done")/(5-COUNTIF(Q66:U66,"N/A"))) -> 0.2 | Z66: =IF(V66="Done",IF(Y66="",0,MAX(0,Y66-P66)),MAX(0,TODAY()-P66)) -> 0 | AA66: =IF(V66="Done","Done",IF(V66="Blocked","Red",IF(Z66>0,"Red",IF(AND(O66<=TODAY(),P66-TODAY()<=3,W66<0.5),"Amber","Green")))) -> Green | AB66: Gap: No test; only components using MoneyText are masked, other rupee displays may not be. | AC66: uncommitted working tree | AD66: Code: web/src/privacy/PrivacyMask.tsx:PrivacyMaskProvider; web/src/components/insights/MoneyText.tsx:MoneyText; web/src/layouts/AppShell.tsx | Run: pytest on SQLite 2026-10-05 (Postgres-only tests skipped) | AE66: =IFERROR(INDEX('Task Register'!$AJ$2:$AJ$771,MATCH(B66,'Task Register'!$A$2:$A$771,0)),"") -> Built - partial | AF66: =IFERROR(INDEX('Task Register'!$AU$2:$AU$771,MATCH(B66,'Task Register'!$A$2:$A$771,0)),"") -> Not run | AG66: web | AI66: 56 | AJ66: UX-0591
A67: WI-058 | C67: Wave 2 verification: full suite on Postgres, register sync, drift check, Pilot gate review | D67: 2 | E67: Pilot | F67: Quality gate | G67: Process | H67: Run the full backend suite on Postgres, register_sync.py and register_drift.py, recalculate the workbook and review every wave item against its pass condition. | I67: Pass: Run the full backend suite on Postgres, register_sync.py and register_drift.py, recalculate the workbook and review every wave item against its pass condition.. Rejecting case: invalid input, a wrong-tenant request and a user without permission are each rejected, each with a test. Done means: full backend suite green on Postgres, register_sync.py and register_drift.py clean, workbook recalculated with 0 formula errors, every item in the wave Done and reviewed. | K67: WI-036, WI-037, WI-038, WI-039, WI-040, WI-041, WI-042, WI-043, WI-044, WI-045, WI-046, WI-047, WI-048, WI-049, WI-050, WI-051, WI-052, WI-053, WI-054, WI-055, WI-056, WI-057 | L67: Agent 1 | M67: 2 | N67: =ROUNDUP(M67*(1+'Plan guide'!$B$6),0) -> 3 | O67: 46486 | P67: 46490 | Q67: N/A | R67: N/A | S67: Not started | T67: Not started | U67: Not started | V67: =IF(COUNTIF(Q67:U67,"Blocked")>0,"Blocked",IF(COUNTIF(Q67:U67,"Done")+COUNTIF(Q67:U67,"N/A")=5,"Done",IF(COUNTIF(Q67:U67,"Done")+COUNTIF(Q67:U67,"In progress")>0,"In progress","Not started"))) -> Not started | W67: =IF(5-COUNTIF(Q67:U67,"N/A")=0,1,COUNTIF(Q67:U67,"Done")/(5-COUNTIF(Q67:U67,"N/A"))) -> 0 | Z67: =IF(V67="Done",IF(Y67="",0,MAX(0,Y67-P67)),MAX(0,TODAY()-P67)) -> 0 | AA67: =IF(V67="Done","Done",IF(V67="Blocked","Red",IF(Z67>0,"Red",IF(AND(O67<=TODAY(),P67-TODAY()<=3,W67<0.5),"Amber","Green")))) -> Green | AB67: Gap: Tools exist, but no recorded Wave 2 full-suite-on-Postgres result, drift check output or per-item pass-condition review is stored. | AC67: uncommitted working tree | AD67: Code: qos/tools/register_sync.py; qos/tools/register_drift.py | Run: pytest on SQLite 2026-10-05 (Postgres-only tests skipped) | AG67: gate | AJ67: VER-2
A68: WI-059 | B68: D-0684 | C68: Predictive cash-flow simulation engine modeling actual debtor payment delay probabilities | D68: 3 | E68: Later | F68: Growth & SaaS | G68: Full stack | H68: Per-debtor bootstrap of days-late from the last 12 settled invoices, shrunk to the segment average, 1,000 runs, show p10/p50/p90; under 5 settled invoices fall back to the ageing heuristic with a low-confidence badge. | I68: Pass: Per-debtor bootstrap of days-late from the last 12 settled invoices, shrunk to the segment average, 1,000 runs, show p10/p50/p90; under 5 settled invoices fall back to the ageing heuristic with a low-confidence badge.. Rejecting case: invalid input, a wrong-tenant request and a user without permission are each rejected, each with a test. Done means: tests for the touched apps pass on Postgres 17 with lint and type checks clean and any strict xfail for the item removed; the reviewer (not the author) signs; register_sync.py scores the test and the register row reads Built - tested / Pass; the full suite runs nightly and at the wave gate. | J68: backend/tests/test_plan_d_0684.py | K68: WI-058 | L68: Agent 1 | M68: 10 | N68: =ROUNDUP(M68*(1+'Plan guide'!$B$6),0) -> 12 | O68: 46492 | P68: 46507 | Q68: Done | R68: In progress | S68: In progress | T68: Not started | U68: Not started | V68: =IF(COUNTIF(Q68:U68,"Blocked")>0,"Blocked",IF(COUNTIF(Q68:U68,"Done")+COUNTIF(Q68:U68,"N/A")=5,"Done",IF(COUNTIF(Q68:U68,"Done")+COUNTIF(Q68:U68,"In progress")>0,"In progress","Not started"))) -> In progress | W68: =IF(5-COUNTIF(Q68:U68,"N/A")=0,1,COUNTIF(Q68:U68,"Done")/(5-COUNTIF(Q68:U68,"N/A"))) -> 0.2 | Z68: =IF(V68="Done",IF(Y68="",0,MAX(0,Y68-P68)),MAX(0,TODAY()-P68)) -> 0 | AA68: =IF(V68="Done","Done",IF(V68="Blocked","Red",IF(Z68>0,"Red",IF(AND(O68<=TODAY(),P68-TODAY()<=3,W68<0.5),"Amber","Green")))) -> Green | AB68: Gap: The 1,000 runs cycle the sample deterministically rather than bootstrap-resampling; under 5 invoices it uses the segment average rather than the ageing heuristic; no cash-flow aggregate or UI badge; percentile values are not asserted. | AC68: uncommitted working tree | AD68: Tests: tests/test_plan_remaining_open.py::test_cashflow_uses_settled_invoices [pass]; tests/test_planwave_remaining.py::test_provision_interest_anomaly_cashflow_and_2b [pass] | Code: backend/planwave/services.py:cashflow_forecast; backend/planwave/finish.py:debtor_delays; backend/planwave/finish.py:cashflow_for_customer | Run: pytest on SQLite 2026-10-05 (Postgres-only tests skipped) | AE68: =IFERROR(INDEX('Task Register'!$AJ$2:$AJ$771,MATCH(B68,'Task Register'!$A$2:$A$771,0)),"") -> Built - partial | AF68: =IFERROR(INDEX('Task Register'!$AU$2:$AU$771,MATCH(B68,'Task Register'!$A$2:$A$771,0)),"") -> Partial | AG68: feature | AI68: 57 | AJ68: D-0684
A69: WI-060 | B69: D-0690 | C69: Automated GSTR-2B 'Smart Reconciler' with fuzzy name and fractional rounding matching | D69: 3 | E69: Later | F69: Growth & SaaS | G69: Backend | H69: Score at least 0.95 with equal GSTIN and tax within tolerance links automatically; 0.80 to 0.95 suggests; below 0.80 shows nothing. Runs on uploaded 2B data after P-0503. | I69: Pass: Score at least 0.95 with equal GSTIN and tax within tolerance links automatically; 0.80 to 0.95 suggests; below 0.80 shows nothing. Runs on uploaded 2B data after P-0503.. Rejecting case: invalid input, a wrong-tenant request and a user without permission are each rejected, each with a test. Done means: tests for the touched apps pass on Postgres 17 with lint and type checks clean and any strict xfail for the item removed; the reviewer (not the author) signs; register_sync.py scores the test and the register row reads Built - tested / Pass; the full suite runs nightly and at the wave gate. | J69: backend/tests/test_plan_d_0690.py | K69: WI-019, WI-058 | L69: Agent 2 | M69: 6 | N69: =ROUNDUP(M69*(1+'Plan guide'!$B$6),0) -> 8 | O69: 46492 | P69: 46503 | Q69: Done | R69: In progress | S69: In progress | T69: Not started | U69: Not started | V69: =IF(COUNTIF(Q69:U69,"Blocked")>0,"Blocked",IF(COUNTIF(Q69:U69,"Done")+COUNTIF(Q69:U69,"N/A")=5,"Done",IF(COUNTIF(Q69:U69,"Done")+COUNTIF(Q69:U69,"In progress")>0,"In progress","Not started"))) -> In progress | W69: =IF(5-COUNTIF(Q69:U69,"N/A")=0,1,COUNTIF(Q69:U69,"Done")/(5-COUNTIF(Q69:U69,"N/A"))) -> 0.2 | Z69: =IF(V69="Done",IF(Y69="",0,MAX(0,Y69-P69)),MAX(0,TODAY()-P69)) -> 0 | AA69: =IF(V69="Done","Done",IF(V69="Blocked","Red",IF(Z69>0,"Red",IF(AND(O69<=TODAY(),P69-TODAY()<=3,W69<0.5),"Amber","Green")))) -> Green | AB69: Gap: No numeric fuzzy name score or 0.95/0.80 thresholds (boolean GSTIN and tax-tolerance banding); nothing links automatically; it scores caller-posted rows, not uploaded 2B data. | AC69: uncommitted working tree | AD69: Tests: tests/test_planwave_remaining.py::test_provision_interest_anomaly_cashflow_and_2b [pass]; tests/test_planwave_finish.py::test_2b_blocked_invoice_is_not_eligible [pass] | Code: backend/planwave/services.py:gstr2b_score; backend/planwave/finish.py:score_2b_rows; backend/planwave/views.py:TwoBScoreView | Run: pytest on SQLite 2026-10-05 (Postgres-only tests skipped) | AE69: =IFERROR(INDEX('Task Register'!$AJ$2:$AJ$771,MATCH(B69,'Task Register'!$A$2:$A$771,0)),"") -> Built - partial | AF69: =IFERROR(INDEX('Task Register'!$AU$2:$AU$771,MATCH(B69,'Task Register'!$A$2:$A$771,0)),"") -> Partial | AG69: feature | AI69: 58 | AJ69: D-0690
A70: WI-061 | B70: D-0693 | C70: One-click complete Tally historical backup migration wizard | D70: 3 | E70: Later | F70: Growth & SaaS | G70: Full stack | H70: TallyPrime only: ledger masters, stock items, opening balances and one financial year of vouchers with a mandatory ledger and stock-item mapping step. ENABLE_TALLY stays off; flipping it is a separate freeze exception. | I70: Pass: TallyPrime only: ledger masters, stock items, opening balances and one financial year of vouchers with a mandatory ledger and stock-item mapping step. ENABLE_TALLY stays off; flipping it is a separate freeze exception.. Rejecting case: invalid input, a wrong-tenant request and a user without permission are each rejected, each with a test. Done means: tests for the touched apps pass on Postgres 17 with lint and type checks clean and any strict xfail for the item removed; the reviewer (not the author) signs; register_sync.py scores the test and the register row reads Built - tested / Pass; the full suite runs nightly and at the wave gate. | J70: backend/tests/test_plan_d_0693.py | K70: WI-058 | L70: Agent 2 | M70: 25 | N70: =ROUNDUP(M70*(1+'Plan guide'!$B$6),0) -> 30 | O70: 46504 | P70: 46545 | Q70: Done | R70: In progress | S70: In progress | T70: Not started | U70: Not started | V70: =IF(COUNTIF(Q70:U70,"Blocked")>0,"Blocked",IF(COUNTIF(Q70:U70,"Done")+COUNTIF(Q70:U70,"N/A")=5,"Done",IF(COUNTIF(Q70:U70,"Done")+COUNTIF(Q70:U70,"In progress")>0,"In progress","Not started"))) -> In progress | W70: =IF(5-COUNTIF(Q70:U70,"N/A")=0,1,COUNTIF(Q70:U70,"Done")/(5-COUNTIF(Q70:U70,"N/A"))) -> 0.2 | Z70: =IF(V70="Done",IF(Y70="",0,MAX(0,Y70-P70)),MAX(0,TODAY()-P70)) -> 0 | AA70: =IF(V70="Done","Done",IF(V70="Blocked","Red",IF(Z70>0,"Red",IF(AND(O70<=TODAY(),P70-TODAY()<=3,W70<0.5),"Amber","Green")))) -> Green | AB70: Gap: Only the mandatory ledger and stock-item mapping step and a stored job with voucher count exist. No TallyPrime backup parsing, no master or opening balance import and no voucher posting in the wizard; commit endpoint is a stub returning imported False. No wizard UI found. | AC70: uncommitted working tree | AD70: Tests: tests/test_planwave_remaining.py::test_bulk_import_and_tally_map [pass]; tests/test_plan_partials.py::test_tally_commit_stays_off [pass] | Code: backend/planwave/services.py:map_tally_import; backend/planwave/views.py:TallyMapView; backend/planwave/views.py:TallyCommitView; backend/planwave/models.py:TallyImportJob | Run: pytest on SQLite 2026-10-05 (Postgres-only tests skipped) | AE70: =IFERROR(INDEX('Task Register'!$AJ$2:$AJ$771,MATCH(B70,'Task Register'!$A$2:$A$771,0)),"") -> Built - partial | AF70: =IFERROR(INDEX('Task Register'!$AU$2:$AU$771,MATCH(B70,'Task Register'!$A$2:$A$771,0)),"") -> Partial | AG70: feature | AI70: 59 | AJ70: D-0693
A71: WI-064 | B71: S-0574 | C71: Anomaly detector for unusual discounts and bill amounts | D71: 3 | E71: Later | F71: Platform & reliability | G71: Backend | H71: Review queue only, never blocks a bill. Unusual: discount above 3 times the item's median discount, or a bill above both a rupee floor and 3 times the customer's median bill; thresholds per company. | I71: Pass: Review queue only, never blocks a bill. Unusual: discount above 3 times the item's median discount, or a bill above both a rupee floor and 3 times the customer's median bill; thresholds per company.. Rejecting case: invalid input, a wrong-tenant request and a user without permission are each rejected, each with a test. Done means: tests for the touched apps pass on Postgres 17 with lint and type checks clean and any strict xfail for the item removed; the reviewer (not the author) signs; register_sync.py scores the test and the register row reads Built - tested / Pass; the full suite runs nightly and at the wave gate. | J71: backend/tests/test_plan_s_0574.py | K71: WI-058 | L71: Agent 1 | M71: 8 | N71: =ROUNDUP(M71*(1+'Plan guide'!$B$6),0) -> 10 | O71: 46510 | P71: 46521 | Q71: Done | R71: In progress | S71: In progress | T71: Not started | U71: Not started | V71: =IF(COUNTIF(Q71:U71,"Blocked")>0,"Blocked",IF(COUNTIF(Q71:U71,"Done")+COUNTIF(Q71:U71,"N/A")=5,"Done",IF(COUNTIF(Q71:U71,"Done")+COUNTIF(Q71:U71,"In progress")>0,"In progress","Not started"))) -> In progress | W71: =IF(5-COUNTIF(Q71:U71,"N/A")=0,1,COUNTIF(Q71:U71,"Done")/(5-COUNTIF(Q71:U71,"N/A"))) -> 0.2 | Z71: =IF(V71="Done",IF(Y71="",0,MAX(0,Y71-P71)),MAX(0,TODAY()-P71)) -> 0 | AA71: =IF(V71="Done","Done",IF(V71="Blocked","Red",IF(Z71>0,"Red",IF(AND(O71<=TODAY(),P71-TODAY()<=3,W71<0.5),"Amber","Green")))) -> Green | AB71: Gap: The discount median is across all the customer's lines rather than the item's; the rupee floor is a code default, not per company; the review queue is list-only (no resolve) and has no UI; review_completed_sale and the queue endpoint are untested. | AC71: uncommitted working tree | AD71: Tests: tests/test_planwave_remaining.py::test_provision_interest_anomaly_cashflow_and_2b [pass] | Code: backend/planwave/services.py:flag_anomaly; backend/planwave/finish.py:review_completed_sale; backend/planwave/models.py:AnomalyReview; backend/planwave/views.py:AnomalyList | Run: pytest on SQLite 2026-10-05 (Postgres-only tests skipped) | AE71: =IFERROR(INDEX('Task Register'!$AJ$2:$AJ$771,MATCH(B71,'Task Register'!$A$2:$A$771,0)),"") -> Built - partial | AF71: =IFERROR(INDEX('Task Register'!$AU$2:$AU$771,MATCH(B71,'Task Register'!$A$2:$A$771,0)),"") -> Partial | AG71: feature | AI71: 61 | AJ71: S-0574
A72: WI-067 | C72: Wave 3 verification: full suite on Postgres, register sync, drift check, Later gate review | D72: 3 | E72: Later | F72: Quality gate | G72: Process | H72: Run the full backend suite on Postgres, register_sync.py and register_drift.py, recalculate the workbook and review every wave item against its pass condition. | I72: Pass: Run the full backend suite on Postgres, register_sync.py and register_drift.py, recalculate the workbook and review every wave item against its pass condition.. Rejecting case: invalid input, a wrong-tenant request and a user without permission are each rejected, each with a test. Done means: full backend suite green on Postgres, register_sync.py and register_drift.py clean, workbook recalculated with 0 formula errors, every item in the wave Done and reviewed. | K72: WI-059, WI-060, WI-061, WI-064 | L72: Agent 1 | M72: 2 | N72: =ROUNDUP(M72*(1+'Plan guide'!$B$6),0) -> 3 | O72: 46547 | P72: 46549 | Q72: N/A | R72: N/A | S72: Not started | T72: Not started | U72: Not started | V72: =IF(COUNTIF(Q72:U72,"Blocked")>0,"Blocked",IF(COUNTIF(Q72:U72,"Done")+COUNTIF(Q72:U72,"N/A")=5,"Done",IF(COUNTIF(Q72:U72,"Done")+COUNTIF(Q72:U72,"In progress")>0,"In progress","Not started"))) -> Not started | W72: =IF(5-COUNTIF(Q72:U72,"N/A")=0,1,COUNTIF(Q72:U72,"Done")/(5-COUNTIF(Q72:U72,"N/A"))) -> 0 | Z72: =IF(V72="Done",IF(Y72="",0,MAX(0,Y72-P72)),MAX(0,TODAY()-P72)) -> 0 | AA72: =IF(V72="Done","Done",IF(V72="Blocked","Red",IF(Z72>0,"Red",IF(AND(O72<=TODAY(),P72-TODAY()<=3,W72<0.5),"Amber","Green")))) -> Green | AB72: Gap: No recorded Wave 3 Postgres full-suite run, drift check result or gate review file. | AC72: uncommitted working tree | AD72: Code: qos/tools/register_sync.py; qos/tools/register_drift.py | Run: pytest on SQLite 2026-10-05 (Postgres-only tests skipped) | AG72: gate | AJ72: VER-3

Sheet Plan rollup
A1: Plan rollup
A2: Live counts from the Implementation plan sheet. Effort % weights by estimate days.
A4: Wave | B4: Items | C4: Done | D4: In progress | E4: Blocked | F4: Red | G4: Estimate days | H4: Days done | I4: Effort done % | J4: Item done %
A5: Wave 1: MVP | B5: =COUNTIF('Implementation plan'!$D$5:$D$72,1) -> 40 | C5: =COUNTIFS('Implementation plan'!$D$5:$D$72,1,'Implementation plan'!$V$5:$V$72,"Done") -> 0 | D5: =COUNTIFS('Implementation plan'!$D$5:$D$72,1,'Implementation plan'!$V$5:$V$72,"In progress") -> 35 | E5: =COUNTIFS('Implementation plan'!$D$5:$D$72,1,'Implementation plan'!$V$5:$V$72,"Blocked") -> 0 | F5: =COUNTIFS('Implementation plan'!$D$5:$D$72,1,'Implementation plan'!$AA$5:$AA$72,"Red") -> 0 | G5: =SUMIFS('Implementation plan'!$M$5:$M$72,'Implementation plan'!$D$5:$D$72,1) -> 99.5 | H5: =SUMPRODUCT(('Implementation plan'!$D$5:$D$72=1)*'Implementation plan'!$M$5:$M$72*'Implementation plan'!$W$5:$W$72) -> 32.5 | I5: =IF(G5=0,0,H5/G5) -> 0.32663317 | J5: =IF(B5=0,0,C5/B5) -> 0
A6: Wave 2: Pilot | B6: =COUNTIF('Implementation plan'!$D$5:$D$72,2) -> 23 | C6: =COUNTIFS('Implementation plan'!$D$5:$D$72,2,'Implementation plan'!$V$5:$V$72,"Done") -> 0 | D6: =COUNTIFS('Implementation plan'!$D$5:$D$72,2,'Implementation plan'!$V$5:$V$72,"In progress") -> 21 | E6: =COUNTIFS('Implementation plan'!$D$5:$D$72,2,'Implementation plan'!$V$5:$V$72,"Blocked") -> 0 | F6: =COUNTIFS('Implementation plan'!$D$5:$D$72,2,'Implementation plan'!$AA$5:$AA$72,"Red") -> 0 | G6: =SUMIFS('Implementation plan'!$M$5:$M$72,'Implementation plan'!$D$5:$D$72,2) -> 62 | H6: =SUMPRODUCT(('Implementation plan'!$D$5:$D$72=2)*'Implementation plan'!$M$5:$M$72*'Implementation plan'!$W$5:$W$72) -> 18 | I6: =IF(G6=0,0,H6/G6) -> 0.29032258 | J6: =IF(B6=0,0,C6/B6) -> 0
A7: Wave 3: Later | B7: =COUNTIF('Implementation plan'!$D$5:$D$72,3) -> 5 | C7: =COUNTIFS('Implementation plan'!$D$5:$D$72,3,'Implementation plan'!$V$5:$V$72,"Done") -> 0 | D7: =COUNTIFS('Implementation plan'!$D$5:$D$72,3,'Implementation plan'!$V$5:$V$72,"In progress") -> 4 | E7: =COUNTIFS('Implementation plan'!$D$5:$D$72,3,'Implementation plan'!$V$5:$V$72,"Blocked") -> 0 | F7: =COUNTIFS('Implementation plan'!$D$5:$D$72,3,'Implementation plan'!$AA$5:$AA$72,"Red") -> 0 | G7: =SUMIFS('Implementation plan'!$M$5:$M$72,'Implementation plan'!$D$5:$D$72,3) -> 51 | H7: =SUMPRODUCT(('Implementation plan'!$D$5:$D$72=3)*'Implementation plan'!$M$5:$M$72*'Implementation plan'!$W$5:$W$72) -> 9.8 | I7: =IF(G7=0,0,H7/G7) -> 0.19215686 | J7: =IF(B7=0,0,C7/B7) -> 0
A8: Total | B8: =SUM(B5:B7) -> 68 | C8: =SUM(C5:C7) -> 0 | D8: =SUM(D5:D7) -> 60 | E8: =SUM(E5:E7) -> 0 | F8: =SUM(F5:F7) -> 0 | G8: =SUM(G5:G7) -> 212.5 | H8: =SUM(H5:H7) -> 60.3 | I8: =IF(G8=0,0,H8/G8) -> 0.28376471 | J8: =IF(B8=0,0,C8/B8) -> 0
A10: Workstream | B10: Items | C10: Done | D10: In progress | E10: Blocked | F10: Red | G10: Estimate days | H10: Days done | I10: Effort done % | J10: Item done %
A11: Audit & integrity | B11: =COUNTIF('Implementation plan'!$F$5:$F$72,"Audit & integrity") -> 9 | C11: =COUNTIFS('Implementation plan'!$F$5:$F$72,"Audit & integrity",'Implementation plan'!$V$5:$V$72,"Done") -> 0 | D11: =COUNTIFS('Implementation plan'!$F$5:$F$72,"Audit & integrity",'Implementation plan'!$V$5:$V$72,"In progress") -> 8 | E11: =COUNTIFS('Implementation plan'!$F$5:$F$72,"Audit & integrity",'Implementation plan'!$V$5:$V$72,"Blocked") -> 0 | F11: =COUNTIFS('Implementation plan'!$F$5:$F$72,"Audit & integrity",'Implementation plan'!$AA$5:$AA$72,"Red") -> 0 | G11: =SUMIFS('Implementation plan'!$M$5:$M$72,'Implementation plan'!$F$5:$F$72,"Audit & integrity") -> 17 | H11: =SUMPRODUCT(('Implementation plan'!$F$5:$F$72="Audit & integrity")*'Implementation plan'!$M$5:$M$72*'Implementation plan'!$W$5:$W$72) -> 5.4 | I11: =IF(G11=0,0,H11/G11) -> 0.31764706 | J11: =IF(B11=0,0,C11/B11) -> 0
A12: Security | B12: =COUNTIF('Implementation plan'!$F$5:$F$72,"Security") -> 6 | C12: =COUNTIFS('Implementation plan'!$F$5:$F$72,"Security",'Implementation plan'!$V$5:$V$72,"Done") -> 0 | D12: =COUNTIFS('Implementation plan'!$F$5:$F$72,"Security",'Implementation plan'!$V$5:$V$72,"In progress") -> 6 | E12: =COUNTIFS('Implementation plan'!$F$5:$F$72,"Security",'Implementation plan'!$V$5:$V$72,"Blocked") -> 0 | F12: =COUNTIFS('Implementation plan'!$F$5:$F$72,"Security",'Implementation plan'!$AA$5:$AA$72,"Red") -> 0 | G12: =SUMIFS('Implementation plan'!$M$5:$M$72,'Implementation plan'!$F$5:$F$72,"Security") -> 16 | H12: =SUMPRODUCT(('Implementation plan'!$F$5:$F$72="Security")*'Implementation plan'!$M$5:$M$72*'Implementation plan'!$W$5:$W$72) -> 7.4 | I12: =IF(G12=0,0,H12/G12) -> 0.4625 | J12: =IF(B12=0,0,C12/B12) -> 0
A13: GST & compliance | B13: =COUNTIF('Implementation plan'!$F$5:$F$72,"GST & compliance") -> 12 | C13: =COUNTIFS('Implementation plan'!$F$5:$F$72,"GST & compliance",'Implementation plan'!$V$5:$V$72,"Done") -> 0 | D13: =COUNTIFS('Implementation plan'!$F$5:$F$72,"GST & compliance",'Implementation plan'!$V$5:$V$72,"In progress") -> 11 | E13: =COUNTIFS('Implementation plan'!$F$5:$F$72,"GST & compliance",'Implementation plan'!$V$5:$V$72,"Blocked") -> 0 | F13: =COUNTIFS('Implementation plan'!$F$5:$F$72,"GST & compliance",'Implementation plan'!$AA$5:$AA$72,"Red") -> 0 | G13: =SUMIFS('Implementation plan'!$M$5:$M$72,'Implementation plan'!$F$5:$F$72,"GST & compliance") -> 34.5 | H13: =SUMPRODUCT(('Implementation plan'!$F$5:$F$72="GST & compliance")*'Implementation plan'!$M$5:$M$72*'Implementation plan'!$W$5:$W$72) -> 12.2 | I13: =IF(G13=0,0,H13/G13) -> 0.35362319 | J13: =IF(B13=0,0,C13/B13) -> 0
A14: Payments & credit | B14: =COUNTIF('Implementation plan'!$F$5:$F$72,"Payments & credit") -> 8 | C14: =COUNTIFS('Implementation plan'!$F$5:$F$72,"Payments & credit",'Implementation plan'!$V$5:$V$72,"Done") -> 0 | D14: =COUNTIFS('Implementation plan'!$F$5:$F$72,"Payments & credit",'Implementation plan'!$V$5:$V$72,"In progress") -> 8 | E14: =COUNTIFS('Implementation plan'!$F$5:$F$72,"Payments & credit",'Implementation plan'!$V$5:$V$72,"Blocked") -> 0 | F14: =COUNTIFS('Implementation plan'!$F$5:$F$72,"Payments & credit",'Implementation plan'!$AA$5:$AA$72,"Red") -> 0 | G14: =SUMIFS('Implementation plan'!$M$5:$M$72,'Implementation plan'!$F$5:$F$72,"Payments & credit") -> 24 | H14: =SUMPRODUCT(('Implementation plan'!$F$5:$F$72="Payments & credit")*'Implementation plan'!$M$5:$M$72*'Implementation plan'!$W$5:$W$72) -> 9 | I14: =IF(G14=0,0,H14/G14) -> 0.375 | J14: =IF(B14=0,0,C14/B14) -> 0
A15: Inventory & POS | B15: =COUNTIF('Implementation plan'!$F$5:$F$72,"Inventory & POS") -> 17 | C15: =COUNTIFS('Implementation plan'!$F$5:$F$72,"Inventory & POS",'Implementation plan'!$V$5:$V$72,"Done") -> 0 | D15: =COUNTIFS('Implementation plan'!$F$5:$F$72,"Inventory & POS",'Implementation plan'!$V$5:$V$72,"In progress") -> 15 | E15: =COUNTIFS('Implementation plan'!$F$5:$F$72,"Inventory & POS",'Implementation plan'!$V$5:$V$72,"Blocked") -> 0 | F15: =COUNTIFS('Implementation plan'!$F$5:$F$72,"Inventory & POS",'Implementation plan'!$AA$5:$AA$72,"Red") -> 0 | G15: =SUMIFS('Implementation plan'!$M$5:$M$72,'Implementation plan'!$F$5:$F$72,"Inventory & POS") -> 50 | H15: =SUMPRODUCT(('Implementation plan'!$F$5:$F$72="Inventory & POS")*'Implementation plan'!$M$5:$M$72*'Implementation plan'!$W$5:$W$72) -> 12.6 | I15: =IF(G15=0,0,H15/G15) -> 0.252 | J15: =IF(B15=0,0,C15/B15) -> 0
A16: Platform & reliability | B16: =COUNTIF('Implementation plan'!$F$5:$F$72,"Platform & reliability") -> 5 | C16: =COUNTIFS('Implementation plan'!$F$5:$F$72,"Platform & reliability",'Implementation plan'!$V$5:$V$72,"Done") -> 0 | D16: =COUNTIFS('Implementation plan'!$F$5:$F$72,"Platform & reliability",'Implementation plan'!$V$5:$V$72,"In progress") -> 4 | E16: =COUNTIFS('Implementation plan'!$F$5:$F$72,"Platform & reliability",'Implementation plan'!$V$5:$V$72,"Blocked") -> 0 | F16: =COUNTIFS('Implementation plan'!$F$5:$F$72,"Platform & reliability",'Implementation plan'!$AA$5:$AA$72,"Red") -> 0 | G16: =SUMIFS('Implementation plan'!$M$5:$M$72,'Implementation plan'!$F$5:$F$72,"Platform & reliability") -> 13 | H16: =SUMPRODUCT(('Implementation plan'!$F$5:$F$72="Platform & reliability")*'Implementation plan'!$M$5:$M$72*'Implementation plan'!$W$5:$W$72) -> 2.7 | I16: =IF(G16=0,0,H16/G16) -> 0.20769231 | J16: =IF(B16=0,0,C16/B16) -> 0
A17: Growth & SaaS | B17: =COUNTIF('Implementation plan'!$F$5:$F$72,"Growth & SaaS") -> 8 | C17: =COUNTIFS('Implementation plan'!$F$5:$F$72,"Growth & SaaS",'Implementation plan'!$V$5:$V$72,"Done") -> 0 | D17: =COUNTIFS('Implementation plan'!$F$5:$F$72,"Growth & SaaS",'Implementation plan'!$V$5:$V$72,"In progress") -> 8 | E17: =COUNTIFS('Implementation plan'!$F$5:$F$72,"Growth & SaaS",'Implementation plan'!$V$5:$V$72,"Blocked") -> 0 | F17: =COUNTIFS('Implementation plan'!$F$5:$F$72,"Growth & SaaS",'Implementation plan'!$AA$5:$AA$72,"Red") -> 0 | G17: =SUMIFS('Implementation plan'!$M$5:$M$72,'Implementation plan'!$F$5:$F$72,"Growth & SaaS") -> 52 | H17: =SUMPRODUCT(('Implementation plan'!$F$5:$F$72="Growth & SaaS")*'Implementation plan'!$M$5:$M$72*'Implementation plan'!$W$5:$W$72) -> 11 | I17: =IF(G17=0,0,H17/G17) -> 0.21153846 | J17: =IF(B17=0,0,C17/B17) -> 0
A18: Quality gate | B18: =COUNTIF('Implementation plan'!$F$5:$F$72,"Quality gate") -> 3 | C18: =COUNTIFS('Implementation plan'!$F$5:$F$72,"Quality gate",'Implementation plan'!$V$5:$V$72,"Done") -> 0 | D18: =COUNTIFS('Implementation plan'!$F$5:$F$72,"Quality gate",'Implementation plan'!$V$5:$V$72,"In progress") -> 0 | E18: =COUNTIFS('Implementation plan'!$F$5:$F$72,"Quality gate",'Implementation plan'!$V$5:$V$72,"Blocked") -> 0 | F18: =COUNTIFS('Implementation plan'!$F$5:$F$72,"Quality gate",'Implementation plan'!$AA$5:$AA$72,"Red") -> 0 | G18: =SUMIFS('Implementation plan'!$M$5:$M$72,'Implementation plan'!$F$5:$F$72,"Quality gate") -> 6 | H18: =SUMPRODUCT(('Implementation plan'!$F$5:$F$72="Quality gate")*'Implementation plan'!$M$5:$M$72*'Implementation plan'!$W$5:$W$72) -> 0 | I18: =IF(G18=0,0,H18/G18) -> 0 | J18: =IF(B18=0,0,C18/B18) -> 0
A19: Total | B19: =SUM(B11:B18) -> 68 | C19: =SUM(C11:C18) -> 0 | D19: =SUM(D11:D18) -> 60 | E19: =SUM(E11:E18) -> 0 | F19: =SUM(F11:F18) -> 0 | G19: =SUM(G11:G18) -> 212.5 | H19: =SUM(H11:H18) -> 60.3 | I19: =IF(G19=0,0,H19/G19) -> 0.28376471 | J19: =IF(B19=0,0,C19/B19) -> 0
A21: Owner | B21: Items | C21: Done | D21: In progress | E21: Blocked | F21: Red | G21: Estimate days | H21: Days done | I21: Effort done % | J21: Item done %
A22: Agent 1 | B22: =COUNTIF('Implementation plan'!$L$5:$L$72,"Agent 1") -> 34 | C22: =COUNTIFS('Implementation plan'!$L$5:$L$72,"Agent 1",'Implementation plan'!$V$5:$V$72,"Done") -> 0 | D22: =COUNTIFS('Implementation plan'!$L$5:$L$72,"Agent 1",'Implementation plan'!$V$5:$V$72,"In progress") -> 30 | E22: =COUNTIFS('Implementation plan'!$L$5:$L$72,"Agent 1",'Implementation plan'!$V$5:$V$72,"Blocked") -> 0 | F22: =COUNTIFS('Implementation plan'!$L$5:$L$72,"Agent 1",'Implementation plan'!$AA$5:$AA$72,"Red") -> 0 | G22: =SUMIFS('Implementation plan'!$M$5:$M$72,'Implementation plan'!$L$5:$L$72,"Agent 1") -> 92.5 | H22: =SUMPRODUCT(('Implementation plan'!$L$5:$L$72="Agent 1")*'Implementation plan'!$M$5:$M$72*'Implementation plan'!$W$5:$W$72) -> 28.5 | I22: =IF(G22=0,0,H22/G22) -> 0.30810811 | J22: =IF(B22=0,0,C22/B22) -> 0
